[
  {
    "createdAt": 1668548055883,
    "updatedAt": 1668548055883,
    "deletedAt": 0,
    "createdFirstAt": 1668548055883,
    "name": "Authorization",
    "slug": "authorization",
    "type": "type",
    "hasGeneric": false,
    "module": "auth-types",
    "isModuleResolved": true,
    "comments": [],
    "operationRelativeTypescriptFilePath": "src/FunctionContext.ts",
    "classification": "operation",
    "isAbsolute": true,
    "isModuleFromMonorepo": true,
    "id": "vozmvwzvtbiqwlvriczprwin"
  },
  {
    "createdAt": 1668548055883,
    "updatedAt": 1668548055883,
    "deletedAt": 0,
    "createdFirstAt": 1668548055883,
    "name": "TsFunction",
    "slug": "ts-function",
    "type": "type",
    "hasGeneric": false,
    "module": "code-types",
    "isModuleResolved": true,
    "comments": [],
    "operationRelativeTypescriptFilePath": "src/FunctionContext.ts",
    "classification": "operation",
    "isAbsolute": true,
    "isModuleFromMonorepo": true,
    "id": "vbeunifrphufhxghzlvfhomm"
  },
  {
    "createdAt": 1668548055883,
    "updatedAt": 1668548055883,
    "deletedAt": 0,
    "createdFirstAt": 1668548055883,
    "name": "Group",
    "slug": "group",
    "type": "type",
    "hasGeneric": false,
    "module": "peer-types",
    "isModuleResolved": true,
    "comments": [],
    "operationRelativeTypescriptFilePath": "src/FunctionContext.ts",
    "classification": "operation",
    "isAbsolute": true,
    "isModuleFromMonorepo": true,
    "id": "oexygpwnkcenygxelayusxxb"
  },
  {
    "createdAt": 1668548055883,
    "updatedAt": 1668548055883,
    "deletedAt": 0,
    "createdFirstAt": 1668548055883,
    "name": "Device",
    "slug": "device",
    "type": "type",
    "hasGeneric": false,
    "module": "peer-types",
    "isModuleResolved": true,
    "comments": [],
    "operationRelativeTypescriptFilePath": "src/FunctionContext.ts",
    "classification": "operation",
    "isAbsolute": true,
    "isModuleFromMonorepo": true,
    "id": "nsoutstuuzbtdaagrcrcsdgg"
  },
  {
    "createdAt": 1668548055883,
    "updatedAt": 1668548055883,
    "deletedAt": 0,
    "createdFirstAt": 1668548055883,
    "name": "Context",
    "slug": "context",
    "module": "server/typings/common",
    "isModuleResolved": true,
    "comments": [],
    "operationRelativeTypescriptFilePath": "src/FunctionContext.ts",
    "classification": "package",
    "isAbsolute": true,
    "isModuleFromMonorepo": false,
    "id": "zlxfizxownqujgavvgyewqtq"
  }
]