[
  {
    "createdAt": 1670527667969,
    "updatedAt": 1670527667969,
    "deletedAt": 0,
    "createdFirstAt": 1670527667969,
    "name": "api",
    "slug": "api",
    "type": "value",
    "module": "api",
    "isModuleResolved": true,
    "comments": [],
    "operationRelativeTypescriptFilePath": "src/EditWriterInput.tsx",
    "classification": "operation",
    "isAbsolute": true,
    "isModuleFromMonorepo": true,
    "id": "ddzxarxxuidocdnhstcaobmw"
  },
  {
    "createdAt": 1670527667969,
    "updatedAt": 1670527667969,
    "deletedAt": 0,
    "createdFirstAt": 1670527667969,
    "name": "queries",
    "slug": "queries",
    "type": "value",
    "module": "api",
    "isModuleResolved": true,
    "comments": [],
    "operationRelativeTypescriptFilePath": "src/EditWriterInput.tsx",
    "classification": "operation",
    "isAbsolute": true,
    "isModuleFromMonorepo": true,
    "id": "ivzebvpuylnfvhwzrglyqsrg"
  },
  {
    "createdAt": 1670527667970,
    "updatedAt": 1670527667970,
    "deletedAt": 0,
    "createdFirstAt": 1670527667970,
    "name": "ClickableIcon",
    "slug": "clickable-icon",
    "type": "value",
    "module": "clickable-icon",
    "isModuleResolved": true,
    "comments": [],
    "operationRelativeTypescriptFilePath": "src/EditWriterInput.tsx",
    "classification": "operation",
    "isAbsolute": true,
    "isModuleFromMonorepo": true,
    "id": "jqtjoydlrqofqoqotsztdyap"
  },
  {
    "createdAt": 1670527667970,
    "updatedAt": 1670527667970,
    "deletedAt": 0,
    "createdFirstAt": 1670527667970,
    "name": "errorToast",
    "slug": "error-toast",
    "type": "value",
    "module": "cool-toast",
    "isModuleResolved": true,
    "comments": [],
    "operationRelativeTypescriptFilePath": "src/EditWriterInput.tsx",
    "classification": "operation",
    "isAbsolute": true,
    "isModuleFromMonorepo": true,
    "id": "qpmniphtnnlmxbcgfpdbmdtm"
  },
  {
    "createdAt": 1670527667970,
    "updatedAt": 1670527667970,
    "deletedAt": 0,
    "createdFirstAt": 1670527667970,
    "name": "getFileTypeFromPath",
    "slug": "get-file-type-from-path",
    "type": "value",
    "module": "filename-conventions",
    "isModuleResolved": true,
    "comments": [],
    "operationRelativeTypescriptFilePath": "src/EditWriterInput.tsx",
    "classification": "operation",
    "isAbsolute": true,
    "isModuleFromMonorepo": true,
    "id": "kelhzhudxslettxbznemnyym"
  },
  {
    "createdAt": 1670527667970,
    "updatedAt": 1670527667970,
    "deletedAt": 0,
    "createdFirstAt": 1670527667970,
    "name": "getFileOrFolderName",
    "slug": "get-file-or-folder-name",
    "type": "value",
    "module": "fs-util-js",
    "isModuleResolved": true,
    "comments": [],
    "operationRelativeTypescriptFilePath": "src/EditWriterInput.tsx",
    "classification": "operation",
    "isAbsolute": true,
    "isModuleFromMonorepo": true,
    "id": "uoypdcscxnmpkgfwwmbajsox"
  },
  {
    "createdAt": 1670527667971,
    "updatedAt": 1670527667971,
    "deletedAt": 0,
    "createdFirstAt": 1670527667971,
    "name": "FilePromptSelect",
    "slug": "file-prompt-select",
    "type": "value",
    "module": "prompt-components",
    "isModuleResolved": true,
    "comments": [],
    "operationRelativeTypescriptFilePath": "src/EditWriterInput.tsx",
    "classification": "operation",
    "isAbsolute": true,
    "isModuleFromMonorepo": true,
    "id": "asdbapajwpssuylsyvvepauq"
  },
  {
    "createdAt": 1670527667971,
    "updatedAt": 1670527667971,
    "deletedAt": 0,
    "createdFirstAt": 1670527667971,
    "name": "useState",
    "slug": "use-state",
    "module": "react",
    "isModuleResolved": true,
    "comments": [],
    "operationRelativeTypescriptFilePath": "src/EditWriterInput.tsx",
    "classification": "react",
    "isAbsolute": true,
    "isModuleFromMonorepo": false,
    "id": "hmlffwpqiuqgmmlqkvwqkgko"
  },
  {
    "createdAt": 1670527667971,
    "updatedAt": 1670527667971,
    "deletedAt": 0,
    "createdFirstAt": 1670527667971,
    "name": "Div",
    "slug": "div",
    "type": "value",
    "module": "react-with-native",
    "isModuleResolved": true,
    "comments": [],
    "operationRelativeTypescriptFilePath": "src/EditWriterInput.tsx",
    "classification": "operation",
    "isAbsolute": true,
    "isModuleFromMonorepo": true,
    "id": "beovrvwgwwnbxznnttrmndmj"
  },
  {
    "createdAt": 1670527667971,
    "updatedAt": 1670527667971,
    "deletedAt": 0,
    "createdFirstAt": 1670527667971,
    "name": "DbModels",
    "slug": "db-models",
    "type": "type",
    "hasGeneric": false,
    "module": "sdk-db",
    "isModuleResolved": true,
    "comments": [],
    "operationRelativeTypescriptFilePath": "src/EditWriterInput.tsx",
    "classification": "operation",
    "isAbsolute": true,
    "isModuleFromMonorepo": true,
    "id": "hzquiuadiekcbtqvyjkpkjud"
  },
  {
    "createdAt": 1670527667971,
    "updatedAt": 1670527667971,
    "deletedAt": 0,
    "createdFirstAt": 1670527667971,
    "name": "ContextTextArea",
    "slug": "context-text-area",
    "module": "./old/ContextTextArea",
    "isModuleResolved": true,
    "comments": [],
    "operationRelativeTypescriptFilePath": "src/EditWriterInput.tsx",
    "classification": "internal",
    "isAbsolute": false,
    "isModuleFromMonorepo": false,
    "id": "apshudmvbhrfoumujsmmbwrf"
  },
  {
    "createdAt": 1670527667972,
    "updatedAt": 1670527667972,
    "deletedAt": 0,
    "createdFirstAt": 1670527667972,
    "name": "api",
    "slug": "api",
    "type": "value",
    "module": "api",
    "isModuleResolved": true,
    "comments": [],
    "operationRelativeTypescriptFilePath": "src/FrontmatterForm.tsx",
    "classification": "operation",
    "isAbsolute": true,
    "isModuleFromMonorepo": true,
    "id": "fssobxtqktddacpiblucuekl"
  },
  {
    "createdAt": 1670527667972,
    "updatedAt": 1670527667972,
    "deletedAt": 0,
    "createdFirstAt": 1670527667972,
    "name": "findAssetParametersRecursively",
    "slug": "find-asset-parameters-recursively",
    "type": "value",
    "module": "asset-functions-js",
    "isModuleResolved": true,
    "comments": [],
    "operationRelativeTypescriptFilePath": "src/FrontmatterForm.tsx",
    "classification": "operation",
    "isAbsolute": true,
    "isModuleFromMonorepo": true,
    "id": "qxujxxwgtmugrfzdoxtjwpfh"
  },
  {
    "createdAt": 1670527667972,
    "updatedAt": 1670527667972,
    "deletedAt": 0,
    "createdFirstAt": 1670527667972,
    "name": "BackendAsset",
    "slug": "backend-asset",
    "type": "type",
    "hasGeneric": false,
    "module": "asset-type",
    "isModuleResolved": true,
    "comments": [],
    "operationRelativeTypescriptFilePath": "src/FrontmatterForm.tsx",
    "classification": "operation",
    "isAbsolute": true,
    "isModuleFromMonorepo": true,
    "id": "voppdxvieteklhdvsvlvtfsa"
  },
  {
    "createdAt": 1670527667972,
    "updatedAt": 1670527667972,
    "deletedAt": 0,
    "createdFirstAt": 1670527667972,
    "name": "SimplifiedSchema",
    "slug": "simplified-schema",
    "type": "type",
    "hasGeneric": false,
    "module": "code-types",
    "isModuleResolved": true,
    "comments": [],
    "operationRelativeTypescriptFilePath": "src/FrontmatterForm.tsx",
    "classification": "operation",
    "isAbsolute": true,
    "isModuleFromMonorepo": true,
    "id": "rvlzcstepmojkadhbjjbgkle"
  },
  {
    "createdAt": 1670527667972,
    "updatedAt": 1670527667972,
    "deletedAt": 0,
    "createdFirstAt": 1670527667972,
    "name": "frontmatterToObject",
    "slug": "frontmatter-to-object",
    "type": "value",
    "module": "frontmatter-util",
    "isModuleResolved": true,
    "comments": [],
    "operationRelativeTypescriptFilePath": "src/FrontmatterForm.tsx",
    "classification": "operation",
    "isAbsolute": true,
    "isModuleFromMonorepo": true,
    "id": "gvtgqfbucyeesdmfkwicosss"
  },
  {
    "createdAt": 1670527667972,
    "updatedAt": 1670527667972,
    "deletedAt": 0,
    "createdFirstAt": 1670527667972,
    "name": "objectToFrontmatter",
    "slug": "object-to-frontmatter",
    "type": "value",
    "module": "frontmatter-util",
    "isModuleResolved": true,
    "comments": [],
    "operationRelativeTypescriptFilePath": "src/FrontmatterForm.tsx",
    "classification": "operation",
    "isAbsolute": true,
    "isModuleFromMonorepo": true,
    "id": "lpppamzfpugulyznewmwbuoe"
  },
  {
    "createdAt": 1670527667972,
    "updatedAt": 1670527667972,
    "deletedAt": 0,
    "createdFirstAt": 1670527667972,
    "name": "makeArray",
    "slug": "make-array",
    "type": "value",
    "module": "js-util",
    "isModuleResolved": true,
    "comments": [],
    "operationRelativeTypescriptFilePath": "src/FrontmatterForm.tsx",
    "classification": "operation",
    "isAbsolute": true,
    "isModuleFromMonorepo": true,
    "id": "xsacfziwlcklbhchsvqmqcme"
  },
  {
    "createdAt": 1670527667973,
    "updatedAt": 1670527667973,
    "deletedAt": 0,
    "createdFirstAt": 1670527667973,
    "name": "takeFirst",
    "slug": "take-first",
    "type": "value",
    "module": "js-util",
    "isModuleResolved": true,
    "comments": [],
    "operationRelativeTypescriptFilePath": "src/FrontmatterForm.tsx",
    "classification": "operation",
    "isAbsolute": true,
    "isModuleFromMonorepo": true,
    "id": "xecgwspktgxsvmydzwjmqluw"
  },
  {
    "createdAt": 1670527667973,
    "updatedAt": 1670527667973,
    "deletedAt": 0,
    "createdFirstAt": 1670527667973,
    "name": "markdownParseToMarkdownString",
    "slug": "markdown-parse-to-markdown-string",
    "type": "value",
    "module": "markdown-parse-js",
    "isModuleResolved": true,
    "comments": [],
    "operationRelativeTypescriptFilePath": "src/FrontmatterForm.tsx",
    "classification": "operation",
    "isAbsolute": true,
    "isModuleFromMonorepo": true,
    "id": "ypwyocftgrpschrkepsfsgmb"
  },
  {
    "createdAt": 1670527667973,
    "updatedAt": 1670527667973,
    "deletedAt": 0,
    "createdFirstAt": 1670527667973,
    "name": "MarkdownParse",
    "slug": "markdown-parse",
    "type": "type",
    "hasGeneric": false,
    "module": "markdown-types",
    "isModuleResolved": true,
    "comments": [],
    "operationRelativeTypescriptFilePath": "src/FrontmatterForm.tsx",
    "classification": "operation",
    "isAbsolute": true,
    "isModuleFromMonorepo": true,
    "id": "txgdkdabudohhkaaqzchmvaw"
  },
  {
    "createdAt": 1670527667973,
    "updatedAt": 1670527667973,
    "deletedAt": 0,
    "createdFirstAt": 1670527667973,
    "name": "Frontmatter",
    "slug": "frontmatter",
    "type": "type",
    "hasGeneric": false,
    "module": "matter-types",
    "isModuleResolved": true,
    "comments": [],
    "operationRelativeTypescriptFilePath": "src/FrontmatterForm.tsx",
    "classification": "operation",
    "isAbsolute": true,
    "isModuleFromMonorepo": true,
    "id": "dhzxqlyisglehqszksdygcdy"
  },
  {
    "createdAt": 1670527667973,
    "updatedAt": 1670527667973,
    "deletedAt": 0,
    "createdFirstAt": 1670527667973,
    "name": "useState",
    "slug": "use-state",
    "module": "react",
    "isModuleResolved": true,
    "comments": [],
    "operationRelativeTypescriptFilePath": "src/FrontmatterForm.tsx",
    "classification": "react",
    "isAbsolute": true,
    "isModuleFromMonorepo": false,
    "id": "pnoxhddmsafgvxybnifhkrdx"
  },
  {
    "createdAt": 1670527667973,
    "updatedAt": 1670527667973,
    "deletedAt": 0,
    "createdFirstAt": 1670527667973,
    "name": "SimplifiedSchemaForm",
    "slug": "simplified-schema-form",
    "type": "value",
    "module": "simplified-schema-form",
    "isModuleResolved": true,
    "comments": [],
    "operationRelativeTypescriptFilePath": "src/FrontmatterForm.tsx",
    "classification": "operation",
    "isAbsolute": true,
    "isModuleFromMonorepo": true,
    "id": "bhtzoqwndrwixcbwhcwfluxe"
  },
  {
    "createdAt": 1670527667973,
    "updatedAt": 1670527667973,
    "deletedAt": 0,
    "createdFirstAt": 1670527667973,
    "name": "useReferencableModelData",
    "slug": "use-referencable-model-data",
    "type": "value",
    "module": "simplified-schema-form",
    "isModuleResolved": true,
    "comments": [],
    "operationRelativeTypescriptFilePath": "src/FrontmatterForm.tsx",
    "classification": "operation",
    "isAbsolute": true,
    "isModuleFromMonorepo": true,
    "id": "ldsqggssmmubmagcvqtnftns"
  },
  {
    "createdAt": 1670527667974,
    "updatedAt": 1670527667974,
    "deletedAt": 0,
    "createdFirstAt": 1670527667974,
    "name": "useState",
    "slug": "use-state",
    "module": "react",
    "isModuleResolved": true,
    "comments": [],
    "operationRelativeTypescriptFilePath": "src/MarkdownParsePresentation.tsx",
    "classification": "react",
    "isAbsolute": true,
    "isModuleFromMonorepo": false,
    "id": "olurduzigshddvjutgdzgyve"
  },
  {
    "createdAt": 1670527667974,
    "updatedAt": 1670527667974,
    "deletedAt": 0,
    "createdFirstAt": 1670527667974,
    "name": "Div",
    "slug": "div",
    "type": "value",
    "module": "react-with-native",
    "isModuleResolved": true,
    "comments": [],
    "operationRelativeTypescriptFilePath": "src/MarkdownParsePresentation.tsx",
    "classification": "operation",
    "isAbsolute": true,
    "isModuleFromMonorepo": true,
    "id": "fmkmlxmmcrfbugmuzniobruh"
  },
  {
    "createdAt": 1670527667974,
    "updatedAt": 1670527667974,
    "deletedAt": 0,
    "createdFirstAt": 1670527667974,
    "name": "P",
    "slug": "p",
    "type": "value",
    "module": "react-with-native",
    "isModuleResolved": true,
    "comments": [],
    "operationRelativeTypescriptFilePath": "src/MarkdownParsePresentation.tsx",
    "classification": "operation",
    "isAbsolute": true,
    "isModuleFromMonorepo": true,
    "id": "tvenpnjberqfeygffllsqdza"
  },
  {
    "createdAt": 1670527667974,
    "updatedAt": 1670527667974,
    "deletedAt": 0,
    "createdFirstAt": 1670527667974,
    "name": "isDev",
    "slug": "is-dev",
    "type": "value",
    "module": "server-api-url",
    "isModuleResolved": true,
    "comments": [],
    "operationRelativeTypescriptFilePath": "src/MarkdownParsePresentation.tsx",
    "classification": "operation",
    "isAbsolute": true,
    "isModuleFromMonorepo": true,
    "id": "obyepwiwhnlzwrjnkczpvqvv"
  },
  {
    "createdAt": 1670527667974,
    "updatedAt": 1670527667974,
    "deletedAt": 0,
    "createdFirstAt": 1670527667974,
    "name": "MarkdownParse",
    "slug": "markdown-parse",
    "type": "type",
    "hasGeneric": false,
    "module": "markdown-types",
    "isModuleResolved": true,
    "comments": [],
    "operationRelativeTypescriptFilePath": "src/MarkdownParsePresentation.tsx",
    "classification": "operation",
    "isAbsolute": true,
    "isModuleFromMonorepo": true,
    "id": "wkvrclrheyuevsqzdqwdruqh"
  },
  {
    "createdAt": 1670527667974,
    "updatedAt": 1670527667974,
    "deletedAt": 0,
    "createdFirstAt": 1670527667974,
    "name": "renderMarkdownContent",
    "slug": "render-markdown-content",
    "type": "value",
    "module": "markdown",
    "isModuleResolved": true,
    "comments": [],
    "operationRelativeTypescriptFilePath": "src/MarkdownParsePresentation.tsx",
    "classification": "operation",
    "isAbsolute": true,
    "isModuleFromMonorepo": true,
    "id": "oaxknrfklnsheeoowvrywnnx"
  },
  {
    "createdAt": 1670527667974,
    "updatedAt": 1670527667974,
    "deletedAt": 0,
    "createdFirstAt": 1670527667974,
    "name": "renderBreadCrumbs",
    "slug": "render-bread-crumbs",
    "type": "value",
    "module": "breadcrumbs",
    "isModuleResolved": true,
    "comments": [],
    "operationRelativeTypescriptFilePath": "src/MarkdownParsePresentation.tsx",
    "classification": "operation",
    "isAbsolute": true,
    "isModuleFromMonorepo": true,
    "id": "xkoqatvmrdvduejfcncvhriw"
  },
  {
    "createdAt": 1670527667975,
    "updatedAt": 1670527667975,
    "deletedAt": 0,
    "createdFirstAt": 1670527667975,
    "name": "ClickableIcon",
    "slug": "clickable-icon",
    "type": "value",
    "module": "clickable-icon",
    "isModuleResolved": true,
    "comments": [],
    "operationRelativeTypescriptFilePath": "src/MarkdownParsePresentation.tsx",
    "classification": "operation",
    "isAbsolute": true,
    "isModuleFromMonorepo": true,
    "id": "wxqiswjffjocudbdshflhtdk"
  },
  {
    "createdAt": 1670527667975,
    "updatedAt": 1670527667975,
    "deletedAt": 0,
    "createdFirstAt": 1670527667975,
    "name": "ClickableIconType",
    "slug": "clickable-icon-type",
    "type": "type",
    "hasGeneric": false,
    "module": "clickable-icon",
    "isModuleResolved": true,
    "comments": [],
    "operationRelativeTypescriptFilePath": "src/MarkdownParsePresentation.tsx",
    "classification": "operation",
    "isAbsolute": true,
    "isModuleFromMonorepo": true,
    "id": "zowtnxsxxczneilyyheidjfe"
  },
  {
    "createdAt": 1670527667975,
    "updatedAt": 1670527667975,
    "deletedAt": 0,
    "createdFirstAt": 1670527667975,
    "name": "MappedObject",
    "slug": "mapped-object",
    "type": "type",
    "hasGeneric": true,
    "module": "js-util",
    "isModuleResolved": true,
    "comments": [],
    "operationRelativeTypescriptFilePath": "src/MarkdownParsePresentation.tsx",
    "classification": "operation",
    "isAbsolute": true,
    "isModuleFromMonorepo": true,
    "id": "minglnfoqchigqbfndhznfnq"
  },
  {
    "createdAt": 1670527667975,
    "updatedAt": 1670527667975,
    "deletedAt": 0,
    "createdFirstAt": 1670527667975,
    "name": "AugmentedWord",
    "slug": "augmented-word",
    "type": "type",
    "hasGeneric": false,
    "module": "augmented-word-types",
    "isModuleResolved": true,
    "comments": [],
    "operationRelativeTypescriptFilePath": "src/MarkdownParsePresentation.tsx",
    "classification": "operation",
    "isAbsolute": true,
    "isModuleFromMonorepo": true,
    "id": "rcehflogecrjdpuojcbhacdv"
  },
  {
    "createdAt": 1670527667975,
    "updatedAt": 1670527667975,
    "deletedAt": 0,
    "createdFirstAt": 1670527667975,
    "name": "flattenMarkdownChunks",
    "slug": "flatten-markdown-chunks",
    "type": "value",
    "module": "key-value-markdown-js",
    "isModuleResolved": true,
    "comments": [],
    "operationRelativeTypescriptFilePath": "src/MarkdownParsePresentation.tsx",
    "classification": "operation",
    "isAbsolute": true,
    "isModuleFromMonorepo": true,
    "id": "ujikwgswzfharvfxbhegdzgx"
  },
  {
    "createdAt": 1670527667975,
    "updatedAt": 1670527667975,
    "deletedAt": 0,
    "createdFirstAt": 1670527667975,
    "name": "Div",
    "slug": "div",
    "type": "value",
    "module": "react-with-native",
    "isModuleResolved": true,
    "comments": [],
    "operationRelativeTypescriptFilePath": "src/MarkdownView.tsx",
    "classification": "operation",
    "isAbsolute": true,
    "isModuleFromMonorepo": true,
    "id": "gsnhtucxgsqwqxmjcvavleqy"
  },
  {
    "createdAt": 1670527667975,
    "updatedAt": 1670527667975,
    "deletedAt": 0,
    "createdFirstAt": 1670527667975,
    "name": "MarkdownParseRenderConfig",
    "slug": "markdown-parse-render-config",
    "module": "markdown/build/esm",
    "isModuleResolved": true,
    "comments": [],
    "operationRelativeTypescriptFilePath": "src/MarkdownView.tsx",
    "classification": "package",
    "isAbsolute": true,
    "isModuleFromMonorepo": false,
    "id": "mjezlpnphsizcjadyhggpnon"
  },
  {
    "createdAt": 1670527667975,
    "updatedAt": 1670527667975,
    "deletedAt": 0,
    "createdFirstAt": 1670527667975,
    "name": "renderMarkdownParse",
    "slug": "render-markdown-parse",
    "module": "markdown/build/esm",
    "isModuleResolved": true,
    "comments": [],
    "operationRelativeTypescriptFilePath": "src/MarkdownView.tsx",
    "classification": "package",
    "isAbsolute": true,
    "isModuleFromMonorepo": false,
    "id": "pzrgjiysfswxtdmmdcavhosq"
  },
  {
    "createdAt": 1670527667975,
    "updatedAt": 1670527667975,
    "deletedAt": 0,
    "createdFirstAt": 1670527667975,
    "name": "MarkdownParse",
    "slug": "markdown-parse",
    "type": "type",
    "hasGeneric": false,
    "module": "markdown-types",
    "isModuleResolved": true,
    "comments": [],
    "operationRelativeTypescriptFilePath": "src/MarkdownView.tsx",
    "classification": "operation",
    "isAbsolute": true,
    "isModuleFromMonorepo": true,
    "id": "wfzllaqsibmglfjwrnjviomw"
  },
  {
    "createdAt": 1670527667976,
    "updatedAt": 1670527667976,
    "deletedAt": 0,
    "createdFirstAt": 1670527667976,
    "name": "MarkdownParsePresentation",
    "slug": "markdown-parse-presentation",
    "module": "./MarkdownParsePresentation",
    "isModuleResolved": true,
    "comments": [],
    "operationRelativeTypescriptFilePath": "src/MarkdownView.tsx",
    "classification": "internal",
    "isAbsolute": false,
    "isModuleFromMonorepo": false,
    "id": "megfhnpzngkirwiwmdfszbfz"
  },
  {
    "createdAt": 1670527667976,
    "updatedAt": 1670527667976,
    "deletedAt": 0,
    "createdFirstAt": 1670527667976,
    "name": "createStore",
    "slug": "create-store",
    "type": "value",
    "module": "react-with-native-store",
    "isModuleResolved": true,
    "comments": [],
    "operationRelativeTypescriptFilePath": "src/store.ts",
    "classification": "operation",
    "isAbsolute": true,
    "isModuleFromMonorepo": true,
    "id": "ruqeaxkvlbnxvemisnshanvz"
  },
  {
    "createdAt": 1670527667976,
    "updatedAt": 1670527667976,
    "deletedAt": 0,
    "createdFirstAt": 1670527667976,
    "name": "SubtextConfig",
    "slug": "subtext-config",
    "type": "type",
    "hasGeneric": false,
    "module": "writer-types",
    "isModuleResolved": true,
    "comments": [],
    "operationRelativeTypescriptFilePath": "src/store.ts",
    "classification": "operation",
    "isAbsolute": true,
    "isModuleFromMonorepo": true,
    "id": "dzlkditkttocxkrhvapzpsjo"
  },
  {
    "createdAt": 1670527667976,
    "updatedAt": 1670527667976,
    "deletedAt": 0,
    "createdFirstAt": 1670527667976,
    "name": "SubwordConfig",
    "slug": "subword-config",
    "type": "type",
    "hasGeneric": false,
    "module": "writer-types",
    "isModuleResolved": true,
    "comments": [],
    "operationRelativeTypescriptFilePath": "src/store.ts",
    "classification": "operation",
    "isAbsolute": true,
    "isModuleFromMonorepo": true,
    "id": "ljbrokslypvboetregzbukgw"
  },
  {
    "createdAt": 1670527667976,
    "updatedAt": 1670527667976,
    "deletedAt": 0,
    "createdFirstAt": 1670527667976,
    "name": "WriterViewEnum",
    "slug": "writer-view-enum",
    "type": "type",
    "hasGeneric": false,
    "module": "writer-types",
    "isModuleResolved": true,
    "comments": [],
    "operationRelativeTypescriptFilePath": "src/store.ts",
    "classification": "operation",
    "isAbsolute": true,
    "isModuleFromMonorepo": true,
    "id": "xofhjnagloyybsatoncrxuuz"
  },
  {
    "createdAt": 1670527667976,
    "updatedAt": 1670527667976,
    "deletedAt": 0,
    "createdFirstAt": 1670527667976,
    "name": "LabeledButton",
    "slug": "labeled-button",
    "type": "value",
    "module": "labeled-button",
    "isModuleResolved": true,
    "comments": [],
    "operationRelativeTypescriptFilePath": "src/TitleContainer.tsx",
    "classification": "operation",
    "isAbsolute": true,
    "isModuleFromMonorepo": true,
    "id": "rjpyefqjlbhrbsdpqjuuhmau"
  },
  {
    "createdAt": 1670527667976,
    "updatedAt": 1670527667976,
    "deletedAt": 0,
    "createdFirstAt": 1670527667976,
    "name": "LabeledButtonType",
    "slug": "labeled-button-type",
    "type": "type",
    "hasGeneric": false,
    "module": "labeled-button",
    "isModuleResolved": true,
    "comments": [],
    "operationRelativeTypescriptFilePath": "src/TitleContainer.tsx",
    "classification": "operation",
    "isAbsolute": true,
    "isModuleFromMonorepo": true,
    "id": "atfusbolnbnwyojmjuespndy"
  },
  {
    "createdAt": 1670527667976,
    "updatedAt": 1670527667976,
    "deletedAt": 0,
    "createdFirstAt": 1670527667976,
    "name": "Div",
    "slug": "div",
    "type": "value",
    "module": "react-with-native",
    "isModuleResolved": true,
    "comments": [],
    "operationRelativeTypescriptFilePath": "src/TitleContainer.tsx",
    "classification": "operation",
    "isAbsolute": true,
    "isModuleFromMonorepo": true,
    "id": "ygiujvlibwzvtdpiswyzogkx"
  },
  {
    "createdAt": 1670527667977,
    "updatedAt": 1670527667977,
    "deletedAt": 0,
    "createdFirstAt": 1670527667977,
    "name": "P",
    "slug": "p",
    "type": "value",
    "module": "react-with-native",
    "isModuleResolved": true,
    "comments": [],
    "operationRelativeTypescriptFilePath": "src/TitleContainer.tsx",
    "classification": "operation",
    "isAbsolute": true,
    "isModuleFromMonorepo": true,
    "id": "idnswdxbdfmzoafayswegtvn"
  },
  {
    "createdAt": 1670527667977,
    "updatedAt": 1670527667977,
    "deletedAt": 0,
    "createdFirstAt": 1670527667977,
    "name": "WriterType",
    "slug": "writer-type",
    "type": "type",
    "hasGeneric": false,
    "module": "filename-conventions",
    "isModuleResolved": true,
    "comments": [],
    "operationRelativeTypescriptFilePath": "src/types.ts",
    "classification": "operation",
    "isAbsolute": true,
    "isModuleFromMonorepo": true,
    "id": "ljtsmvcmxjcwgpbnhgfalqaa"
  },
  {
    "createdAt": 1670527667977,
    "updatedAt": 1670527667977,
    "deletedAt": 0,
    "createdFirstAt": 1670527667977,
    "name": "MappedObject",
    "slug": "mapped-object",
    "type": "type",
    "hasGeneric": true,
    "module": "js-util",
    "isModuleResolved": true,
    "comments": [],
    "operationRelativeTypescriptFilePath": "src/types.ts",
    "classification": "operation",
    "isAbsolute": true,
    "isModuleFromMonorepo": true,
    "id": "cnagvvqfxbptvwmqreocaaky"
  },
  {
    "createdAt": 1670527667977,
    "updatedAt": 1670527667977,
    "deletedAt": 0,
    "createdFirstAt": 1670527667977,
    "name": "AugmentedWord",
    "slug": "augmented-word",
    "type": "type",
    "hasGeneric": false,
    "module": "augmented-word-types",
    "isModuleResolved": true,
    "comments": [],
    "operationRelativeTypescriptFilePath": "src/types.ts",
    "classification": "operation",
    "isAbsolute": true,
    "isModuleFromMonorepo": true,
    "id": "ojrvudcwnwcqgcjnfmbikfaa"
  },
  {
    "createdAt": 1670527667977,
    "updatedAt": 1670527667977,
    "deletedAt": 0,
    "createdFirstAt": 1670527667977,
    "name": "useEffect",
    "slug": "use-effect",
    "module": "react",
    "isModuleResolved": true,
    "comments": [],
    "operationRelativeTypescriptFilePath": "src/WriterInput.tsx",
    "classification": "react",
    "isAbsolute": true,
    "isModuleFromMonorepo": false,
    "id": "guyjdnbcfinnwnxesuukncet"
  },
  {
    "createdAt": 1670527667977,
    "updatedAt": 1670527667977,
    "deletedAt": 0,
    "createdFirstAt": 1670527667977,
    "name": "Div",
    "slug": "div",
    "type": "value",
    "module": "react-with-native",
    "isModuleResolved": true,
    "comments": [],
    "operationRelativeTypescriptFilePath": "src/WriterInput.tsx",
    "classification": "operation",
    "isAbsolute": true,
    "isModuleFromMonorepo": true,
    "id": "fzopstbmowznvcifbiksxcsj"
  },
  {
    "createdAt": 1670527667977,
    "updatedAt": 1670527667977,
    "deletedAt": 0,
    "createdFirstAt": 1670527667977,
    "name": "DbModels",
    "slug": "db-models",
    "type": "type",
    "hasGeneric": false,
    "module": "sdk-db",
    "isModuleResolved": true,
    "comments": [],
    "operationRelativeTypescriptFilePath": "src/WriterInput.tsx",
    "classification": "operation",
    "isAbsolute": true,
    "isModuleFromMonorepo": true,
    "id": "amrjitnrsknsaxmhnhleqnub"
  },
  {
    "createdAt": 1670527667977,
    "updatedAt": 1670527667977,
    "deletedAt": 0,
    "createdFirstAt": 1670527667977,
    "name": "api",
    "slug": "api",
    "type": "value",
    "module": "api",
    "isModuleResolved": true,
    "comments": [],
    "operationRelativeTypescriptFilePath": "src/WriterInput.tsx",
    "classification": "operation",
    "isAbsolute": true,
    "isModuleFromMonorepo": true,
    "id": "hsthcejkifajgajgxzzkhnuz"
  },
  {
    "createdAt": 1670527667978,
    "updatedAt": 1670527667978,
    "deletedAt": 0,
    "createdFirstAt": 1670527667978,
    "name": "queries",
    "slug": "queries",
    "type": "value",
    "module": "api",
    "isModuleResolved": true,
    "comments": [],
    "operationRelativeTypescriptFilePath": "src/WriterInput.tsx",
    "classification": "operation",
    "isAbsolute": true,
    "isModuleFromMonorepo": true,
    "id": "yjmnedrqkybhclepyaijdzeg"
  },
  {
    "createdAt": 1670527667978,
    "updatedAt": 1670527667978,
    "deletedAt": 0,
    "createdFirstAt": 1670527667978,
    "name": "AugmentedWord",
    "slug": "augmented-word",
    "type": "type",
    "hasGeneric": false,
    "module": "augmented-word-types",
    "isModuleResolved": true,
    "comments": [],
    "operationRelativeTypescriptFilePath": "src/WriterInput.tsx",
    "classification": "operation",
    "isAbsolute": true,
    "isModuleFromMonorepo": true,
    "id": "ufgojmuypaoyxlrmsegskexv"
  },
  {
    "createdAt": 1670527667978,
    "updatedAt": 1670527667978,
    "deletedAt": 0,
    "createdFirstAt": 1670527667978,
    "name": "DbPage",
    "slug": "db-page",
    "type": "value",
    "module": "db-crud",
    "isModuleResolved": true,
    "comments": [],
    "operationRelativeTypescriptFilePath": "src/WriterInput.tsx",
    "classification": "operation",
    "isAbsolute": true,
    "isModuleFromMonorepo": true,
    "id": "wnkturllpczavqllaylkjwvi"
  },
  {
    "createdAt": 1670527667978,
    "updatedAt": 1670527667978,
    "deletedAt": 0,
    "createdFirstAt": 1670527667978,
    "name": "FancyLoader",
    "slug": "fancy-loader",
    "type": "value",
    "module": "fancy-loader",
    "isModuleResolved": true,
    "comments": [],
    "operationRelativeTypescriptFilePath": "src/WriterInput.tsx",
    "classification": "operation",
    "isAbsolute": true,
    "isModuleFromMonorepo": true,
    "id": "zikmtbseqazftaqcngozdrpy"
  },
  {
    "createdAt": 1670527667978,
    "updatedAt": 1670527667978,
    "deletedAt": 0,
    "createdFirstAt": 1670527667978,
    "name": "getWriterType",
    "slug": "get-writer-type",
    "type": "value",
    "module": "filename-conventions",
    "isModuleResolved": true,
    "comments": [],
    "operationRelativeTypescriptFilePath": "src/WriterInput.tsx",
    "classification": "operation",
    "isAbsolute": true,
    "isModuleFromMonorepo": true,
    "id": "bcntmkqgtrrbflqbhnduybjj"
  },
  {
    "createdAt": 1670527667978,
    "updatedAt": 1670527667978,
    "deletedAt": 0,
    "createdFirstAt": 1670527667978,
    "name": "WriterType",
    "slug": "writer-type",
    "type": "type",
    "hasGeneric": false,
    "module": "filename-conventions",
    "isModuleResolved": true,
    "comments": [],
    "operationRelativeTypescriptFilePath": "src/WriterInput.tsx",
    "classification": "operation",
    "isAbsolute": true,
    "isModuleFromMonorepo": true,
    "id": "fnijxlrjfziqfsolrknoufyt"
  },
  {
    "createdAt": 1670527667978,
    "updatedAt": 1670527667978,
    "deletedAt": 0,
    "createdFirstAt": 1670527667978,
    "name": "getFolderJs",
    "slug": "get-folder-js",
    "type": "value",
    "module": "fs-util-js",
    "isModuleResolved": true,
    "comments": [],
    "operationRelativeTypescriptFilePath": "src/WriterInput.tsx",
    "classification": "operation",
    "isAbsolute": true,
    "isModuleFromMonorepo": true,
    "id": "xepcoallzyzgxuolxaclowwp"
  },
  {
    "createdAt": 1670527667978,
    "updatedAt": 1670527667978,
    "deletedAt": 0,
    "createdFirstAt": 1670527667978,
    "name": "MappedObject",
    "slug": "mapped-object",
    "type": "type",
    "hasGeneric": true,
    "module": "js-util",
    "isModuleResolved": true,
    "comments": [],
    "operationRelativeTypescriptFilePath": "src/WriterInput.tsx",
    "classification": "operation",
    "isAbsolute": true,
    "isModuleFromMonorepo": true,
    "id": "lgtawrhuilaecyyzcbpinsjj"
  },
  {
    "createdAt": 1670527667979,
    "updatedAt": 1670527667979,
    "deletedAt": 0,
    "createdFirstAt": 1670527667979,
    "name": "MarkdownParseRenderConfig",
    "slug": "markdown-parse-render-config",
    "type": "type",
    "hasGeneric": false,
    "module": "markdown",
    "isModuleResolved": true,
    "comments": [],
    "operationRelativeTypescriptFilePath": "src/WriterInput.tsx",
    "classification": "operation",
    "isAbsolute": true,
    "isModuleFromMonorepo": true,
    "id": "kvwailohiaidnwvtiavsqdvx"
  },
  {
    "createdAt": 1670527667979,
    "updatedAt": 1670527667979,
    "deletedAt": 0,
    "createdFirstAt": 1670527667979,
    "name": "mdToJsonParse",
    "slug": "md-to-json-parse",
    "type": "value",
    "module": "markdown-parse-js",
    "isModuleResolved": true,
    "comments": [],
    "operationRelativeTypescriptFilePath": "src/WriterInput.tsx",
    "classification": "operation",
    "isAbsolute": true,
    "isModuleFromMonorepo": true,
    "id": "stbslanupriravptrmqrtfdq"
  },
  {
    "createdAt": 1670527667979,
    "updatedAt": 1670527667979,
    "deletedAt": 0,
    "createdFirstAt": 1670527667979,
    "name": "ContextualPromptResultsTab",
    "slug": "contextual-prompt-results-tab",
    "type": "value",
    "module": "prompt-components",
    "isModuleResolved": true,
    "comments": [],
    "operationRelativeTypescriptFilePath": "src/WriterInput.tsx",
    "classification": "operation",
    "isAbsolute": true,
    "isModuleFromMonorepo": true,
    "id": "czfwwbvphxkuwopggtnzmiwb"
  },
  {
    "createdAt": 1670527667979,
    "updatedAt": 1670527667979,
    "deletedAt": 0,
    "createdFirstAt": 1670527667979,
    "name": "isDev",
    "slug": "is-dev",
    "type": "value",
    "module": "server-api-url",
    "isModuleResolved": true,
    "comments": [],
    "operationRelativeTypescriptFilePath": "src/WriterInput.tsx",
    "classification": "operation",
    "isAbsolute": true,
    "isModuleFromMonorepo": true,
    "id": "favnaktlybarmfonbjwbbmld"
  },
  {
    "createdAt": 1670527667979,
    "updatedAt": 1670527667979,
    "deletedAt": 0,
    "createdFirstAt": 1670527667979,
    "name": "ShortStudio",
    "slug": "short-studio",
    "type": "value",
    "module": "short-markdown-writer-input",
    "isModuleResolved": true,
    "comments": [],
    "operationRelativeTypescriptFilePath": "src/WriterInput.tsx",
    "classification": "operation",
    "isAbsolute": true,
    "isModuleFromMonorepo": true,
    "id": "rbxkvcogwnhcsludnxsinnzj"
  },
  {
    "createdAt": 1670527667979,
    "updatedAt": 1670527667979,
    "deletedAt": 0,
    "createdFirstAt": 1670527667979,
    "name": "WriterViewEnum",
    "slug": "writer-view-enum",
    "type": "type",
    "hasGeneric": false,
    "module": "writer-types",
    "isModuleResolved": true,
    "comments": [],
    "operationRelativeTypescriptFilePath": "src/WriterInput.tsx",
    "classification": "operation",
    "isAbsolute": true,
    "isModuleFromMonorepo": true,
    "id": "suekepolgktrxkvwiiwjanwj"
  },
  {
    "createdAt": 1670527667979,
    "updatedAt": 1670527667979,
    "deletedAt": 0,
    "createdFirstAt": 1670527667979,
    "name": "WriterConfigForm",
    "slug": "writer-config-form",
    "module": "./config/WriterConfigForm",
    "isModuleResolved": true,
    "comments": [],
    "operationRelativeTypescriptFilePath": "src/WriterInput.tsx",
    "classification": "internal",
    "isAbsolute": false,
    "isModuleFromMonorepo": false,
    "id": "vrganomotwdpkegfvohrxxlz"
  },
  {
    "createdAt": 1670527667979,
    "updatedAt": 1670527667979,
    "deletedAt": 0,
    "createdFirstAt": 1670527667979,
    "name": "FrontmatterForm",
    "slug": "frontmatter-form",
    "module": "./FrontmatterForm",
    "isModuleResolved": true,
    "comments": [],
    "operationRelativeTypescriptFilePath": "src/WriterInput.tsx",
    "classification": "internal",
    "isAbsolute": false,
    "isModuleFromMonorepo": false,
    "id": "vyqjllapjwtflpybkgcmqlxg"
  },
  {
    "createdAt": 1670527667979,
    "updatedAt": 1670527667979,
    "deletedAt": 0,
    "createdFirstAt": 1670527667979,
    "name": "TitleContainer",
    "slug": "title-container",
    "module": "./TitleContainer",
    "isModuleResolved": true,
    "comments": [],
    "operationRelativeTypescriptFilePath": "src/WriterInput.tsx",
    "classification": "internal",
    "isAbsolute": false,
    "isModuleFromMonorepo": false,
    "id": "jbvufcjnhvcmwnzeendoljfu"
  },
  {
    "createdAt": 1670527667980,
    "updatedAt": 1670527667980,
    "deletedAt": 0,
    "createdFirstAt": 1670527667980,
    "name": "getWriterTypeFromContent",
    "slug": "get-writer-type-from-content",
    "module": "./util/getWriterTypeFromContent",
    "isModuleResolved": true,
    "comments": [],
    "operationRelativeTypescriptFilePath": "src/WriterInput.tsx",
    "classification": "internal",
    "isAbsolute": false,
    "isModuleFromMonorepo": false,
    "id": "aazagzpbtjuwtqhqrvzovoff"
  },
  {
    "createdAt": 1670527667980,
    "updatedAt": 1670527667980,
    "deletedAt": 0,
    "createdFirstAt": 1670527667980,
    "name": "EditWriterInput",
    "slug": "edit-writer-input",
    "module": "./EditWriterInput",
    "isModuleResolved": true,
    "comments": [],
    "operationRelativeTypescriptFilePath": "src/WriterInput.tsx",
    "classification": "internal",
    "isAbsolute": false,
    "isModuleFromMonorepo": false,
    "id": "ssivdqdywggeylddxxdpnyer"
  },
  {
    "createdAt": 1670527667980,
    "updatedAt": 1670527667980,
    "deletedAt": 0,
    "createdFirstAt": 1670527667980,
    "name": "MarkdownView",
    "slug": "markdown-view",
    "module": "./MarkdownView",
    "isModuleResolved": true,
    "comments": [],
    "operationRelativeTypescriptFilePath": "src/WriterInput.tsx",
    "classification": "internal",
    "isAbsolute": false,
    "isModuleFromMonorepo": false,
    "id": "iaomjyeeroxvyifstebbcnka"
  },
  {
    "createdAt": 1670527667980,
    "updatedAt": 1670527667980,
    "deletedAt": 0,
    "createdFirstAt": 1670527667980,
    "name": "useStore",
    "slug": "use-store",
    "module": "./store",
    "isModuleResolved": true,
    "comments": [],
    "operationRelativeTypescriptFilePath": "src/WriterInput.tsx",
    "classification": "internal",
    "isAbsolute": false,
    "isModuleFromMonorepo": false,
    "id": "xtuqzfceirtiiqcsrntwybxx"
  },
  {
    "createdAt": 1670527667980,
    "updatedAt": 1670527667980,
    "deletedAt": 0,
    "createdFirstAt": 1670527667980,
    "name": "SubtextConfig",
    "slug": "subtext-config",
    "type": "type",
    "hasGeneric": false,
    "module": "writer-types",
    "isModuleResolved": true,
    "comments": [],
    "operationRelativeTypescriptFilePath": "src/config/editSubtextSubwordConfig.ts",
    "classification": "operation",
    "isAbsolute": true,
    "isModuleFromMonorepo": true,
    "id": "dzlzqaqoemjmoimwlqaenyil"
  },
  {
    "createdAt": 1670527667980,
    "updatedAt": 1670527667980,
    "deletedAt": 0,
    "createdFirstAt": 1670527667980,
    "name": "SubwordConfig",
    "slug": "subword-config",
    "type": "type",
    "hasGeneric": false,
    "module": "writer-types",
    "isModuleResolved": true,
    "comments": [],
    "operationRelativeTypescriptFilePath": "src/config/editSubtextSubwordConfig.ts",
    "classification": "operation",
    "isAbsolute": true,
    "isModuleFromMonorepo": true,
    "id": "xdxpfsavrcmhksbyzezzhcdk"
  },
  {
    "createdAt": 1670527667980,
    "updatedAt": 1670527667980,
    "deletedAt": 0,
    "createdFirstAt": 1670527667980,
    "name": "Div",
    "slug": "div",
    "type": "value",
    "module": "react-with-native",
    "isModuleResolved": true,
    "comments": [],
    "operationRelativeTypescriptFilePath": "src/config/WriterConfigForm.tsx",
    "classification": "operation",
    "isAbsolute": true,
    "isModuleFromMonorepo": true,
    "id": "qgjmqkdawuwcgwgdrsuntzlu"
  },
  {
    "createdAt": 1670527667980,
    "updatedAt": 1670527667980,
    "deletedAt": 0,
    "createdFirstAt": 1670527667980,
    "name": "useStore",
    "slug": "use-store",
    "module": "../store",
    "isModuleResolved": true,
    "comments": [],
    "operationRelativeTypescriptFilePath": "src/config/WriterConfigForm.tsx",
    "classification": "internal",
    "isAbsolute": false,
    "isModuleFromMonorepo": false,
    "id": "pxzhkektcyqjzmjosqkrnyoi"
  },
  {
    "createdAt": 1670527667981,
    "updatedAt": 1670527667981,
    "deletedAt": 0,
    "createdFirstAt": 1670527667981,
    "name": "SimplifiedSchemaForm",
    "slug": "simplified-schema-form",
    "type": "value",
    "module": "simplified-schema-form",
    "isModuleResolved": true,
    "comments": [],
    "operationRelativeTypescriptFilePath": "src/config/WriterConfigForm.tsx",
    "classification": "operation",
    "isAbsolute": true,
    "isModuleFromMonorepo": true,
    "id": "pfryvigmdgphstqppqfzgahk"
  },
  {
    "createdAt": 1670527667981,
    "updatedAt": 1670527667981,
    "deletedAt": 0,
    "createdFirstAt": 1670527667981,
    "name": "SimplifiedSchema",
    "slug": "simplified-schema",
    "type": "type",
    "hasGeneric": false,
    "module": "code-types",
    "isModuleResolved": true,
    "comments": [],
    "operationRelativeTypescriptFilePath": "src/config/WriterConfigForm.tsx",
    "classification": "operation",
    "isAbsolute": true,
    "isModuleFromMonorepo": true,
    "id": "wwdnieztiffnjbblbgsrbujb"
  },
  {
    "createdAt": 1670527667981,
    "updatedAt": 1670527667981,
    "deletedAt": 0,
    "createdFirstAt": 1670527667981,
    "name": "SubtextConfig",
    "slug": "subtext-config",
    "type": "type",
    "hasGeneric": false,
    "module": "writer-types",
    "isModuleResolved": true,
    "comments": [],
    "operationRelativeTypescriptFilePath": "src/config/WriterConfigForm.tsx",
    "classification": "operation",
    "isAbsolute": true,
    "isModuleFromMonorepo": true,
    "id": "okdwoeinqulhsbskgaywbgoz"
  },
  {
    "createdAt": 1670527667981,
    "updatedAt": 1670527667981,
    "deletedAt": 0,
    "createdFirstAt": 1670527667981,
    "name": "SubwordConfig",
    "slug": "subword-config",
    "type": "type",
    "hasGeneric": false,
    "module": "writer-types",
    "isModuleResolved": true,
    "comments": [],
    "operationRelativeTypescriptFilePath": "src/config/WriterConfigForm.tsx",
    "classification": "operation",
    "isAbsolute": true,
    "isModuleFromMonorepo": true,
    "id": "lodvukboaalrkysximxfqexj"
  },
  {
    "createdAt": 1670527667981,
    "updatedAt": 1670527667981,
    "deletedAt": 0,
    "createdFirstAt": 1670527667981,
    "name": "getFolderJs",
    "slug": "get-folder-js",
    "type": "value",
    "module": "fs-util-js",
    "isModuleResolved": true,
    "comments": [],
    "operationRelativeTypescriptFilePath": "src/editors/autocomplete-components.tsx",
    "classification": "operation",
    "isAbsolute": true,
    "isModuleFromMonorepo": true,
    "id": "jumvfgawtevflzotuqxyycqx"
  },
  {
    "createdAt": 1670527667981,
    "updatedAt": 1670527667981,
    "deletedAt": 0,
    "createdFirstAt": 1670527667981,
    "name": "MappedObject",
    "slug": "mapped-object",
    "type": "type",
    "hasGeneric": true,
    "module": "js-util",
    "isModuleResolved": true,
    "comments": [],
    "operationRelativeTypescriptFilePath": "src/editors/autocomplete-components.tsx",
    "classification": "operation",
    "isAbsolute": true,
    "isModuleFromMonorepo": true,
    "id": "cxktajnryhzshamtxrpajhxw"
  },
  {
    "createdAt": 1670527667981,
    "updatedAt": 1670527667981,
    "deletedAt": 0,
    "createdFirstAt": 1670527667981,
    "name": "renderMarkdownContent",
    "slug": "render-markdown-content",
    "type": "value",
    "module": "markdown",
    "isModuleResolved": true,
    "comments": [],
    "operationRelativeTypescriptFilePath": "src/editors/autocomplete-components.tsx",
    "classification": "operation",
    "isAbsolute": true,
    "isModuleFromMonorepo": true,
    "id": "dgpolonxgmmmykaecrctcnas"
  },
  {
    "createdAt": 1670527667981,
    "updatedAt": 1670527667981,
    "deletedAt": 0,
    "createdFirstAt": 1670527667981,
    "name": "AugmentedWord",
    "slug": "augmented-word",
    "type": "type",
    "hasGeneric": false,
    "module": "augmented-word-types",
    "isModuleResolved": true,
    "comments": [],
    "operationRelativeTypescriptFilePath": "src/editors/autocomplete-components.tsx",
    "classification": "operation",
    "isAbsolute": true,
    "isModuleFromMonorepo": true,
    "id": "lbpauoapixwhnjurbfxutrhh"
  },
  {
    "createdAt": 1670527667981,
    "updatedAt": 1670527667981,
    "deletedAt": 0,
    "createdFirstAt": 1670527667981,
    "name": "Div",
    "slug": "div",
    "type": "value",
    "module": "react-with-native",
    "isModuleResolved": true,
    "comments": [],
    "operationRelativeTypescriptFilePath": "src/editors/autocomplete-components.tsx",
    "classification": "operation",
    "isAbsolute": true,
    "isModuleFromMonorepo": true,
    "id": "cliiluqqyttxnvgwgblcteup"
  },
  {
    "createdAt": 1670527667982,
    "updatedAt": 1670527667982,
    "deletedAt": 0,
    "createdFirstAt": 1670527667982,
    "name": "P",
    "slug": "p",
    "type": "value",
    "module": "react-with-native",
    "isModuleResolved": true,
    "comments": [],
    "operationRelativeTypescriptFilePath": "src/editors/autocomplete-components.tsx",
    "classification": "operation",
    "isAbsolute": true,
    "isModuleFromMonorepo": true,
    "id": "dmriqnnkvwwaktdyetsugams"
  },
  {
    "createdAt": 1670527667982,
    "updatedAt": 1670527667982,
    "deletedAt": 0,
    "createdFirstAt": 1670527667982,
    "name": "isDev",
    "slug": "is-dev",
    "type": "value",
    "module": "server-api-url",
    "isModuleResolved": true,
    "comments": [],
    "operationRelativeTypescriptFilePath": "src/editors/autocomplete-components.tsx",
    "classification": "operation",
    "isAbsolute": true,
    "isModuleFromMonorepo": true,
    "id": "diwhqcbytnsxrmpdgqzwwrzj"
  },
  {
    "createdAt": 1670527667982,
    "updatedAt": 1670527667982,
    "deletedAt": 0,
    "createdFirstAt": 1670527667982,
    "name": "TextEditingContext",
    "slug": "text-editing-context",
    "module": "../old/getContext",
    "isModuleResolved": true,
    "comments": [],
    "operationRelativeTypescriptFilePath": "src/editors/autocomplete-components.tsx",
    "classification": "internal",
    "isAbsolute": false,
    "isModuleFromMonorepo": false,
    "id": "iiijkhlihthrhleauuzkviyc"
  },
  {
    "createdAt": 1670527667982,
    "updatedAt": 1670527667982,
    "deletedAt": 0,
    "createdFirstAt": 1670527667982,
    "name": "trimLeft",
    "slug": "trim-left",
    "module": "../util/word-trimming",
    "isModuleResolved": true,
    "comments": [],
    "operationRelativeTypescriptFilePath": "src/editors/autocomplete-components.tsx",
    "classification": "internal",
    "isAbsolute": false,
    "isModuleFromMonorepo": false,
    "id": "eizbsdhatgqanbnqsgxoaczr"
  },
  {
    "createdAt": 1670527667982,
    "updatedAt": 1670527667982,
    "deletedAt": 0,
    "createdFirstAt": 1670527667982,
    "name": "MAX_COMPLETIONS_AMOUNT",
    "slug": "max-completions-amount",
    "module": "./MarkedToken",
    "isModuleResolved": true,
    "comments": [],
    "operationRelativeTypescriptFilePath": "src/editors/autocomplete-components.tsx",
    "classification": "internal",
    "isAbsolute": false,
    "isModuleFromMonorepo": false,
    "id": "kdummhihvcsolktkgpipylfu"
  },
  {
    "createdAt": 1670527667982,
    "updatedAt": 1670527667982,
    "deletedAt": 0,
    "createdFirstAt": 1670527667982,
    "name": "notEmpty",
    "slug": "not-empty",
    "type": "value",
    "module": "js-util",
    "isModuleResolved": true,
    "comments": [],
    "operationRelativeTypescriptFilePath": "src/editors/ContentEditableDivInput.tsx",
    "classification": "operation",
    "isAbsolute": true,
    "isModuleFromMonorepo": true,
    "id": "iteqjbtfjpqgnmvmmypmxbri"
  },
  {
    "createdAt": 1670527667982,
    "updatedAt": 1670527667982,
    "deletedAt": 0,
    "createdFirstAt": 1670527667982,
    "name": "useEffect",
    "slug": "use-effect",
    "module": "react",
    "isModuleResolved": true,
    "comments": [],
    "operationRelativeTypescriptFilePath": "src/editors/ContentEditableDivInput.tsx",
    "classification": "react",
    "isAbsolute": true,
    "isModuleFromMonorepo": false,
    "id": "lepjjiboyjegprziscvdlzoh"
  },
  {
    "createdAt": 1670527667982,
    "updatedAt": 1670527667982,
    "deletedAt": 0,
    "createdFirstAt": 1670527667982,
    "name": "useRef",
    "slug": "use-ref",
    "module": "react",
    "isModuleResolved": true,
    "comments": [],
    "operationRelativeTypescriptFilePath": "src/editors/ContentEditableDivInput.tsx",
    "classification": "react",
    "isAbsolute": true,
    "isModuleFromMonorepo": false,
    "id": "rpvcmhvuorcasgcgsdcdbzeu"
  },
  {
    "createdAt": 1670527667983,
    "updatedAt": 1670527667983,
    "deletedAt": 0,
    "createdFirstAt": 1670527667983,
    "name": "Div",
    "slug": "div",
    "type": "value",
    "module": "react-with-native",
    "isModuleResolved": true,
    "comments": [],
    "operationRelativeTypescriptFilePath": "src/editors/ContentEditableDivInput.tsx",
    "classification": "operation",
    "isAbsolute": true,
    "isModuleFromMonorepo": true,
    "id": "vlfhikkcixhwyuxjbmuckntt"
  },
  {
    "createdAt": 1670527667983,
    "updatedAt": 1670527667983,
    "deletedAt": 0,
    "createdFirstAt": 1670527667983,
    "name": "FinalDivType",
    "slug": "final-div-type",
    "type": "type",
    "hasGeneric": true,
    "module": "react-with-native",
    "isModuleResolved": true,
    "comments": [],
    "operationRelativeTypescriptFilePath": "src/editors/ContentEditableDivInput.tsx",
    "classification": "operation",
    "isAbsolute": true,
    "isModuleFromMonorepo": true,
    "id": "dxmsjcrqhzikbftfmzxlnbik"
  },
  {
    "createdAt": 1670527667983,
    "updatedAt": 1670527667983,
    "deletedAt": 0,
    "createdFirstAt": 1670527667983,
    "name": "MarkdownParseRenderConfig",
    "slug": "markdown-parse-render-config",
    "type": "type",
    "hasGeneric": false,
    "module": "markdown",
    "isModuleResolved": true,
    "comments": [],
    "operationRelativeTypescriptFilePath": "src/editors/ContentEditableDivInput.tsx",
    "classification": "operation",
    "isAbsolute": true,
    "isModuleFromMonorepo": true,
    "id": "pkfuqyxibynbzypuicrnmcji"
  },
  {
    "createdAt": 1670527667983,
    "updatedAt": 1670527667983,
    "deletedAt": 0,
    "createdFirstAt": 1670527667983,
    "name": "metaClickableClassName",
    "slug": "meta-clickable-class-name",
    "module": "../editors/MarkedToken",
    "isModuleResolved": true,
    "comments": [],
    "operationRelativeTypescriptFilePath": "src/editors/ContentEditableDivInput.tsx",
    "classification": "internal",
    "isAbsolute": false,
    "isModuleFromMonorepo": false,
    "id": "tyjoxkxkkufyklmdfgnqyoet"
  },
  {
    "createdAt": 1670527667983,
    "updatedAt": 1670527667983,
    "deletedAt": 0,
    "createdFirstAt": 1670527667983,
    "name": "ParseTextContentToHtmlString",
    "slug": "parse-text-content-to-html-string",
    "module": "./SmartContentEditableDivInput",
    "isModuleResolved": true,
    "comments": [],
    "operationRelativeTypescriptFilePath": "src/editors/ContentEditableDivInput.tsx",
    "classification": "internal",
    "isAbsolute": false,
    "isModuleFromMonorepo": false,
    "id": "zzvwhtdaseuyaqywaovvijqg"
  },
  {
    "createdAt": 1670527667983,
    "updatedAt": 1670527667983,
    "deletedAt": 0,
    "createdFirstAt": 1670527667983,
    "name": "SubtextConfig",
    "slug": "subtext-config",
    "type": "type",
    "hasGeneric": false,
    "module": "writer-types",
    "isModuleResolved": true,
    "comments": [],
    "operationRelativeTypescriptFilePath": "src/editors/ContentEditableDivInput.tsx",
    "classification": "operation",
    "isAbsolute": true,
    "isModuleFromMonorepo": true,
    "id": "bwfvohtmqyeuionuglhepqtu"
  },
  {
    "createdAt": 1670527667983,
    "updatedAt": 1670527667983,
    "deletedAt": 0,
    "createdFirstAt": 1670527667983,
    "name": "SubwordConfig",
    "slug": "subword-config",
    "type": "type",
    "hasGeneric": false,
    "module": "writer-types",
    "isModuleResolved": true,
    "comments": [],
    "operationRelativeTypescriptFilePath": "src/editors/ContentEditableDivInput.tsx",
    "classification": "operation",
    "isAbsolute": true,
    "isModuleFromMonorepo": true,
    "id": "hkebbgxdtxqsdihqmcnacrrd"
  },
  {
    "createdAt": 1670527667983,
    "updatedAt": 1670527667983,
    "deletedAt": 0,
    "createdFirstAt": 1670527667983,
    "name": "SubtextConfig",
    "slug": "subtext-config",
    "type": "type",
    "hasGeneric": false,
    "module": "writer-types",
    "isModuleResolved": true,
    "comments": [],
    "operationRelativeTypescriptFilePath": "src/editors/getSubtext.tsx",
    "classification": "operation",
    "isAbsolute": true,
    "isModuleFromMonorepo": true,
    "id": "aoouulasenruakxufdicpovg"
  },
  {
    "createdAt": 1670527667983,
    "updatedAt": 1670527667983,
    "deletedAt": 0,
    "createdFirstAt": 1670527667983,
    "name": "marked",
    "slug": "marked",
    "module": "marked",
    "isModuleResolved": true,
    "comments": [],
    "operationRelativeTypescriptFilePath": "src/editors/MarkedParagraph.tsx",
    "classification": "package",
    "isAbsolute": true,
    "isModuleFromMonorepo": false,
    "id": "hxrsuqtomyivzkbjezpkqhwh"
  },
  {
    "createdAt": 1670527667984,
    "updatedAt": 1670527667984,
    "deletedAt": 0,
    "createdFirstAt": 1670527667984,
    "name": "getSubtext",
    "slug": "get-subtext",
    "module": "./getSubtext",
    "isModuleResolved": true,
    "comments": [],
    "operationRelativeTypescriptFilePath": "src/editors/MarkedParagraph.tsx",
    "classification": "internal",
    "isAbsolute": false,
    "isModuleFromMonorepo": false,
    "id": "nsiuatnwoxsbpexwvgasaecw"
  },
  {
    "createdAt": 1670527667984,
    "updatedAt": 1670527667984,
    "deletedAt": 0,
    "createdFirstAt": 1670527667984,
    "name": "MarkedToken",
    "slug": "marked-token",
    "module": "./MarkedToken",
    "isModuleResolved": true,
    "comments": [],
    "operationRelativeTypescriptFilePath": "src/editors/MarkedParagraph.tsx",
    "classification": "internal",
    "isAbsolute": false,
    "isModuleFromMonorepo": false,
    "id": "xgukrtqysxdtxhfmbhbsoupp"
  },
  {
    "createdAt": 1670527667984,
    "updatedAt": 1670527667984,
    "deletedAt": 0,
    "createdFirstAt": 1670527667984,
    "name": "ContentEditableRenderComponentType",
    "slug": "content-editable-render-component-type",
    "module": "./types",
    "isModuleResolved": true,
    "comments": [],
    "operationRelativeTypescriptFilePath": "src/editors/MarkedParagraph.tsx",
    "classification": "internal",
    "isAbsolute": false,
    "isModuleFromMonorepo": false,
    "id": "ocsqsauztyihionlgqfmmpms"
  },
  {
    "createdAt": 1670527667984,
    "updatedAt": 1670527667984,
    "deletedAt": 0,
    "createdFirstAt": 1670527667984,
    "name": "marked",
    "slug": "marked",
    "module": "marked",
    "isModuleResolved": true,
    "comments": [],
    "operationRelativeTypescriptFilePath": "src/editors/MarkedText.tsx",
    "classification": "package",
    "isAbsolute": true,
    "isModuleFromMonorepo": false,
    "id": "pjmmcbbsnylcvoadkktswojp"
  },
  {
    "createdAt": 1670527667984,
    "updatedAt": 1670527667984,
    "deletedAt": 0,
    "createdFirstAt": 1670527667984,
    "name": "SpannedSentence",
    "slug": "spanned-sentence",
    "module": "./SpannedSentence",
    "isModuleResolved": true,
    "comments": [],
    "operationRelativeTypescriptFilePath": "src/editors/MarkedText.tsx",
    "classification": "internal",
    "isAbsolute": false,
    "isModuleFromMonorepo": false,
    "id": "vfoxhlywaglfrhgcxasbypar"
  },
  {
    "createdAt": 1670527667984,
    "updatedAt": 1670527667984,
    "deletedAt": 0,
    "createdFirstAt": 1670527667984,
    "name": "ContentEditableRenderComponentType",
    "slug": "content-editable-render-component-type",
    "module": "./types",
    "isModuleResolved": true,
    "comments": [],
    "operationRelativeTypescriptFilePath": "src/editors/MarkedText.tsx",
    "classification": "internal",
    "isAbsolute": false,
    "isModuleFromMonorepo": false,
    "id": "bvvnfxacgotznftbclmuxtjt"
  },
  {
    "createdAt": 1670527667984,
    "updatedAt": 1670527667984,
    "deletedAt": 0,
    "createdFirstAt": 1670527667984,
    "name": "getRealSrc",
    "slug": "get-real-src",
    "type": "value",
    "module": "markdown",
    "isModuleResolved": true,
    "comments": [],
    "operationRelativeTypescriptFilePath": "src/editors/MarkedToken.tsx",
    "classification": "operation",
    "isAbsolute": true,
    "isModuleFromMonorepo": true,
    "id": "ljacgbbvbgsnmjqacvqghhvv"
  },
  {
    "createdAt": 1670527667984,
    "updatedAt": 1670527667984,
    "deletedAt": 0,
    "createdFirstAt": 1670527667984,
    "name": "MarkdownParseRenderConfig",
    "slug": "markdown-parse-render-config",
    "type": "type",
    "hasGeneric": false,
    "module": "markdown",
    "isModuleResolved": true,
    "comments": [],
    "operationRelativeTypescriptFilePath": "src/editors/MarkedToken.tsx",
    "classification": "operation",
    "isAbsolute": true,
    "isModuleFromMonorepo": true,
    "id": "adcrmydmortmwdgqxlidddnx"
  },
  {
    "createdAt": 1670527667984,
    "updatedAt": 1670527667984,
    "deletedAt": 0,
    "createdFirstAt": 1670527667984,
    "name": "marked",
    "slug": "marked",
    "module": "marked",
    "isModuleResolved": true,
    "comments": [],
    "operationRelativeTypescriptFilePath": "src/editors/MarkedToken.tsx",
    "classification": "package",
    "isAbsolute": true,
    "isModuleFromMonorepo": false,
    "id": "ssclaxwskdkvsdycfkbwcqil"
  },
  {
    "createdAt": 1670527667985,
    "updatedAt": 1670527667985,
    "deletedAt": 0,
    "createdFirstAt": 1670527667985,
    "name": "SubtextConfig",
    "slug": "subtext-config",
    "type": "type",
    "hasGeneric": false,
    "module": "writer-types",
    "isModuleResolved": true,
    "comments": [],
    "operationRelativeTypescriptFilePath": "src/editors/MarkedToken.tsx",
    "classification": "operation",
    "isAbsolute": true,
    "isModuleFromMonorepo": true,
    "id": "ajrcxgysttenxfbzscngnpdc"
  },
  {
    "createdAt": 1670527667985,
    "updatedAt": 1670527667985,
    "deletedAt": 0,
    "createdFirstAt": 1670527667985,
    "name": "SubwordConfig",
    "slug": "subword-config",
    "type": "type",
    "hasGeneric": false,
    "module": "writer-types",
    "isModuleResolved": true,
    "comments": [],
    "operationRelativeTypescriptFilePath": "src/editors/MarkedToken.tsx",
    "classification": "operation",
    "isAbsolute": true,
    "isModuleFromMonorepo": true,
    "id": "bksibjxbmpyxrtvlqltsmuyf"
  },
  {
    "createdAt": 1670527667985,
    "updatedAt": 1670527667985,
    "deletedAt": 0,
    "createdFirstAt": 1670527667985,
    "name": "trimAround",
    "slug": "trim-around",
    "module": "../util/word-trimming",
    "isModuleResolved": true,
    "comments": [],
    "operationRelativeTypescriptFilePath": "src/editors/MarkedToken.tsx",
    "classification": "internal",
    "isAbsolute": false,
    "isModuleFromMonorepo": false,
    "id": "wtmynegbxfywwczrjkpjxpmi"
  },
  {
    "createdAt": 1670527667985,
    "updatedAt": 1670527667985,
    "deletedAt": 0,
    "createdFirstAt": 1670527667985,
    "name": "getSubtext",
    "slug": "get-subtext",
    "module": "./getSubtext",
    "isModuleResolved": true,
    "comments": [],
    "operationRelativeTypescriptFilePath": "src/editors/MarkedToken.tsx",
    "classification": "internal",
    "isAbsolute": false,
    "isModuleFromMonorepo": false,
    "id": "kliotgiqycohdxxisgxzlplc"
  },
  {
    "createdAt": 1670527667988,
    "updatedAt": 1670527667988,
    "deletedAt": 0,
    "createdFirstAt": 1670527667988,
    "name": "MarkedParagraph",
    "slug": "marked-paragraph",
    "module": "./MarkedParagraph",
    "isModuleResolved": true,
    "comments": [],
    "operationRelativeTypescriptFilePath": "src/editors/MarkedToken.tsx",
    "classification": "internal",
    "isAbsolute": false,
    "isModuleFromMonorepo": false,
    "id": "dysdpzjonxdwvyuvtdftkdfm"
  },
  {
    "createdAt": 1670527667988,
    "updatedAt": 1670527667988,
    "deletedAt": 0,
    "createdFirstAt": 1670527667988,
    "name": "SpannedSentence",
    "slug": "spanned-sentence",
    "module": "./SpannedSentence",
    "isModuleResolved": true,
    "comments": [],
    "operationRelativeTypescriptFilePath": "src/editors/MarkedToken.tsx",
    "classification": "internal",
    "isAbsolute": false,
    "isModuleFromMonorepo": false,
    "id": "hiievzryxqsqtbqdqymfibpp"
  },
  {
    "createdAt": 1670527667988,
    "updatedAt": 1670527667988,
    "deletedAt": 0,
    "createdFirstAt": 1670527667988,
    "name": "MarkedText",
    "slug": "marked-text",
    "module": "./MarkedText",
    "isModuleResolved": true,
    "comments": [],
    "operationRelativeTypescriptFilePath": "src/editors/MarkedToken.tsx",
    "classification": "internal",
    "isAbsolute": false,
    "isModuleFromMonorepo": false,
    "id": "aeffpzpoaaltccttzaevpuph"
  },
  {
    "createdAt": 1670527667988,
    "updatedAt": 1670527667988,
    "deletedAt": 0,
    "createdFirstAt": 1670527667988,
    "name": "testContentEditableRenderComponent",
    "slug": "test-content-editable-render-component",
    "module": "./testContentEditableRenderComponent",
    "isModuleResolved": true,
    "comments": [],
    "operationRelativeTypescriptFilePath": "src/editors/MarkedToken.tsx",
    "classification": "internal",
    "isAbsolute": false,
    "isModuleFromMonorepo": false,
    "id": "gfdlovxnrwyrdabcuxrtyunx"
  },
  {
    "createdAt": 1670527667988,
    "updatedAt": 1670527667988,
    "deletedAt": 0,
    "createdFirstAt": 1670527667988,
    "name": "useEffect",
    "slug": "use-effect",
    "module": "react",
    "isModuleResolved": true,
    "comments": [],
    "operationRelativeTypescriptFilePath": "src/editors/SmartContentEditableDivInput.tsx",
    "classification": "react",
    "isAbsolute": true,
    "isModuleFromMonorepo": false,
    "id": "zorjkloedvlhoiukrcgszyun"
  },
  {
    "createdAt": 1670527667988,
    "updatedAt": 1670527667988,
    "deletedAt": 0,
    "createdFirstAt": 1670527667988,
    "name": "Div",
    "slug": "div",
    "type": "value",
    "module": "react-with-native",
    "isModuleResolved": true,
    "comments": [],
    "operationRelativeTypescriptFilePath": "src/editors/SmartContentEditableDivInput.tsx",
    "classification": "operation",
    "isAbsolute": true,
    "isModuleFromMonorepo": true,
    "id": "sjbyxzypukztjkiqqdbdwpms"
  },
  {
    "createdAt": 1670527667988,
    "updatedAt": 1670527667988,
    "deletedAt": 0,
    "createdFirstAt": 1670527667988,
    "name": "marked",
    "slug": "marked",
    "module": "marked",
    "isModuleResolved": true,
    "comments": [],
    "operationRelativeTypescriptFilePath": "src/editors/SmartContentEditableDivInput.tsx",
    "classification": "package",
    "isAbsolute": true,
    "isModuleFromMonorepo": false,
    "id": "ascieuirxxvmujgphoigoqec"
  },
  {
    "createdAt": 1670527667989,
    "updatedAt": 1670527667989,
    "deletedAt": 0,
    "createdFirstAt": 1670527667989,
    "name": "WriterType",
    "slug": "writer-type",
    "type": "type",
    "hasGeneric": false,
    "module": "filename-conventions",
    "isModuleResolved": true,
    "comments": [],
    "operationRelativeTypescriptFilePath": "src/editors/SmartContentEditableDivInput.tsx",
    "classification": "operation",
    "isAbsolute": true,
    "isModuleFromMonorepo": true,
    "id": "uxheotezycdpzrrytdanmyis"
  },
  {
    "createdAt": 1670527667989,
    "updatedAt": 1670527667989,
    "deletedAt": 0,
    "createdFirstAt": 1670527667989,
    "name": "MarkdownParseRenderConfig",
    "slug": "markdown-parse-render-config",
    "type": "type",
    "hasGeneric": false,
    "module": "markdown",
    "isModuleResolved": true,
    "comments": [],
    "operationRelativeTypescriptFilePath": "src/editors/SmartContentEditableDivInput.tsx",
    "classification": "operation",
    "isAbsolute": true,
    "isModuleFromMonorepo": true,
    "id": "japtgpnxfzkkmqupytfnsyrf"
  },
  {
    "createdAt": 1670527667989,
    "updatedAt": 1670527667989,
    "deletedAt": 0,
    "createdFirstAt": 1670527667989,
    "name": "SubtextConfig",
    "slug": "subtext-config",
    "type": "type",
    "hasGeneric": false,
    "module": "writer-types",
    "isModuleResolved": true,
    "comments": [],
    "operationRelativeTypescriptFilePath": "src/editors/SmartContentEditableDivInput.tsx",
    "classification": "operation",
    "isAbsolute": true,
    "isModuleFromMonorepo": true,
    "id": "mzlhamfwmtlbazjqkxqdwtgr"
  },
  {
    "createdAt": 1670527667989,
    "updatedAt": 1670527667989,
    "deletedAt": 0,
    "createdFirstAt": 1670527667989,
    "name": "SubwordConfig",
    "slug": "subword-config",
    "type": "type",
    "hasGeneric": false,
    "module": "writer-types",
    "isModuleResolved": true,
    "comments": [],
    "operationRelativeTypescriptFilePath": "src/editors/SmartContentEditableDivInput.tsx",
    "classification": "operation",
    "isAbsolute": true,
    "isModuleFromMonorepo": true,
    "id": "kkvewnnkiqzafwggasyrzsqg"
  },
  {
    "createdAt": 1670527667989,
    "updatedAt": 1670527667989,
    "deletedAt": 0,
    "createdFirstAt": 1670527667989,
    "name": "MarkedToken",
    "slug": "marked-token",
    "module": "./MarkedToken",
    "isModuleResolved": true,
    "comments": [],
    "operationRelativeTypescriptFilePath": "src/editors/SmartContentEditableDivInput.tsx",
    "classification": "internal",
    "isAbsolute": false,
    "isModuleFromMonorepo": false,
    "id": "mngjbmpvhhuzqyixncjtbmkp"
  },
  {
    "createdAt": 1670527667989,
    "updatedAt": 1670527667989,
    "deletedAt": 0,
    "createdFirstAt": 1670527667989,
    "name": "useStore",
    "slug": "use-store",
    "module": "../store",
    "isModuleResolved": true,
    "comments": [],
    "operationRelativeTypescriptFilePath": "src/editors/SmartContentEditableDivInput.tsx",
    "classification": "internal",
    "isAbsolute": false,
    "isModuleFromMonorepo": false,
    "id": "ayebgguhcapgzgyuqddcrhvd"
  },
  {
    "createdAt": 1670527667989,
    "updatedAt": 1670527667989,
    "deletedAt": 0,
    "createdFirstAt": 1670527667989,
    "name": "ContentEditableDivInput",
    "slug": "content-editable-div-input",
    "module": "./ContentEditableDivInput",
    "isModuleResolved": true,
    "comments": [],
    "operationRelativeTypescriptFilePath": "src/editors/SmartContentEditableDivInput.tsx",
    "classification": "internal",
    "isAbsolute": false,
    "isModuleFromMonorepo": false,
    "id": "cntayxswrlonnazibfyjgqgn"
  },
  {
    "createdAt": 1670527667989,
    "updatedAt": 1670527667989,
    "deletedAt": 0,
    "createdFirstAt": 1670527667989,
    "name": "Subword",
    "slug": "subword",
    "module": "./Subword",
    "isModuleResolved": true,
    "comments": [],
    "operationRelativeTypescriptFilePath": "src/editors/SpannedSentence.tsx",
    "classification": "internal",
    "isAbsolute": false,
    "isModuleFromMonorepo": false,
    "id": "lanimcfoweahfslomwxoohqe"
  },
  {
    "createdAt": 1670527667989,
    "updatedAt": 1670527667989,
    "deletedAt": 0,
    "createdFirstAt": 1670527667989,
    "name": "ContentEditableRenderProps",
    "slug": "content-editable-render-props",
    "module": "./types",
    "isModuleResolved": true,
    "comments": [],
    "operationRelativeTypescriptFilePath": "src/editors/SpannedSentence.tsx",
    "classification": "internal",
    "isAbsolute": false,
    "isModuleFromMonorepo": false,
    "id": "pigkjeehwjxcwlsrnrgkhhwz"
  },
  {
    "createdAt": 1670527667990,
    "updatedAt": 1670527667990,
    "deletedAt": 0,
    "createdFirstAt": 1670527667990,
    "name": "SubtextConfig",
    "slug": "subtext-config",
    "type": "type",
    "hasGeneric": false,
    "module": "writer-types",
    "isModuleResolved": true,
    "comments": [],
    "operationRelativeTypescriptFilePath": "src/editors/SubtextContainer.tsx",
    "classification": "operation",
    "isAbsolute": true,
    "isModuleFromMonorepo": true,
    "id": "teogzzwlgqidwzzeashuwxlh"
  },
  {
    "createdAt": 1670527667990,
    "updatedAt": 1670527667990,
    "deletedAt": 0,
    "createdFirstAt": 1670527667990,
    "name": "getSubtext",
    "slug": "get-subtext",
    "module": "./getSubtext",
    "isModuleResolved": true,
    "comments": [],
    "operationRelativeTypescriptFilePath": "src/editors/SubtextContainer.tsx",
    "classification": "internal",
    "isAbsolute": false,
    "isModuleFromMonorepo": false,
    "id": "avlmmdoiiclvmyzghrckiiie"
  },
  {
    "createdAt": 1670527667990,
    "updatedAt": 1670527667990,
    "deletedAt": 0,
    "createdFirstAt": 1670527667990,
    "name": "SubwordConfig",
    "slug": "subword-config",
    "type": "type",
    "hasGeneric": false,
    "module": "writer-types",
    "isModuleResolved": true,
    "comments": [],
    "operationRelativeTypescriptFilePath": "src/editors/Subword.tsx",
    "classification": "operation",
    "isAbsolute": true,
    "isModuleFromMonorepo": true,
    "id": "hqvyvzcjnbapwmhapvukmakx"
  },
  {
    "createdAt": 1670527667990,
    "updatedAt": 1670527667990,
    "deletedAt": 0,
    "createdFirstAt": 1670527667990,
    "name": "MarkedParagraph",
    "slug": "marked-paragraph",
    "module": "./MarkedParagraph",
    "isModuleResolved": true,
    "comments": [],
    "operationRelativeTypescriptFilePath": "src/editors/testAllContentEditableRenderComponents.tsx",
    "classification": "internal",
    "isAbsolute": false,
    "isModuleFromMonorepo": false,
    "id": "lobldssswgyqgkjhqdhaxyiy"
  },
  {
    "createdAt": 1670527667990,
    "updatedAt": 1670527667990,
    "deletedAt": 0,
    "createdFirstAt": 1670527667990,
    "name": "MarkedText",
    "slug": "marked-text",
    "module": "./MarkedText",
    "isModuleResolved": true,
    "comments": [],
    "operationRelativeTypescriptFilePath": "src/editors/testAllContentEditableRenderComponents.tsx",
    "classification": "internal",
    "isAbsolute": false,
    "isModuleFromMonorepo": false,
    "id": "veruuixvjzzcyrkuuepavaux"
  },
  {
    "createdAt": 1670527667990,
    "updatedAt": 1670527667990,
    "deletedAt": 0,
    "createdFirstAt": 1670527667990,
    "name": "testContentEditableRenderComponent",
    "slug": "test-content-editable-render-component",
    "module": "./testContentEditableRenderComponent",
    "isModuleResolved": true,
    "comments": [],
    "operationRelativeTypescriptFilePath": "src/editors/testAllContentEditableRenderComponents.tsx",
    "classification": "internal",
    "isAbsolute": false,
    "isModuleFromMonorepo": false,
    "id": "swgdgofdbikwcnpjtxknzuxa"
  },
  {
    "createdAt": 1670527667990,
    "updatedAt": 1670527667990,
    "deletedAt": 0,
    "createdFirstAt": 1670527667990,
    "name": "ContentEditableRenderComponentType",
    "slug": "content-editable-render-component-type",
    "module": "./types",
    "isModuleResolved": true,
    "comments": [],
    "operationRelativeTypescriptFilePath": "src/editors/testAllContentEditableRenderComponents.tsx",
    "classification": "internal",
    "isAbsolute": false,
    "isModuleFromMonorepo": false,
    "id": "vkvukslscwcfwblajbihzmkf"
  },
  {
    "createdAt": 1670527667990,
    "updatedAt": 1670527667990,
    "deletedAt": 0,
    "createdFirstAt": 1670527667990,
    "name": "SubtextConfig",
    "slug": "subtext-config",
    "type": "type",
    "hasGeneric": false,
    "module": "writer-types",
    "isModuleResolved": true,
    "comments": [],
    "operationRelativeTypescriptFilePath": "src/editors/testContentEditableRenderComponent.tsx",
    "classification": "operation",
    "isAbsolute": true,
    "isModuleFromMonorepo": true,
    "id": "bbqcadaxioszoardixjtwiwv"
  },
  {
    "createdAt": 1670527667990,
    "updatedAt": 1670527667990,
    "deletedAt": 0,
    "createdFirstAt": 1670527667990,
    "name": "SubwordConfig",
    "slug": "subword-config",
    "type": "type",
    "hasGeneric": false,
    "module": "writer-types",
    "isModuleResolved": true,
    "comments": [],
    "operationRelativeTypescriptFilePath": "src/editors/testContentEditableRenderComponent.tsx",
    "classification": "operation",
    "isAbsolute": true,
    "isModuleFromMonorepo": true,
    "id": "weyyxylkonxoxhuzjbpjdipr"
  },
  {
    "createdAt": 1670527667991,
    "updatedAt": 1670527667991,
    "deletedAt": 0,
    "createdFirstAt": 1670527667991,
    "name": "MarkdownParseRenderConfig",
    "slug": "markdown-parse-render-config",
    "type": "type",
    "hasGeneric": false,
    "module": "markdown",
    "isModuleResolved": true,
    "comments": [],
    "operationRelativeTypescriptFilePath": "src/editors/testContentEditableRenderComponent.tsx",
    "classification": "operation",
    "isAbsolute": true,
    "isModuleFromMonorepo": true,
    "id": "ecjkpxjuqxhmtybfmoltswoh"
  },
  {
    "createdAt": 1670527667991,
    "updatedAt": 1670527667991,
    "deletedAt": 0,
    "createdFirstAt": 1670527667991,
    "name": "ContentEditableRenderComponentType",
    "slug": "content-editable-render-component-type",
    "module": "./types",
    "isModuleResolved": true,
    "comments": [],
    "operationRelativeTypescriptFilePath": "src/editors/testContentEditableRenderComponent.tsx",
    "classification": "internal",
    "isAbsolute": false,
    "isModuleFromMonorepo": false,
    "id": "nxzlkcaxxisccnqziuzcpmmt"
  },
  {
    "createdAt": 1670527667991,
    "updatedAt": 1670527667991,
    "deletedAt": 0,
    "createdFirstAt": 1670527667991,
    "name": "marked",
    "slug": "marked",
    "module": "marked",
    "isModuleResolved": true,
    "comments": [],
    "operationRelativeTypescriptFilePath": "src/editors/testContentEditableRenderComponent.tsx",
    "classification": "package",
    "isAbsolute": true,
    "isModuleFromMonorepo": false,
    "id": "yglmdvmsexydvjuwzhwzsugf"
  },
  {
    "createdAt": 1670527667991,
    "updatedAt": 1670527667991,
    "deletedAt": 0,
    "createdFirstAt": 1670527667991,
    "name": "MarkdownParseRenderConfig",
    "slug": "markdown-parse-render-config",
    "type": "type",
    "hasGeneric": false,
    "module": "markdown",
    "isModuleResolved": true,
    "comments": [],
    "operationRelativeTypescriptFilePath": "src/editors/types.ts",
    "classification": "operation",
    "isAbsolute": true,
    "isModuleFromMonorepo": true,
    "id": "ntqgsvcozcudszxucusentet"
  },
  {
    "createdAt": 1670527667991,
    "updatedAt": 1670527667991,
    "deletedAt": 0,
    "createdFirstAt": 1670527667991,
    "name": "marked",
    "slug": "marked",
    "module": "marked",
    "isModuleResolved": true,
    "comments": [],
    "operationRelativeTypescriptFilePath": "src/editors/types.ts",
    "classification": "package",
    "isAbsolute": true,
    "isModuleFromMonorepo": false,
    "id": "ravkjnutwbkomldnholdvplr"
  },
  {
    "createdAt": 1670527667991,
    "updatedAt": 1670527667991,
    "deletedAt": 0,
    "createdFirstAt": 1670527667991,
    "name": "SubtextConfig",
    "slug": "subtext-config",
    "type": "type",
    "hasGeneric": false,
    "module": "writer-types",
    "isModuleResolved": true,
    "comments": [],
    "operationRelativeTypescriptFilePath": "src/editors/types.ts",
    "classification": "operation",
    "isAbsolute": true,
    "isModuleFromMonorepo": true,
    "id": "hoachaxypxnqlvlmmtibrvfy"
  },
  {
    "createdAt": 1670527667991,
    "updatedAt": 1670527667991,
    "deletedAt": 0,
    "createdFirstAt": 1670527667991,
    "name": "SubwordConfig",
    "slug": "subword-config",
    "type": "type",
    "hasGeneric": false,
    "module": "writer-types",
    "isModuleResolved": true,
    "comments": [],
    "operationRelativeTypescriptFilePath": "src/editors/types.ts",
    "classification": "operation",
    "isAbsolute": true,
    "isModuleFromMonorepo": true,
    "id": "idwjijyvoyhwfpdygyyzeggw"
  },
  {
    "createdAt": 1670527667991,
    "updatedAt": 1670527667991,
    "deletedAt": 0,
    "createdFirstAt": 1670527667991,
    "name": "useLastSelection",
    "slug": "use-last-selection",
    "type": "value",
    "module": "share",
    "isModuleResolved": true,
    "comments": [],
    "operationRelativeTypescriptFilePath": "src/old/ContextTextArea.tsx",
    "classification": "operation",
    "isAbsolute": true,
    "isModuleFromMonorepo": true,
    "id": "bmpudzfhmfckmqjzikojmzxf"
  },
  {
    "createdAt": 1670527667992,
    "updatedAt": 1670527667992,
    "deletedAt": 0,
    "createdFirstAt": 1670527667992,
    "name": "useAlert",
    "slug": "use-alert",
    "type": "value",
    "module": "react-with-native-alert",
    "isModuleResolved": true,
    "comments": [],
    "operationRelativeTypescriptFilePath": "src/old/ContextTextArea.tsx",
    "classification": "operation",
    "isAbsolute": true,
    "isModuleFromMonorepo": true,
    "id": "psixsdvzydqmujbxqmgpqwuv"
  },
  {
    "createdAt": 1670527667992,
    "updatedAt": 1670527667992,
    "deletedAt": 0,
    "createdFirstAt": 1670527667992,
    "name": "useHotkeys",
    "slug": "use-hotkeys",
    "type": "value",
    "module": "hotkeys",
    "isModuleResolved": true,
    "comments": [],
    "operationRelativeTypescriptFilePath": "src/old/ContextTextArea.tsx",
    "classification": "operation",
    "isAbsolute": true,
    "isModuleFromMonorepo": true,
    "id": "jryubyyanowmzdbbdwpqfxjj"
  },
  {
    "createdAt": 1670527667992,
    "updatedAt": 1670527667992,
    "deletedAt": 0,
    "createdFirstAt": 1670527667992,
    "name": "EditorProps",
    "slug": "editor-props",
    "module": "./types",
    "isModuleResolved": true,
    "comments": [],
    "operationRelativeTypescriptFilePath": "src/old/ContextTextArea.tsx",
    "classification": "internal",
    "isAbsolute": false,
    "isModuleFromMonorepo": false,
    "id": "cfgnyliqwgeqayjtrqazdapx"
  },
  {
    "createdAt": 1670527667992,
    "updatedAt": 1670527667992,
    "deletedAt": 0,
    "createdFirstAt": 1670527667992,
    "name": "getContext",
    "slug": "get-context",
    "module": "./getContext",
    "isModuleResolved": true,
    "comments": [],
    "operationRelativeTypescriptFilePath": "src/old/ContextTextArea.tsx",
    "classification": "internal",
    "isAbsolute": false,
    "isModuleFromMonorepo": false,
    "id": "trlflhtdlqsvhdomlfdushci"
  },
  {
    "createdAt": 1670527667992,
    "updatedAt": 1670527667992,
    "deletedAt": 0,
    "createdFirstAt": 1670527667992,
    "name": "queries",
    "slug": "queries",
    "type": "value",
    "module": "api",
    "isModuleResolved": true,
    "comments": [],
    "operationRelativeTypescriptFilePath": "src/old/ContextTextArea.tsx",
    "classification": "operation",
    "isAbsolute": true,
    "isModuleFromMonorepo": true,
    "id": "ccmbasnysecfxfqvefixczbm"
  },
  {
    "createdAt": 1670527667992,
    "updatedAt": 1670527667992,
    "deletedAt": 0,
    "createdFirstAt": 1670527667992,
    "name": "getFileTypeFromPath",
    "slug": "get-file-type-from-path",
    "type": "value",
    "module": "filename-conventions",
    "isModuleResolved": true,
    "comments": [],
    "operationRelativeTypescriptFilePath": "src/old/ContextTextArea.tsx",
    "classification": "operation",
    "isAbsolute": true,
    "isModuleFromMonorepo": true,
    "id": "jhekmdyozkqvxaniygjnhmhs"
  },
  {
    "createdAt": 1670527667992,
    "updatedAt": 1670527667992,
    "deletedAt": 0,
    "createdFirstAt": 1670527667992,
    "name": "useSelectionPromptsMenu",
    "slug": "use-selection-prompts-menu",
    "type": "value",
    "module": "prompt-components",
    "isModuleResolved": true,
    "comments": [],
    "operationRelativeTypescriptFilePath": "src/old/ContextTextArea.tsx",
    "classification": "operation",
    "isAbsolute": true,
    "isModuleFromMonorepo": true,
    "id": "wfbzvwaszicxcxmebzzoxupc"
  },
  {
    "createdAt": 1670527667992,
    "updatedAt": 1670527667992,
    "deletedAt": 0,
    "createdFirstAt": 1670527667992,
    "name": "useEffect",
    "slug": "use-effect",
    "module": "react",
    "isModuleResolved": true,
    "comments": [],
    "operationRelativeTypescriptFilePath": "src/old/DivContentEditable.tsx",
    "classification": "react",
    "isAbsolute": true,
    "isModuleFromMonorepo": false,
    "id": "kyujkulipxqavfexjxylknwd"
  },
  {
    "createdAt": 1670527667992,
    "updatedAt": 1670527667992,
    "deletedAt": 0,
    "createdFirstAt": 1670527667992,
    "name": "useRef",
    "slug": "use-ref",
    "module": "react",
    "isModuleResolved": true,
    "comments": [],
    "operationRelativeTypescriptFilePath": "src/old/DivContentEditable.tsx",
    "classification": "react",
    "isAbsolute": true,
    "isModuleFromMonorepo": false,
    "id": "nqhnlbvliokzyivqksbizelg"
  },
  {
    "createdAt": 1670527667993,
    "updatedAt": 1670527667993,
    "deletedAt": 0,
    "createdFirstAt": 1670527667993,
    "name": "Div",
    "slug": "div",
    "type": "value",
    "module": "react-with-native",
    "isModuleResolved": true,
    "comments": [],
    "operationRelativeTypescriptFilePath": "src/old/DivContentEditable.tsx",
    "classification": "operation",
    "isAbsolute": true,
    "isModuleFromMonorepo": true,
    "id": "kttbeytsbcscvxbdnztntprb"
  },
  {
    "createdAt": 1670527667993,
    "updatedAt": 1670527667993,
    "deletedAt": 0,
    "createdFirstAt": 1670527667993,
    "name": "EditorProps",
    "slug": "editor-props",
    "module": "./types",
    "isModuleResolved": true,
    "comments": [],
    "operationRelativeTypescriptFilePath": "src/old/DivContentEditable.tsx",
    "classification": "internal",
    "isAbsolute": false,
    "isModuleFromMonorepo": false,
    "id": "qnfbptdhgyfjdjnthernqret"
  },
  {
    "createdAt": 1670527667993,
    "updatedAt": 1670527667993,
    "deletedAt": 0,
    "createdFirstAt": 1670527667993,
    "name": "getContext",
    "slug": "get-context",
    "module": "./getContext",
    "isModuleResolved": true,
    "comments": [],
    "operationRelativeTypescriptFilePath": "src/old/DivContentEditable.tsx",
    "classification": "internal",
    "isAbsolute": false,
    "isModuleFromMonorepo": false,
    "id": "gtkpzktrldhcedlspxfeqkmv"
  },
  {
    "createdAt": 1670527667993,
    "updatedAt": 1670527667993,
    "deletedAt": 0,
    "createdFirstAt": 1670527667993,
    "name": "TextEditingContext",
    "slug": "text-editing-context",
    "module": "./getContext",
    "isModuleResolved": true,
    "comments": [],
    "operationRelativeTypescriptFilePath": "src/old/types.ts",
    "classification": "internal",
    "isAbsolute": false,
    "isModuleFromMonorepo": false,
    "id": "szaeviadneulfczwuycdrifj"
  },
  {
    "createdAt": 1670527667993,
    "updatedAt": 1670527667993,
    "deletedAt": 0,
    "createdFirstAt": 1670527667993,
    "name": "WriterType",
    "slug": "writer-type",
    "type": "type",
    "hasGeneric": false,
    "module": "filename-conventions",
    "isModuleResolved": true,
    "comments": [],
    "operationRelativeTypescriptFilePath": "src/util/getWriterTypeFromContent.ts",
    "classification": "operation",
    "isAbsolute": true,
    "isModuleFromMonorepo": true,
    "id": "mrwkuwskqjspunxlnzgdbrte"
  },
  {
    "createdAt": 1670527667993,
    "updatedAt": 1670527667993,
    "deletedAt": 0,
    "createdFirstAt": 1670527667993,
    "name": "tryParseJson",
    "slug": "try-parse-json",
    "type": "value",
    "module": "try-parse-json",
    "isModuleResolved": true,
    "comments": [],
    "operationRelativeTypescriptFilePath": "src/util/getWriterTypeFromContent.ts",
    "classification": "operation",
    "isAbsolute": true,
    "isModuleFromMonorepo": true,
    "id": "bmkpjyjdwsutjvvtrjoubawi"
  },
  {
    "createdAt": 1670527667993,
    "updatedAt": 1670527667993,
    "deletedAt": 0,
    "createdFirstAt": 1670527667993,
    "name": "isTypescript",
    "slug": "is-typescript",
    "module": "./isTypescript",
    "isModuleResolved": true,
    "comments": [],
    "operationRelativeTypescriptFilePath": "src/util/getWriterTypeFromContent.ts",
    "classification": "internal",
    "isAbsolute": false,
    "isModuleFromMonorepo": false,
    "id": "xwykqedpshflntwrmagzqmwy"
  }
]