{
  "createdAt": 1664525322153,
  "updatedAt": 1668237137932,
  "deletedAt": 0,
  "createdFirstAt": 1664525322153,
  "indexInteracesErrors": "[\"No schema/definitions found for /Users/king/King/operations/tools/control-project/explore-project/src/exploreProject.ts. Error: Error: No overload matches this call.\\n  Overload 1 of 2, '(...items: ConcatArray<TextJson>[]): TextJson[]', gave the following error.\\n    Property 'isFolder' is missing in type '{ path: string; }' but required in type 'TextJson'.\\n  Overload 2 of 2, '(...items: (TextJson | ConcatArray<TextJson>)[]): TextJson[]', gave the following error.\\n    Property 'isFolder' is missing in type '{ path: string; }' but required in type 'TextJson'.\\n\\nNo overload matches this call.\\n  Overload 1 of 2, '(...items: ConcatArray<TextJson>[]): TextJson[]', gave the following error.\\n    Property 'isFolder' is missing in type '{ path: string; }' but required in type 'TextJson'.\\n  Overload 2 of 2, '(...items: (TextJson | ConcatArray<TextJson>)[]): TextJson[]', gave the following error.\\n    Property 'isFolder' is missing in type '{ path: string; }' but required in type 'TextJson'.\"]",
  "buildSucceeded": true,
  "id": "zznerxornjyqbrlabyiolyii",
  "indexImportExportError": "",
  "lintProblems": [],
  "folderName": "explore-project",
  "packageName": "explore-project",
  "relativeOperationLocationPath": "operations/tools/control-project",
  "classification": "node",
  "name": "explore-project",
  "slug": "explore-project",
  "coreDependencies": [],
  "operationDependencies": [
    "path",
    "explore",
    "getBundleSummary",
    "BundleSummary",
    "explore",
    "exploreOperationFolders",
    "pathArrayIsOperation",
    "getLastFolder",
    "path",
    "getPathsWithOperations",
    "getProjectRoot",
    "getRootPath",
    "db",
    "FolderExploration",
    "notEmpty",
    "databaseFolderName",
    "ExplorationDetails",
    "FolderExploration",
    "OperationIndex",
    "calculatePathMetaData",
    "getLastFolder",
    "path",
    "findOperationBasePath",
    "readMarkdownFile",
    "getFolderTypescriptIndex",
    "IndexFilter",
    "readJsonFile",
    "db",
    "IndexModels",
    "getProjectRoot",
    "databaseFolderName",
    "FolderExploration",
    "path",
    "writeToAssets",
    "databaseFolderName",
    "generatedFolders",
    "path",
    "getProjectRoot",
    "getRootPath",
    "makeRelative",
    "destructureOptionalObject",
    "explore",
    "findAllTodoFolderPaths",
    "path",
    "TsIndexModelType"
  ],
  "packageDependencies": [],
  "size": {
    "codeSize": {
      "numberOfFiles": 8,
      "lines": 0,
      "characters": 19756,
      "bytes": 19756
    },
    "dataSize": {
      "numberOfFiles": 3,
      "lines": 0,
      "characters": 1176074,
      "bytes": 1176074
    },
    "textSize": {
      "numberOfFiles": 2,
      "lines": 0,
      "characters": 6817,
      "bytes": 6817
    },
    "size": {
      "bytes": 1202647,
      "characters": 1202647,
      "lines": 0,
      "numberOfFiles": 13
    }
  }
}