[
  {
    "createdAt": 1669384287902,
    "updatedAt": 1669384287902,
    "deletedAt": 0,
    "createdFirstAt": 1669384287902,
    "name": "exploreOperation",
    "slug": "explore-operation",
    "operationRelativeTypescriptFilePath": "src/exploreOperation.ts",
    "comments": [],
    "type": "value",
    "id": "uarwyhljqpliaacvsixpuely"
  },
  {
    "createdAt": 1669384287902,
    "updatedAt": 1669384287902,
    "deletedAt": 0,
    "createdFirstAt": 1669384287902,
    "name": "exploreProject",
    "slug": "explore-project",
    "operationRelativeTypescriptFilePath": "src/exploreProject.ts",
    "comments": [],
    "type": "value",
    "id": "fapsjcgfvymhdfiezctangey"
  },
  {
    "createdAt": 1669384287902,
    "updatedAt": 1669384287902,
    "deletedAt": 0,
    "createdFirstAt": 1669384287902,
    "name": "getFolderExplorationDetails",
    "slug": "get-folder-exploration-details",
    "operationRelativeTypescriptFilePath": "src/getFolderExplorationDetails.ts",
    "comments": [],
    "type": "value",
    "id": "muqmjcbjqnuvecbsfzodsqvv"
  },
  {
    "createdAt": 1669384287902,
    "updatedAt": 1669384287902,
    "deletedAt": 0,
    "createdFirstAt": 1669384287902,
    "name": "getFrontmattersMappedObject",
    "slug": "get-frontmatters-mapped-object",
    "operationRelativeTypescriptFilePath": "src/getFrontmattersMappedObject.ts",
    "comments": [],
    "type": "value",
    "id": "wkyqscrgutjmfmraagkpfzlc"
  },
  {
    "createdAt": 1669384287902,
    "updatedAt": 1669384287902,
    "deletedAt": 0,
    "createdFirstAt": 1669384287902,
    "name": "getExplorationType",
    "slug": "get-exploration-type",
    "operationRelativeTypescriptFilePath": "src/getOperationType.ts",
    "comments": [],
    "type": "value",
    "id": "mynywbjuljkrrmxgestwvfyg"
  },
  {
    "createdAt": 1669384287902,
    "updatedAt": 1669384287902,
    "deletedAt": 0,
    "createdFirstAt": 1669384287902,
    "name": "RelativePathType",
    "slug": "relative-path-type",
    "operationRelativeTypescriptFilePath": "src/getProjectRelativePaths.ts",
    "comments": [],
    "type": "type",
    "hasGeneric": false,
    "id": "wowytvghrmajkusynjrddvvn"
  },
  {
    "createdAt": 1669384287902,
    "updatedAt": 1669384287902,
    "deletedAt": 0,
    "createdFirstAt": 1669384287902,
    "name": "getProjectRelativePaths",
    "slug": "get-project-relative-paths",
    "operationRelativeTypescriptFilePath": "src/getProjectRelativePaths.ts",
    "comments": [],
    "type": "value",
    "id": "aiepwfnjqwnrlvjhteofmynz"
  },
  {
    "createdAt": 1669384287903,
    "updatedAt": 1669384287903,
    "deletedAt": 0,
    "createdFirstAt": 1669384287903,
    "name": "getTodoPages",
    "slug": "get-todo-pages",
    "operationRelativeTypescriptFilePath": "src/getTodoPages.ts",
    "comments": [],
    "type": "value",
    "id": "meykpfjefsxgarzstvetouhi"
  },
  {
    "createdAt": 1669384287903,
    "updatedAt": 1669384287903,
    "deletedAt": 0,
    "createdFirstAt": 1669384287903,
    "name": "getTodoPaths",
    "slug": "get-todo-paths",
    "operationRelativeTypescriptFilePath": "src/getTodoPaths.ts",
    "comments": [],
    "type": "value",
    "id": "mhpiepkftvqxgyzsvyirsrlp"
  },
  {
    "createdAt": 1669384287903,
    "updatedAt": 1669384287903,
    "deletedAt": 0,
    "createdFirstAt": 1669384287903,
    "name": "exploreOperation",
    "slug": "explore-operation",
    "operationRelativeTypescriptFilePath": "src/index.ts",
    "comments": [],
    "type": "value",
    "id": "avkkmcsfzkoqbivqkofxafrg"
  },
  {
    "createdAt": 1669384287903,
    "updatedAt": 1669384287903,
    "deletedAt": 0,
    "createdFirstAt": 1669384287903,
    "name": "exploreProject",
    "slug": "explore-project",
    "operationRelativeTypescriptFilePath": "src/index.ts",
    "comments": [],
    "type": "value",
    "id": "uwjhkgvexwmdpvlbsadzkrjc"
  },
  {
    "createdAt": 1669384287903,
    "updatedAt": 1669384287903,
    "deletedAt": 0,
    "createdFirstAt": 1669384287903,
    "name": "getFolderExplorationDetails",
    "slug": "get-folder-exploration-details",
    "operationRelativeTypescriptFilePath": "src/index.ts",
    "comments": [],
    "type": "value",
    "id": "kzsgjlymlobznzmzjchwkdqx"
  },
  {
    "createdAt": 1669384287903,
    "updatedAt": 1669384287903,
    "deletedAt": 0,
    "createdFirstAt": 1669384287903,
    "name": "getExplorationType",
    "slug": "get-exploration-type",
    "operationRelativeTypescriptFilePath": "src/index.ts",
    "comments": [],
    "type": "value",
    "id": "lxktieqyiwlcbnztsbrequrb"
  },
  {
    "createdAt": 1669384287903,
    "updatedAt": 1669384287903,
    "deletedAt": 0,
    "createdFirstAt": 1669384287903,
    "name": "RelativePathType",
    "slug": "relative-path-type",
    "operationRelativeTypescriptFilePath": "src/index.ts",
    "comments": [],
    "type": "type",
    "hasGeneric": false,
    "id": "gtiwxudabsmxwztdfaasltta"
  },
  {
    "createdAt": 1669384287903,
    "updatedAt": 1669384287903,
    "deletedAt": 0,
    "createdFirstAt": 1669384287903,
    "name": "getProjectRelativePaths",
    "slug": "get-project-relative-paths",
    "operationRelativeTypescriptFilePath": "src/index.ts",
    "comments": [],
    "type": "value",
    "id": "cxfkuwerpfdoscmmwazuskdn"
  },
  {
    "createdAt": 1669384287903,
    "updatedAt": 1669384287903,
    "deletedAt": 0,
    "createdFirstAt": 1669384287903,
    "name": "getFrontmattersMappedObject",
    "slug": "get-frontmatters-mapped-object",
    "operationRelativeTypescriptFilePath": "src/index.ts",
    "comments": [],
    "type": "value",
    "id": "wumklkfpzyvbflpqpcuhfuro"
  },
  {
    "createdAt": 1669384287903,
    "updatedAt": 1669384287903,
    "deletedAt": 0,
    "createdFirstAt": 1669384287903,
    "name": "getTodoPages",
    "slug": "get-todo-pages",
    "operationRelativeTypescriptFilePath": "src/index.ts",
    "comments": [],
    "type": "value",
    "id": "lgxgznvqzxpejijbrzimrjoe"
  },
  {
    "createdAt": 1669384287903,
    "updatedAt": 1669384287903,
    "deletedAt": 0,
    "createdFirstAt": 1669384287903,
    "name": "getTodoPaths",
    "slug": "get-todo-paths",
    "operationRelativeTypescriptFilePath": "src/index.ts",
    "comments": [],
    "type": "value",
    "id": "pwpwxrjaiqyvbpoyfjppcztm"
  },
  {
    "createdAt": 1669384287903,
    "updatedAt": 1669384287903,
    "deletedAt": 0,
    "createdFirstAt": 1669384287903,
    "name": "getInstanceNames",
    "slug": "get-instance-names",
    "operationRelativeTypescriptFilePath": "src/index.ts",
    "comments": [],
    "type": "value",
    "id": "parsxyuhrsqtgfxxwucwlwcq"
  },
  {
    "createdAt": 1669384287903,
    "updatedAt": 1669384287903,
    "deletedAt": 0,
    "createdFirstAt": 1669384287903,
    "name": "hasSameProjectPath",
    "slug": "has-same-project-path",
    "operationRelativeTypescriptFilePath": "src/index.ts",
    "comments": [],
    "type": "value",
    "id": "kdjiavgjuuhiqzxjxepctdbk"
  },
  {
    "createdAt": 1669384287903,
    "updatedAt": 1669384287903,
    "deletedAt": 0,
    "createdFirstAt": 1669384287903,
    "name": "getFileWithExtension",
    "slug": "get-file-with-extension",
    "operationRelativeTypescriptFilePath": "src/index.ts",
    "comments": [],
    "type": "value",
    "id": "trbmvusirepmlwgxmkupqjcn"
  },
  {
    "createdAt": 1669384287903,
    "updatedAt": 1669384287903,
    "deletedAt": 0,
    "createdFirstAt": 1669384287903,
    "name": "getInstanceNames",
    "slug": "get-instance-names",
    "operationRelativeTypescriptFilePath": "src/util.ts",
    "comments": [],
    "type": "value",
    "id": "usnboywkkjvhnaiogepjuxqn"
  },
  {
    "createdAt": 1669384287903,
    "updatedAt": 1669384287903,
    "deletedAt": 0,
    "createdFirstAt": 1669384287903,
    "name": "hasSameProjectPath",
    "slug": "has-same-project-path",
    "operationRelativeTypescriptFilePath": "src/util.ts",
    "comments": [],
    "type": "value",
    "id": "qymmlrjbkzbtaiugxlqnpnbg"
  },
  {
    "createdAt": 1669384287903,
    "updatedAt": 1669384287903,
    "deletedAt": 0,
    "createdFirstAt": 1669384287903,
    "name": "getFileWithExtension",
    "slug": "get-file-with-extension",
    "operationRelativeTypescriptFilePath": "src/util.ts",
    "comments": [],
    "type": "value",
    "id": "puqbljyivfnlzzszvkhghovy"
  }
]