[
  {
    "createdAt": 1668332045213,
    "updatedAt": 1668332045213,
    "deletedAt": 0,
    "createdFirstAt": 1668332045213,
    "name": "allOperationsRemoveJsSrc",
    "slug": "all-operations-remove-js-src",
    "operationRelativeTypescriptFilePath": "src/allOperationsRemoveJsSrc.ts",
    "comments": [],
    "type": "value",
    "id": "knpvkllflrwiyviljmousayl"
  },
  {
    "createdAt": 1668332045213,
    "updatedAt": 1668332045213,
    "deletedAt": 0,
    "createdFirstAt": 1668332045213,
    "name": "allOperationsToMarkdown",
    "slug": "all-operations-to-markdown",
    "operationRelativeTypescriptFilePath": "src/allOperationsToMarkdown.ts",
    "comments": [],
    "type": "value",
    "id": "dzqxwkpvqiqubjtcqbtlivlu"
  },
  {
    "createdAt": 1668332045213,
    "updatedAt": 1668332045213,
    "deletedAt": 0,
    "createdFirstAt": 1668332045213,
    "name": "clearAllTsDatabases",
    "slug": "clear-all-ts-databases",
    "operationRelativeTypescriptFilePath": "src/clearAllTsDatabases.ts",
    "comments": [],
    "type": "value",
    "id": "pkkdomlafywfnjoomxkbydti"
  },
  {
    "createdAt": 1668332045214,
    "updatedAt": 1668332045214,
    "deletedAt": 0,
    "createdFirstAt": 1668332045214,
    "name": "codeAll",
    "slug": "code-all",
    "operationRelativeTypescriptFilePath": "src/codeAll.ts",
    "comments": [],
    "type": "value",
    "id": "ibuukwimxkmndgjzmanqdmrq"
  },
  {
    "createdAt": 1668332045214,
    "updatedAt": 1668332045214,
    "deletedAt": 0,
    "createdFirstAt": 1668332045214,
    "name": "ForAllFilesConfig",
    "slug": "for-all-files-config",
    "operationRelativeTypescriptFilePath": "src/forAllFiles.ts",
    "comments": [],
    "type": "type",
    "hasGeneric": false,
    "id": "jnvcdfajtcdqkpdjwftfpyki"
  },
  {
    "createdAt": 1668332045214,
    "updatedAt": 1668332045214,
    "deletedAt": 0,
    "createdFirstAt": 1668332045214,
    "name": "forAllFiles",
    "slug": "for-all-files",
    "operationRelativeTypescriptFilePath": "src/forAllFiles.ts",
    "comments": [],
    "type": "value",
    "id": "pqfuweffglsozgbvuckmpnhd"
  },
  {
    "createdAt": 1668332045214,
    "updatedAt": 1668332045214,
    "deletedAt": 0,
    "createdFirstAt": 1668332045214,
    "name": "DirectoryType",
    "slug": "directory-type",
    "operationRelativeTypescriptFilePath": "src/forAllFolders.ts",
    "comments": [],
    "type": "type",
    "hasGeneric": false,
    "id": "wdmhrvwzyptelhrwcbqphmyf"
  },
  {
    "createdAt": 1668332045214,
    "updatedAt": 1668332045214,
    "deletedAt": 0,
    "createdFirstAt": 1668332045214,
    "name": "AllInputType",
    "slug": "all-input-type",
    "operationRelativeTypescriptFilePath": "src/forAllFolders.ts",
    "comments": [],
    "type": "type",
    "hasGeneric": false,
    "id": "lwyixrdapwcoocwvcclzfnod"
  },
  {
    "createdAt": 1668332045214,
    "updatedAt": 1668332045214,
    "deletedAt": 0,
    "createdFirstAt": 1668332045214,
    "name": "forAllFolders",
    "slug": "for-all-folders",
    "operationRelativeTypescriptFilePath": "src/forAllFolders.ts",
    "comments": [],
    "type": "value",
    "id": "qfjtheypeijdibovotcraund"
  },
  {
    "createdAt": 1668332045214,
    "updatedAt": 1668332045214,
    "deletedAt": 0,
    "createdFirstAt": 1668332045214,
    "name": "getAllOperationClassifications",
    "slug": "get-all-operation-classifications",
    "operationRelativeTypescriptFilePath": "src/getAllOperationClassifications.ts",
    "comments": [],
    "type": "value",
    "id": "wmpakxrepeeiehxdzilksqfi"
  },
  {
    "createdAt": 1668332045214,
    "updatedAt": 1668332045214,
    "deletedAt": 0,
    "createdFirstAt": 1668332045214,
    "name": "gitShipAllRepos",
    "slug": "git-ship-all-repos",
    "operationRelativeTypescriptFilePath": "src/gitShipAllRepos.ts",
    "comments": [],
    "type": "value",
    "id": "geilkirwuniadydjawuatqta"
  },
  {
    "createdAt": 1668332045214,
    "updatedAt": 1668332045214,
    "deletedAt": 0,
    "createdFirstAt": 1668332045214,
    "name": "allOperationsRemoveJsSrc",
    "slug": "all-operations-remove-js-src",
    "operationRelativeTypescriptFilePath": "src/index.ts",
    "comments": [],
    "type": "value",
    "id": "dvhrwztkjgdoknyicoqlcyut"
  },
  {
    "createdAt": 1668332045214,
    "updatedAt": 1668332045214,
    "deletedAt": 0,
    "createdFirstAt": 1668332045214,
    "name": "allOperationsToMarkdown",
    "slug": "all-operations-to-markdown",
    "operationRelativeTypescriptFilePath": "src/index.ts",
    "comments": [],
    "type": "value",
    "id": "qxyaxprtlzkleremgeuxcvdy"
  },
  {
    "createdAt": 1668332045214,
    "updatedAt": 1668332045214,
    "deletedAt": 0,
    "createdFirstAt": 1668332045214,
    "name": "clearAllTsDatabases",
    "slug": "clear-all-ts-databases",
    "operationRelativeTypescriptFilePath": "src/index.ts",
    "comments": [],
    "type": "value",
    "id": "tmidhbeaqvitjzwxdvebhrvy"
  },
  {
    "createdAt": 1668332045214,
    "updatedAt": 1668332045214,
    "deletedAt": 0,
    "createdFirstAt": 1668332045214,
    "name": "codeAll",
    "slug": "code-all",
    "operationRelativeTypescriptFilePath": "src/index.ts",
    "comments": [],
    "type": "value",
    "id": "tmereeaqqynyfrbxwcilssjx"
  },
  {
    "createdAt": 1668332045214,
    "updatedAt": 1668332045214,
    "deletedAt": 0,
    "createdFirstAt": 1668332045214,
    "name": "ForAllFilesConfig",
    "slug": "for-all-files-config",
    "operationRelativeTypescriptFilePath": "src/index.ts",
    "comments": [],
    "type": "type",
    "hasGeneric": false,
    "id": "gqrmrokuobgcgalbktorrind"
  },
  {
    "createdAt": 1668332045214,
    "updatedAt": 1668332045214,
    "deletedAt": 0,
    "createdFirstAt": 1668332045214,
    "name": "forAllFiles",
    "slug": "for-all-files",
    "operationRelativeTypescriptFilePath": "src/index.ts",
    "comments": [],
    "type": "value",
    "id": "saalgvhdrwivkxupbelqazlm"
  },
  {
    "createdAt": 1668332045214,
    "updatedAt": 1668332045214,
    "deletedAt": 0,
    "createdFirstAt": 1668332045214,
    "name": "DirectoryType",
    "slug": "directory-type",
    "operationRelativeTypescriptFilePath": "src/index.ts",
    "comments": [],
    "type": "type",
    "hasGeneric": false,
    "id": "fbinmyohvromnhnnafybfbek"
  },
  {
    "createdAt": 1668332045214,
    "updatedAt": 1668332045214,
    "deletedAt": 0,
    "createdFirstAt": 1668332045214,
    "name": "AllInputType",
    "slug": "all-input-type",
    "operationRelativeTypescriptFilePath": "src/index.ts",
    "comments": [],
    "type": "type",
    "hasGeneric": false,
    "id": "nbthshcrdcvodpcslfhahqls"
  },
  {
    "createdAt": 1668332045214,
    "updatedAt": 1668332045214,
    "deletedAt": 0,
    "createdFirstAt": 1668332045214,
    "name": "forAllFolders",
    "slug": "for-all-folders",
    "operationRelativeTypescriptFilePath": "src/index.ts",
    "comments": [],
    "type": "value",
    "id": "ifmtwigvziqvdukhnlgrxwle"
  },
  {
    "createdAt": 1668332045214,
    "updatedAt": 1668332045214,
    "deletedAt": 0,
    "createdFirstAt": 1668332045214,
    "name": "getAllOperationClassifications",
    "slug": "get-all-operation-classifications",
    "operationRelativeTypescriptFilePath": "src/index.ts",
    "comments": [],
    "type": "value",
    "id": "gswcfwvbldcxpzcfbtbiavfu"
  },
  {
    "createdAt": 1668332045214,
    "updatedAt": 1668332045214,
    "deletedAt": 0,
    "createdFirstAt": 1668332045214,
    "name": "gitShipAllRepos",
    "slug": "git-ship-all-repos",
    "operationRelativeTypescriptFilePath": "src/index.ts",
    "comments": [],
    "type": "value",
    "id": "exdlevmwauhthtootyzstvnx"
  },
  {
    "createdAt": 1668332045214,
    "updatedAt": 1668332045214,
    "deletedAt": 0,
    "createdFirstAt": 1668332045214,
    "name": "mdAllOperations",
    "slug": "md-all-operations",
    "operationRelativeTypescriptFilePath": "src/index.ts",
    "comments": [],
    "type": "value",
    "id": "hbarmcdapldbvltkxecpxkkd"
  },
  {
    "createdAt": 1668332045214,
    "updatedAt": 1668332045214,
    "deletedAt": 0,
    "createdFirstAt": 1668332045214,
    "name": "minifyAllOperations",
    "slug": "minify-all-operations",
    "operationRelativeTypescriptFilePath": "src/index.ts",
    "comments": [],
    "type": "value",
    "id": "jqtvkbrudkaiueunvgoncast"
  },
  {
    "createdAt": 1668332045215,
    "updatedAt": 1668332045215,
    "deletedAt": 0,
    "createdFirstAt": 1668332045215,
    "name": "publishAllOperations",
    "slug": "publish-all-operations",
    "operationRelativeTypescriptFilePath": "src/index.ts",
    "comments": [],
    "type": "value",
    "id": "vihkbtbhiorleqsrfqtjiwjv"
  },
  {
    "createdAt": 1668332045215,
    "updatedAt": 1668332045215,
    "deletedAt": 0,
    "createdFirstAt": 1668332045215,
    "name": "removeAll",
    "slug": "remove-all",
    "operationRelativeTypescriptFilePath": "src/index.ts",
    "comments": [],
    "type": "value",
    "id": "ogqbkpokuazmcjfauxpqjhlb"
  },
  {
    "createdAt": 1668332045215,
    "updatedAt": 1668332045215,
    "deletedAt": 0,
    "createdFirstAt": 1668332045215,
    "name": "removeAllFiles",
    "slug": "remove-all-files",
    "operationRelativeTypescriptFilePath": "src/index.ts",
    "comments": [],
    "type": "value",
    "id": "tgmzxhrneapiteaizocnirtz"
  },
  {
    "createdAt": 1668332045215,
    "updatedAt": 1668332045215,
    "deletedAt": 0,
    "createdFirstAt": 1668332045215,
    "name": "removeAllFolders",
    "slug": "remove-all-folders",
    "operationRelativeTypescriptFilePath": "src/index.ts",
    "comments": [],
    "type": "value",
    "id": "aczgmltoqkbrzsifluhumgfs"
  },
  {
    "createdAt": 1668332045215,
    "updatedAt": 1668332045215,
    "deletedAt": 0,
    "createdFirstAt": 1668332045215,
    "name": "renameAll",
    "slug": "rename-all",
    "operationRelativeTypescriptFilePath": "src/index.ts",
    "comments": [],
    "type": "value",
    "id": "cixtllboxgjklaebmaqwasot"
  },
  {
    "createdAt": 1668332045215,
    "updatedAt": 1668332045215,
    "deletedAt": 0,
    "createdFirstAt": 1668332045215,
    "name": "runScriptEverywhere",
    "slug": "run-script-everywhere",
    "operationRelativeTypescriptFilePath": "src/index.ts",
    "comments": [],
    "type": "value",
    "id": "joypykbulvxfldbledeqvfgc"
  },
  {
    "createdAt": 1668332045215,
    "updatedAt": 1668332045215,
    "deletedAt": 0,
    "createdFirstAt": 1668332045215,
    "name": "setScriptEverywhere",
    "slug": "set-script-everywhere",
    "operationRelativeTypescriptFilePath": "src/index.ts",
    "comments": [],
    "type": "value",
    "id": "bmyapjitmrsvhalnnnsztkjd"
  },
  {
    "createdAt": 1668332045215,
    "updatedAt": 1668332045215,
    "deletedAt": 0,
    "createdFirstAt": 1668332045215,
    "name": "mdAllOperations",
    "slug": "md-all-operations",
    "operationRelativeTypescriptFilePath": "src/mdAllOperations.ts",
    "comments": [],
    "type": "value",
    "id": "fewtjmcllptwfnfegwjxrgfd"
  },
  {
    "createdAt": 1668332045215,
    "updatedAt": 1668332045215,
    "deletedAt": 0,
    "createdFirstAt": 1668332045215,
    "name": "minifyAllOperations",
    "slug": "minify-all-operations",
    "operationRelativeTypescriptFilePath": "src/minifyAllOperations.ts",
    "comments": [],
    "type": "value",
    "id": "yecdhviarchftlswialmitin"
  },
  {
    "createdAt": 1668332045215,
    "updatedAt": 1668332045215,
    "deletedAt": 0,
    "createdFirstAt": 1668332045215,
    "name": "publishAllOperations",
    "slug": "publish-all-operations",
    "operationRelativeTypescriptFilePath": "src/publishAllOperations.ts",
    "comments": [],
    "type": "value",
    "id": "ztybhitqozctkhweezckuhia"
  },
  {
    "createdAt": 1668332045215,
    "updatedAt": 1668332045215,
    "deletedAt": 0,
    "createdFirstAt": 1668332045215,
    "name": "removeAll",
    "slug": "remove-all",
    "operationRelativeTypescriptFilePath": "src/removeAll.ts",
    "comments": [],
    "type": "value",
    "id": "fspnvksfthkvmrjjrpuidewc"
  },
  {
    "createdAt": 1668332045215,
    "updatedAt": 1668332045215,
    "deletedAt": 0,
    "createdFirstAt": 1668332045215,
    "name": "removeAllFiles",
    "slug": "remove-all-files",
    "operationRelativeTypescriptFilePath": "src/removeAllFiles.ts",
    "comments": [],
    "type": "value",
    "id": "lltssuvbyskeekongpnxkjhb"
  },
  {
    "createdAt": 1668332045215,
    "updatedAt": 1668332045215,
    "deletedAt": 0,
    "createdFirstAt": 1668332045215,
    "name": "removeAllFolders",
    "slug": "remove-all-folders",
    "operationRelativeTypescriptFilePath": "src/removeAllFolders.ts",
    "comments": [],
    "type": "value",
    "id": "gbkumhlysahgseggluhekrjw"
  },
  {
    "createdAt": 1668332045215,
    "updatedAt": 1668332045215,
    "deletedAt": 0,
    "createdFirstAt": 1668332045215,
    "name": "renameAll",
    "slug": "rename-all",
    "operationRelativeTypescriptFilePath": "src/renameAll.ts",
    "comments": [],
    "type": "value",
    "id": "olwqocoqpynysvfceurplhdf"
  },
  {
    "createdAt": 1668332045215,
    "updatedAt": 1668332045215,
    "deletedAt": 0,
    "createdFirstAt": 1668332045215,
    "name": "runScriptEverywhere",
    "slug": "run-script-everywhere",
    "operationRelativeTypescriptFilePath": "src/runScriptEverywhere.ts",
    "comments": [],
    "type": "value",
    "id": "fowagaohaobnjqkokvwoqobu"
  },
  {
    "createdAt": 1668332045215,
    "updatedAt": 1668332045215,
    "deletedAt": 0,
    "createdFirstAt": 1668332045215,
    "name": "setScriptEverywhere",
    "slug": "set-script-everywhere",
    "operationRelativeTypescriptFilePath": "src/setScriptEverywhere.ts",
    "comments": [],
    "type": "value",
    "id": "hpibqfmscnqulfjshntrdwac"
  },
  {
    "createdAt": 1668332045215,
    "updatedAt": 1668332045215,
    "deletedAt": 0,
    "createdFirstAt": 1668332045215,
    "name": "test",
    "slug": "test",
    "operationRelativeTypescriptFilePath": "src/test.ts",
    "comments": [],
    "type": "value",
    "id": "emccfqhedhlzbobjwahzwtfa"
  }
]