{"indexInteracesErrors":"[\"Error: Unknown node \\\"new (props: P) => Component<P, any>\"]","indexImportExportError":"\"\"","updatedAt":1661278244618,"folderName":"react-with-native-notification","packageName":"react-with-native-notification","relativeOperationLocationPath":"/tools/ui/react-with-native","classification":"ui-es5","coreDependencies":[],"operationDependencies":[],"packageDependencies":["toast","ToastOptions","ToastContainer","ToastOptions"],"size":{"codeSize":{"numberOfFiles":2,"lines":38,"characters":889,"bytes":889},"dataSize":{"numberOfFiles":2,"lines":81,"characters":2976,"bytes":2976},"textSize":null,"size":{"bytes":3865,"characters":3865,"lines":119,"numberOfFiles":4}}}