[
  {
    "createdAt": 1670589839543,
    "updatedAt": 1670589839543,
    "deletedAt": 0,
    "createdFirstAt": 1670589839543,
    "name": "findFolderWhereMatch",
    "slug": "find-folder-where-match",
    "operationRelativeTypescriptFilePath": "src/findFolderWhereMatch.ts",
    "comments": [],
    "type": "value",
    "id": "gzhrlckfhanvekxwdjssupfl"
  },
  {
    "createdAt": 1670589839544,
    "updatedAt": 1670589839544,
    "deletedAt": 0,
    "createdFirstAt": 1670589839544,
    "name": "findOperationBasePathWithClassification",
    "slug": "find-operation-base-path-with-classification",
    "operationRelativeTypescriptFilePath": "src/findOperationBasePath.ts",
    "comments": [],
    "type": "value",
    "id": "zzyvstdlxzwircpxusynrodo"
  },
  {
    "createdAt": 1670589839544,
    "updatedAt": 1670589839544,
    "deletedAt": 0,
    "createdFirstAt": 1670589839544,
    "name": "findOperationBasePath",
    "slug": "find-operation-base-path",
    "operationRelativeTypescriptFilePath": "src/findOperationBasePath.ts",
    "comments": [],
    "type": "value",
    "id": "bmbsxfuprkupxduigniluoka"
  },
  {
    "createdAt": 1670589839544,
    "updatedAt": 1670589839544,
    "deletedAt": 0,
    "createdFirstAt": 1670589839544,
    "name": "getAllPackageJsonDependencies",
    "slug": "get-all-package-json-dependencies",
    "operationRelativeTypescriptFilePath": "src/getAllPackageJsonDependencies.ts",
    "comments": [],
    "type": "value",
    "id": "bdfxdcrrkmbtrrthveeykzjv"
  },
  {
    "createdAt": 1670589839544,
    "updatedAt": 1670589839544,
    "deletedAt": 0,
    "createdFirstAt": 1670589839544,
    "name": "getCommonAncestor",
    "slug": "get-common-ancestor",
    "operationRelativeTypescriptFilePath": "src/getCommonAncestor.ts",
    "comments": [],
    "type": "value",
    "id": "pnwbsuoalwyhqpawyjbelmqj"
  },
  {
    "createdAt": 1670589839544,
    "updatedAt": 1670589839544,
    "deletedAt": 0,
    "createdFirstAt": 1670589839544,
    "name": "packageCompilesTs",
    "slug": "package-compiles-ts",
    "operationRelativeTypescriptFilePath": "src/getOperationClassification.ts",
    "comments": [],
    "type": "value",
    "id": "esdlrttqwiastaylklqdtdxx"
  },
  {
    "createdAt": 1670589839544,
    "updatedAt": 1670589839544,
    "deletedAt": 0,
    "createdFirstAt": 1670589839544,
    "name": "tsconfigCompilesEsm",
    "slug": "tsconfig-compiles-esm",
    "operationRelativeTypescriptFilePath": "src/getOperationClassification.ts",
    "comments": [],
    "type": "value",
    "id": "mpuhadnlhcbungqotocfhysy"
  },
  {
    "createdAt": 1670589839544,
    "updatedAt": 1670589839544,
    "deletedAt": 0,
    "createdFirstAt": 1670589839544,
    "name": "isUiOperation",
    "slug": "is-ui-operation",
    "operationRelativeTypescriptFilePath": "src/getOperationClassification.ts",
    "comments": [],
    "type": "value",
    "id": "hojgrbwrldxatkgmmhfglpvy"
  },
  {
    "createdAt": 1670589839544,
    "updatedAt": 1670589839544,
    "deletedAt": 0,
    "createdFirstAt": 1670589839544,
    "name": "getOperationClassification",
    "slug": "get-operation-classification",
    "operationRelativeTypescriptFilePath": "src/getOperationClassification.ts",
    "comments": [],
    "type": "value",
    "id": "qnxkyrcgyifixbsvmowrbxwz"
  },
  {
    "createdAt": 1670589839544,
    "updatedAt": 1670589839544,
    "deletedAt": 0,
    "createdFirstAt": 1670589839544,
    "name": "OperationClassificationObject",
    "slug": "operation-classification-object",
    "operationRelativeTypescriptFilePath": "src/getOperationClassificationObject.ts",
    "comments": [],
    "type": "value",
    "id": "bmjsaylkywakuqhqfyabbira"
  },
  {
    "createdAt": 1670589839545,
    "updatedAt": 1670589839545,
    "deletedAt": 0,
    "createdFirstAt": 1670589839545,
    "name": "getOperationClassificationObject",
    "slug": "get-operation-classification-object",
    "operationRelativeTypescriptFilePath": "src/getOperationClassificationObject.ts",
    "comments": [],
    "type": "value",
    "id": "trqrqihriysajxjcakttrduz"
  },
  {
    "createdAt": 1670589839545,
    "updatedAt": 1670589839545,
    "deletedAt": 0,
    "createdFirstAt": 1670589839545,
    "name": "getOperationPath",
    "slug": "get-operation-path",
    "operationRelativeTypescriptFilePath": "src/getOperationPath.ts",
    "comments": [],
    "type": "value",
    "id": "zjbmnkoofvytknpoduzcumfl"
  },
  {
    "createdAt": 1670589839545,
    "updatedAt": 1670589839545,
    "deletedAt": 0,
    "createdFirstAt": 1670589839545,
    "name": "getOperationPathParse",
    "slug": "get-operation-path-parse",
    "operationRelativeTypescriptFilePath": "src/getOperationPathParse.ts",
    "comments": [],
    "type": "value",
    "id": "fwluueliwwwpmkpsiegsmlae"
  },
  {
    "createdAt": 1670589839545,
    "updatedAt": 1670589839545,
    "deletedAt": 0,
    "createdFirstAt": 1670589839545,
    "name": "getOperationRelativePath",
    "slug": "get-operation-relative-path",
    "operationRelativeTypescriptFilePath": "src/getOperationRelativePath.ts",
    "comments": [],
    "type": "value",
    "id": "nsjtfjasecyxciguwcdfkbmj"
  },
  {
    "createdAt": 1670589839545,
    "updatedAt": 1670589839545,
    "deletedAt": 0,
    "createdFirstAt": 1670589839545,
    "name": "getPathParse",
    "slug": "get-path-parse",
    "operationRelativeTypescriptFilePath": "src/getPathParse.ts",
    "comments": [],
    "type": "value",
    "id": "kcykaxcphpirnzhefxiirscn"
  },
  {
    "createdAt": 1670589839545,
    "updatedAt": 1670589839545,
    "deletedAt": 0,
    "createdFirstAt": 1670589839545,
    "name": "getPathsWithOperations",
    "slug": "get-paths-with-operations",
    "operationRelativeTypescriptFilePath": "src/getPathsWithOperations.ts",
    "comments": [],
    "type": "value",
    "id": "mprriizzcodmmryjcgizzqnf"
  },
  {
    "createdAt": 1670589839545,
    "updatedAt": 1670589839545,
    "deletedAt": 0,
    "createdFirstAt": 1670589839545,
    "name": "getProjectRoot",
    "slug": "get-project-root",
    "operationRelativeTypescriptFilePath": "src/getProjectRoot.ts",
    "comments": [],
    "type": "value",
    "id": "awxekkeipynhzxboevfqklra"
  },
  {
    "createdAt": 1670589839545,
    "updatedAt": 1670589839545,
    "deletedAt": 0,
    "createdFirstAt": 1670589839545,
    "name": "getRelativeLinkPath",
    "slug": "get-relative-link-path",
    "operationRelativeTypescriptFilePath": "src/getRelativeLinkPath.ts",
    "comments": [],
    "type": "value",
    "id": "fsgrbkumfwcozmyercxrppyf"
  },
  {
    "createdAt": 1670589839546,
    "updatedAt": 1670589839546,
    "deletedAt": 0,
    "createdFirstAt": 1670589839546,
    "name": "getRelativePath",
    "slug": "get-relative-path",
    "operationRelativeTypescriptFilePath": "src/getRelativePath.ts",
    "comments": [],
    "type": "value",
    "id": "ufyziwwcikaiejezoktutvwk"
  },
  {
    "createdAt": 1670589839546,
    "updatedAt": 1670589839546,
    "deletedAt": 0,
    "createdFirstAt": 1670589839546,
    "name": "osRootFoldersConst",
    "slug": "os-root-folders-const",
    "operationRelativeTypescriptFilePath": "src/getRootPath.ts",
    "comments": [],
    "type": "value",
    "id": "hkgiaggeqxdrlwnfilugmfee"
  },
  {
    "createdAt": 1670589839546,
    "updatedAt": 1670589839546,
    "deletedAt": 0,
    "createdFirstAt": 1670589839546,
    "name": "projectRootFoldersConst",
    "slug": "project-root-folders-const",
    "operationRelativeTypescriptFilePath": "src/getRootPath.ts",
    "comments": [],
    "type": "value",
    "id": "qfewdlpyrudasbjzqaexykam"
  },
  {
    "createdAt": 1670589839546,
    "updatedAt": 1670589839546,
    "deletedAt": 0,
    "createdFirstAt": 1670589839546,
    "name": "projectRootFolders",
    "slug": "project-root-folders",
    "operationRelativeTypescriptFilePath": "src/getRootPath.ts",
    "comments": [],
    "type": "value",
    "id": "ghnvivjpobekjgvzwisicibr"
  },
  {
    "createdAt": 1670589839546,
    "updatedAt": 1670589839546,
    "deletedAt": 0,
    "createdFirstAt": 1670589839546,
    "name": "osRootFolders",
    "slug": "os-root-folders",
    "operationRelativeTypescriptFilePath": "src/getRootPath.ts",
    "comments": [],
    "type": "value",
    "id": "yfpcyqhumlaximgkmrykyail"
  },
  {
    "createdAt": 1670589839546,
    "updatedAt": 1670589839546,
    "deletedAt": 0,
    "createdFirstAt": 1670589839546,
    "name": "OSRootFolder",
    "slug": "osroot-folder",
    "operationRelativeTypescriptFilePath": "src/getRootPath.ts",
    "comments": [],
    "type": "value",
    "id": "gnhwpdkbynhavqicxcnmihad"
  },
  {
    "createdAt": 1670589839546,
    "updatedAt": 1670589839546,
    "deletedAt": 0,
    "createdFirstAt": 1670589839546,
    "name": "ProjectRootFolder",
    "slug": "project-root-folder",
    "operationRelativeTypescriptFilePath": "src/getRootPath.ts",
    "comments": [],
    "type": "value",
    "id": "pfhgtqfnvidhkwbebhkdspzl"
  },
  {
    "createdAt": 1670589839546,
    "updatedAt": 1670589839546,
    "deletedAt": 0,
    "createdFirstAt": 1670589839546,
    "name": "getRootPath",
    "slug": "get-root-path",
    "operationRelativeTypescriptFilePath": "src/getRootPath.ts",
    "comments": [],
    "type": "value",
    "id": "qrowemlwwxpokauyauhnqkre"
  },
  {
    "createdAt": 1670589839546,
    "updatedAt": 1670589839546,
    "deletedAt": 0,
    "createdFirstAt": 1670589839546,
    "name": "getSrcRelativeFileId",
    "slug": "get-src-relative-file-id",
    "operationRelativeTypescriptFilePath": "src/getSrcRelativeFileId.ts",
    "comments": [],
    "type": "value",
    "id": "ealuelwkyeeqvphrfxsffvkp"
  },
  {
    "createdAt": 1670589839547,
    "updatedAt": 1670589839547,
    "deletedAt": 0,
    "createdFirstAt": 1670589839547,
    "name": "hasDependency",
    "slug": "has-dependency",
    "operationRelativeTypescriptFilePath": "src/hasDependency.ts",
    "comments": [],
    "type": "value",
    "id": "kdtavlylmidlctvvnhugrbcv"
  },
  {
    "createdAt": 1670589839547,
    "updatedAt": 1670589839547,
    "deletedAt": 0,
    "createdFirstAt": 1670589839547,
    "name": "findFolderWhereMatch",
    "slug": "find-folder-where-match",
    "operationRelativeTypescriptFilePath": "src/index.ts",
    "comments": [],
    "type": "value",
    "id": "vniuasdrrkljxaxjsgyolptb"
  },
  {
    "createdAt": 1670589839547,
    "updatedAt": 1670589839547,
    "deletedAt": 0,
    "createdFirstAt": 1670589839547,
    "name": "findOperationBasePathWithClassification",
    "slug": "find-operation-base-path-with-classification",
    "operationRelativeTypescriptFilePath": "src/index.ts",
    "comments": [],
    "type": "value",
    "id": "leyyfpfwknzwczfzcpriwvjp"
  },
  {
    "createdAt": 1670589839547,
    "updatedAt": 1670589839547,
    "deletedAt": 0,
    "createdFirstAt": 1670589839547,
    "name": "findOperationBasePath",
    "slug": "find-operation-base-path",
    "operationRelativeTypescriptFilePath": "src/index.ts",
    "comments": [],
    "type": "value",
    "id": "fvjdvpwxcnwszvckjllnvojk"
  },
  {
    "createdAt": 1670589839547,
    "updatedAt": 1670589839547,
    "deletedAt": 0,
    "createdFirstAt": 1670589839547,
    "name": "getAllPackageJsonDependencies",
    "slug": "get-all-package-json-dependencies",
    "operationRelativeTypescriptFilePath": "src/index.ts",
    "comments": [],
    "type": "value",
    "id": "ugnmwgdhoayrraaswhncdnxg"
  },
  {
    "createdAt": 1670589839547,
    "updatedAt": 1670589839547,
    "deletedAt": 0,
    "createdFirstAt": 1670589839547,
    "name": "getCommonAncestor",
    "slug": "get-common-ancestor",
    "operationRelativeTypescriptFilePath": "src/index.ts",
    "comments": [],
    "type": "value",
    "id": "eisuqoaqcuuazfllytmbppvj"
  },
  {
    "createdAt": 1670589839547,
    "updatedAt": 1670589839547,
    "deletedAt": 0,
    "createdFirstAt": 1670589839547,
    "name": "packageCompilesTs",
    "slug": "package-compiles-ts",
    "operationRelativeTypescriptFilePath": "src/index.ts",
    "comments": [],
    "type": "value",
    "id": "xttxklqqxxcknmnpsktdzahs"
  },
  {
    "createdAt": 1670589839547,
    "updatedAt": 1670589839547,
    "deletedAt": 0,
    "createdFirstAt": 1670589839547,
    "name": "tsconfigCompilesEsm",
    "slug": "tsconfig-compiles-esm",
    "operationRelativeTypescriptFilePath": "src/index.ts",
    "comments": [],
    "type": "value",
    "id": "xljfhuyphufnqqxjefultrer"
  },
  {
    "createdAt": 1670589839548,
    "updatedAt": 1670589839548,
    "deletedAt": 0,
    "createdFirstAt": 1670589839548,
    "name": "isUiOperation",
    "slug": "is-ui-operation",
    "operationRelativeTypescriptFilePath": "src/index.ts",
    "comments": [],
    "type": "value",
    "id": "odawfnveqbafchfpctmrhnmz"
  },
  {
    "createdAt": 1670589839548,
    "updatedAt": 1670589839548,
    "deletedAt": 0,
    "createdFirstAt": 1670589839548,
    "name": "getOperationClassification",
    "slug": "get-operation-classification",
    "operationRelativeTypescriptFilePath": "src/index.ts",
    "comments": [],
    "type": "value",
    "id": "khhqlmzhvmrcmfumbblpzyuk"
  },
  {
    "createdAt": 1670589839548,
    "updatedAt": 1670589839548,
    "deletedAt": 0,
    "createdFirstAt": 1670589839548,
    "name": "OperationClassificationObject",
    "slug": "operation-classification-object",
    "operationRelativeTypescriptFilePath": "src/index.ts",
    "comments": [],
    "type": "value",
    "id": "unfkblzeqqkdxevdkypwbumx"
  },
  {
    "createdAt": 1670589839548,
    "updatedAt": 1670589839548,
    "deletedAt": 0,
    "createdFirstAt": 1670589839548,
    "name": "getOperationClassificationObject",
    "slug": "get-operation-classification-object",
    "operationRelativeTypescriptFilePath": "src/index.ts",
    "comments": [],
    "type": "value",
    "id": "raihhrxuwvdozruwcxzxvdek"
  },
  {
    "createdAt": 1670589839548,
    "updatedAt": 1670589839548,
    "deletedAt": 0,
    "createdFirstAt": 1670589839548,
    "name": "getOperationPath",
    "slug": "get-operation-path",
    "operationRelativeTypescriptFilePath": "src/index.ts",
    "comments": [],
    "type": "value",
    "id": "lvygqblunafoiaoukizwqdhh"
  },
  {
    "createdAt": 1670589839548,
    "updatedAt": 1670589839548,
    "deletedAt": 0,
    "createdFirstAt": 1670589839548,
    "name": "getOperationPathParse",
    "slug": "get-operation-path-parse",
    "operationRelativeTypescriptFilePath": "src/index.ts",
    "comments": [],
    "type": "value",
    "id": "cbbxcmzwcfkjlzwjwjehlhvy"
  },
  {
    "createdAt": 1670589839548,
    "updatedAt": 1670589839548,
    "deletedAt": 0,
    "createdFirstAt": 1670589839548,
    "name": "getOperationRelativePath",
    "slug": "get-operation-relative-path",
    "operationRelativeTypescriptFilePath": "src/index.ts",
    "comments": [],
    "type": "value",
    "id": "vckslobupeqghfooaoxoerfi"
  },
  {
    "createdAt": 1670589839548,
    "updatedAt": 1670589839548,
    "deletedAt": 0,
    "createdFirstAt": 1670589839548,
    "name": "getPathParse",
    "slug": "get-path-parse",
    "operationRelativeTypescriptFilePath": "src/index.ts",
    "comments": [],
    "type": "value",
    "id": "oevahrexziktqcpmaropceza"
  },
  {
    "createdAt": 1670589839548,
    "updatedAt": 1670589839548,
    "deletedAt": 0,
    "createdFirstAt": 1670589839548,
    "name": "getPathsWithOperations",
    "slug": "get-paths-with-operations",
    "operationRelativeTypescriptFilePath": "src/index.ts",
    "comments": [],
    "type": "value",
    "id": "tdkyblumqexyyxxbtlnaupfo"
  },
  {
    "createdAt": 1670589839549,
    "updatedAt": 1670589839549,
    "deletedAt": 0,
    "createdFirstAt": 1670589839549,
    "name": "getProjectRoot",
    "slug": "get-project-root",
    "operationRelativeTypescriptFilePath": "src/index.ts",
    "comments": [],
    "type": "value",
    "id": "ilesfwdnbpfpwfiantgealni"
  },
  {
    "createdAt": 1670589839549,
    "updatedAt": 1670589839549,
    "deletedAt": 0,
    "createdFirstAt": 1670589839549,
    "name": "getRelativeLinkPath",
    "slug": "get-relative-link-path",
    "operationRelativeTypescriptFilePath": "src/index.ts",
    "comments": [],
    "type": "value",
    "id": "xqtzqlimhspofdnwwgosqyij"
  },
  {
    "createdAt": 1670589839549,
    "updatedAt": 1670589839549,
    "deletedAt": 0,
    "createdFirstAt": 1670589839549,
    "name": "getRelativePath",
    "slug": "get-relative-path",
    "operationRelativeTypescriptFilePath": "src/index.ts",
    "comments": [],
    "type": "value",
    "id": "yrdigclcjpgfzqpdwovusgtk"
  },
  {
    "createdAt": 1670589839549,
    "updatedAt": 1670589839549,
    "deletedAt": 0,
    "createdFirstAt": 1670589839549,
    "name": "osRootFoldersConst",
    "slug": "os-root-folders-const",
    "operationRelativeTypescriptFilePath": "src/index.ts",
    "comments": [],
    "type": "value",
    "id": "tfjfusviymtdfefksskiyzex"
  },
  {
    "createdAt": 1670589839549,
    "updatedAt": 1670589839549,
    "deletedAt": 0,
    "createdFirstAt": 1670589839549,
    "name": "projectRootFoldersConst",
    "slug": "project-root-folders-const",
    "operationRelativeTypescriptFilePath": "src/index.ts",
    "comments": [],
    "type": "value",
    "id": "uzamctzupvkkzoasmbfxdnqe"
  },
  {
    "createdAt": 1670589839549,
    "updatedAt": 1670589839549,
    "deletedAt": 0,
    "createdFirstAt": 1670589839549,
    "name": "projectRootFolders",
    "slug": "project-root-folders",
    "operationRelativeTypescriptFilePath": "src/index.ts",
    "comments": [],
    "type": "value",
    "id": "gwpgodxhkbmknstdjxijntuf"
  },
  {
    "createdAt": 1670589839549,
    "updatedAt": 1670589839549,
    "deletedAt": 0,
    "createdFirstAt": 1670589839549,
    "name": "osRootFolders",
    "slug": "os-root-folders",
    "operationRelativeTypescriptFilePath": "src/index.ts",
    "comments": [],
    "type": "value",
    "id": "iynmdqtyjssocoelzipupwfr"
  },
  {
    "createdAt": 1670589839549,
    "updatedAt": 1670589839549,
    "deletedAt": 0,
    "createdFirstAt": 1670589839549,
    "name": "OSRootFolder",
    "slug": "osroot-folder",
    "operationRelativeTypescriptFilePath": "src/index.ts",
    "comments": [],
    "type": "value",
    "id": "goukyhwjsastzgyknjtdtkdj"
  },
  {
    "createdAt": 1670589839550,
    "updatedAt": 1670589839550,
    "deletedAt": 0,
    "createdFirstAt": 1670589839550,
    "name": "ProjectRootFolder",
    "slug": "project-root-folder",
    "operationRelativeTypescriptFilePath": "src/index.ts",
    "comments": [],
    "type": "value",
    "id": "xddtxxgjhjoaqksgyyyxxflv"
  },
  {
    "createdAt": 1670589839550,
    "updatedAt": 1670589839550,
    "deletedAt": 0,
    "createdFirstAt": 1670589839550,
    "name": "getRootPath",
    "slug": "get-root-path",
    "operationRelativeTypescriptFilePath": "src/index.ts",
    "comments": [],
    "type": "value",
    "id": "ilbwysfyyuaftasmdcaxjxbk"
  },
  {
    "createdAt": 1670589839550,
    "updatedAt": 1670589839550,
    "deletedAt": 0,
    "createdFirstAt": 1670589839550,
    "name": "getSrcRelativeFileId",
    "slug": "get-src-relative-file-id",
    "operationRelativeTypescriptFilePath": "src/index.ts",
    "comments": [],
    "type": "value",
    "id": "nhkmssbcthmbypyveeduzttm"
  },
  {
    "createdAt": 1670589839550,
    "updatedAt": 1670589839550,
    "deletedAt": 0,
    "createdFirstAt": 1670589839550,
    "name": "hasDependency",
    "slug": "has-dependency",
    "operationRelativeTypescriptFilePath": "src/index.ts",
    "comments": [],
    "type": "value",
    "id": "njdqrmwbrjiduwdohkznwxzq"
  },
  {
    "createdAt": 1670589839550,
    "updatedAt": 1670589839550,
    "deletedAt": 0,
    "createdFirstAt": 1670589839550,
    "name": "isBundle",
    "slug": "is-bundle",
    "operationRelativeTypescriptFilePath": "src/index.ts",
    "comments": [],
    "type": "value",
    "id": "wbfbcrctvpuqlrwmfkksdtpu"
  },
  {
    "createdAt": 1670589839550,
    "updatedAt": 1670589839550,
    "deletedAt": 0,
    "createdFirstAt": 1670589839550,
    "name": "isOperation",
    "slug": "is-operation",
    "operationRelativeTypescriptFilePath": "src/index.ts",
    "comments": [],
    "type": "value",
    "id": "uzgibrrcflqqnteuqaibnvol"
  },
  {
    "createdAt": 1670589839550,
    "updatedAt": 1670589839550,
    "deletedAt": 0,
    "createdFirstAt": 1670589839550,
    "name": "isWorkspaceRoot",
    "slug": "is-workspace-root",
    "operationRelativeTypescriptFilePath": "src/index.ts",
    "comments": [],
    "type": "value",
    "id": "ijqtonadjvqbzremafnjvnwu"
  },
  {
    "createdAt": 1670589839550,
    "updatedAt": 1670589839550,
    "deletedAt": 0,
    "createdFirstAt": 1670589839550,
    "name": "makeRelative",
    "slug": "make-relative",
    "operationRelativeTypescriptFilePath": "src/index.ts",
    "comments": [],
    "type": "value",
    "id": "wkptptwvrpgablfpjbfcseou"
  },
  {
    "createdAt": 1670589839552,
    "updatedAt": 1670589839552,
    "deletedAt": 0,
    "createdFirstAt": 1670589839552,
    "name": "isBundle",
    "slug": "is-bundle",
    "operationRelativeTypescriptFilePath": "src/isBundle.ts",
    "comments": [],
    "type": "value",
    "id": "ycbgdonnggjvwveewajooicv"
  },
  {
    "createdAt": 1670589839552,
    "updatedAt": 1670589839552,
    "deletedAt": 0,
    "createdFirstAt": 1670589839552,
    "name": "isOperation",
    "slug": "is-operation",
    "operationRelativeTypescriptFilePath": "src/isOperation.ts",
    "comments": [],
    "type": "value",
    "id": "wtmkyyeglqvvtebjprcoebfn"
  },
  {
    "createdAt": 1670589839552,
    "updatedAt": 1670589839552,
    "deletedAt": 0,
    "createdFirstAt": 1670589839552,
    "name": "isWorkspaceRoot",
    "slug": "is-workspace-root",
    "operationRelativeTypescriptFilePath": "src/isWorkspaceRoot.ts",
    "comments": [],
    "type": "value",
    "id": "xtwsvkldglfbmjjkyzauyttu"
  },
  {
    "createdAt": 1670589839552,
    "updatedAt": 1670589839552,
    "deletedAt": 0,
    "createdFirstAt": 1670589839552,
    "name": "makeRelative",
    "slug": "make-relative",
    "operationRelativeTypescriptFilePath": "src/makeRelative.ts",
    "comments": [],
    "type": "value",
    "id": "ikzimbtshfxbsiaxuzclwuel"
  }
]