[
  {
    "createdAt": 1667818163678,
    "updatedAt": 1667818163678,
    "deletedAt": 0,
    "createdFirstAt": 1667818163678,
    "name": "copyAllRelativeFiles",
    "slug": "copy-all-relative-files",
    "type": "value",
    "module": "fs-util",
    "isModuleResolved": true,
    "comments": [],
    "operationRelativeTypescriptFilePath": "src/copyStaticAssets.ts",
    "classification": "operation",
    "isAbsolute": true,
    "isModuleFromMonorepo": true,
    "id": "rrzxmmwnqpkjoscurepnnuor"
  },
  {
    "createdAt": 1667818163678,
    "updatedAt": 1667818163678,
    "deletedAt": 0,
    "createdFirstAt": 1667818163678,
    "name": "fs",
    "slug": "fs",
    "type": "value",
    "module": "fs-util",
    "isModuleResolved": true,
    "comments": [],
    "operationRelativeTypescriptFilePath": "src/copyStaticAssets.ts",
    "classification": "operation",
    "isAbsolute": true,
    "isModuleFromMonorepo": true,
    "id": "waoqirqzkewuoylwbpzlmxbx"
  },
  {
    "createdAt": 1667818163678,
    "updatedAt": 1667818163678,
    "deletedAt": 0,
    "createdFirstAt": 1667818163678,
    "name": "path",
    "slug": "path",
    "type": "value",
    "module": "fs-util",
    "isModuleResolved": true,
    "comments": [],
    "operationRelativeTypescriptFilePath": "src/copyStaticAssets.ts",
    "classification": "operation",
    "isAbsolute": true,
    "isModuleFromMonorepo": true,
    "id": "sslqswnrqjkdgwnzfvyqfrzd"
  },
  {
    "createdAt": 1667818163679,
    "updatedAt": 1667818163679,
    "deletedAt": 0,
    "createdFirstAt": 1667818163679,
    "name": "removeAllExcept",
    "slug": "remove-all-except",
    "type": "value",
    "module": "fs-util",
    "isModuleResolved": true,
    "comments": [],
    "operationRelativeTypescriptFilePath": "src/copyStaticAssets.ts",
    "classification": "operation",
    "isAbsolute": true,
    "isModuleFromMonorepo": true,
    "id": "ejvankxiqjswzznrpqfjwwnu"
  },
  {
    "createdAt": 1667818163679,
    "updatedAt": 1667818163679,
    "deletedAt": 0,
    "createdFirstAt": 1667818163679,
    "name": "getOperationPath",
    "slug": "get-operation-path",
    "type": "value",
    "module": "get-path",
    "isModuleResolved": true,
    "comments": [],
    "operationRelativeTypescriptFilePath": "src/copyStaticAssets.ts",
    "classification": "operation",
    "isAbsolute": true,
    "isModuleFromMonorepo": true,
    "id": "pbdruxasnmfsxxnxuopmsxew"
  },
  {
    "createdAt": 1667818163679,
    "updatedAt": 1667818163679,
    "deletedAt": 0,
    "createdFirstAt": 1667818163679,
    "name": "getProjectRoot",
    "slug": "get-project-root",
    "type": "value",
    "module": "get-path",
    "isModuleResolved": true,
    "comments": [],
    "operationRelativeTypescriptFilePath": "src/copyStaticAssets.ts",
    "classification": "operation",
    "isAbsolute": true,
    "isModuleFromMonorepo": true,
    "id": "liarmyzqikyrwqvkmuvxvthu"
  },
  {
    "createdAt": 1667818163679,
    "updatedAt": 1667818163679,
    "deletedAt": 0,
    "createdFirstAt": 1667818163679,
    "name": "makeRelative",
    "slug": "make-relative",
    "type": "value",
    "module": "get-path",
    "isModuleResolved": true,
    "comments": [],
    "operationRelativeTypescriptFilePath": "src/copyStaticAssets.ts",
    "classification": "operation",
    "isAbsolute": true,
    "isModuleFromMonorepo": true,
    "id": "myyczgecxmmtjnuwrtsdftcf"
  },
  {
    "createdAt": 1667818163679,
    "updatedAt": 1667818163679,
    "deletedAt": 0,
    "createdFirstAt": 1667818163679,
    "name": "notEmpty",
    "slug": "not-empty",
    "type": "value",
    "module": "js-util",
    "isModuleResolved": true,
    "comments": [],
    "operationRelativeTypescriptFilePath": "src/copyStaticAssets.ts",
    "classification": "operation",
    "isAbsolute": true,
    "isModuleFromMonorepo": true,
    "id": "emisftlclzuuqglujdkeuomu"
  },
  {
    "createdAt": 1667818163679,
    "updatedAt": 1667818163679,
    "deletedAt": 0,
    "createdFirstAt": 1667818163679,
    "name": "onlyUnique2",
    "slug": "only-unique-2",
    "type": "value",
    "module": "js-util",
    "isModuleResolved": true,
    "comments": [],
    "operationRelativeTypescriptFilePath": "src/copyStaticAssets.ts",
    "classification": "operation",
    "isAbsolute": true,
    "isModuleFromMonorepo": true,
    "id": "exstvgozjpcjxnoekbffszwo"
  },
  {
    "createdAt": 1667818163679,
    "updatedAt": 1667818163679,
    "deletedAt": 0,
    "createdFirstAt": 1667818163679,
    "name": "getMarkdownReferencePaths",
    "slug": "get-markdown-reference-paths",
    "type": "value",
    "module": "markdown-parse-js",
    "isModuleResolved": true,
    "comments": [],
    "operationRelativeTypescriptFilePath": "src/copyStaticAssets.ts",
    "classification": "operation",
    "isAbsolute": true,
    "isModuleFromMonorepo": true,
    "id": "tqouyxabbtrqaeyirncqpaho"
  },
  {
    "createdAt": 1667818163679,
    "updatedAt": 1667818163679,
    "deletedAt": 0,
    "createdFirstAt": 1667818163679,
    "name": "MarkdownReaderPage",
    "slug": "markdown-reader-page",
    "type": "type",
    "hasGeneric": false,
    "module": "markdown-reader-types",
    "isModuleResolved": true,
    "comments": [],
    "operationRelativeTypescriptFilePath": "src/copyStaticAssets.ts",
    "classification": "operation",
    "isAbsolute": true,
    "isModuleFromMonorepo": true,
    "id": "vwueettcapccayzhimdtzfqd"
  },
  {
    "createdAt": 1667818163679,
    "updatedAt": 1667818163679,
    "deletedAt": 0,
    "createdFirstAt": 1667818163679,
    "name": "writeToAssets",
    "slug": "write-to-assets",
    "type": "value",
    "module": "write-to-assets",
    "isModuleResolved": true,
    "comments": [],
    "operationRelativeTypescriptFilePath": "src/getAllMarkdownReaderPages.test.ts",
    "classification": "operation",
    "isAbsolute": true,
    "isModuleFromMonorepo": true,
    "id": "etdjwnmfsygrnnneuqqubxgt"
  },
  {
    "createdAt": 1667818163679,
    "updatedAt": 1667818163679,
    "deletedAt": 0,
    "createdFirstAt": 1667818163679,
    "name": "getAllMarkdownReaderPages",
    "slug": "get-all-markdown-reader-pages",
    "module": "./getAllMarkdownReaderPages",
    "isModuleResolved": true,
    "comments": [],
    "operationRelativeTypescriptFilePath": "src/getAllMarkdownReaderPages.test.ts",
    "classification": "internal",
    "isAbsolute": false,
    "isModuleFromMonorepo": false,
    "id": "lsjtdioalyxsylvwebzkmerq"
  },
  {
    "createdAt": 1667818163679,
    "updatedAt": 1667818163679,
    "deletedAt": 0,
    "createdFirstAt": 1667818163679,
    "name": "getProjectRoot",
    "slug": "get-project-root",
    "type": "value",
    "module": "get-path",
    "isModuleResolved": true,
    "comments": [],
    "operationRelativeTypescriptFilePath": "src/getAllMarkdownReaderPages.ts",
    "classification": "operation",
    "isAbsolute": true,
    "isModuleFromMonorepo": true,
    "id": "vqgktqtbpkvqqlistfispjqo"
  },
  {
    "createdAt": 1667818163680,
    "updatedAt": 1667818163680,
    "deletedAt": 0,
    "createdFirstAt": 1667818163680,
    "name": "MarkdownReaderPage",
    "slug": "markdown-reader-page",
    "type": "type",
    "hasGeneric": false,
    "module": "markdown-reader-types",
    "isModuleResolved": true,
    "comments": [],
    "operationRelativeTypescriptFilePath": "src/getAllMarkdownReaderPages.ts",
    "classification": "operation",
    "isAbsolute": true,
    "isModuleFromMonorepo": true,
    "id": "ehgmtokwtrsnucsmokrvvqtn"
  },
  {
    "createdAt": 1667818163680,
    "updatedAt": 1667818163680,
    "deletedAt": 0,
    "createdFirstAt": 1667818163680,
    "name": "notEmpty",
    "slug": "not-empty",
    "type": "value",
    "module": "js-util",
    "isModuleResolved": true,
    "comments": [],
    "operationRelativeTypescriptFilePath": "src/getAllMarkdownReaderPages.ts",
    "classification": "operation",
    "isAbsolute": true,
    "isModuleFromMonorepo": true,
    "id": "gaugogbigflikpkaldythmjq"
  },
  {
    "createdAt": 1667818163680,
    "updatedAt": 1667818163680,
    "deletedAt": 0,
    "createdFirstAt": 1667818163680,
    "name": "onlyUnique2",
    "slug": "only-unique-2",
    "type": "value",
    "module": "js-util",
    "isModuleResolved": true,
    "comments": [],
    "operationRelativeTypescriptFilePath": "src/getAllMarkdownReaderPages.ts",
    "classification": "operation",
    "isAbsolute": true,
    "isModuleFromMonorepo": true,
    "id": "ddoybrcserhddqycpvuppufx"
  },
  {
    "createdAt": 1667818163680,
    "updatedAt": 1667818163680,
    "deletedAt": 0,
    "createdFirstAt": 1667818163680,
    "name": "findAllDocsFolderPaths",
    "slug": "find-all-docs-folder-paths",
    "type": "value",
    "module": "k-explore",
    "isModuleResolved": true,
    "comments": [],
    "operationRelativeTypescriptFilePath": "src/getAllMarkdownReaderPages.ts",
    "classification": "operation",
    "isAbsolute": true,
    "isModuleFromMonorepo": true,
    "id": "czlczjjokdfzbxoazpbwrtds"
  },
  {
    "createdAt": 1667818163680,
    "updatedAt": 1667818163680,
    "deletedAt": 0,
    "createdFirstAt": 1667818163680,
    "name": "getOperationPages",
    "slug": "get-operation-pages",
    "module": "./getOperationPages",
    "isModuleResolved": true,
    "comments": [],
    "operationRelativeTypescriptFilePath": "src/getAllMarkdownReaderPages.ts",
    "classification": "internal",
    "isAbsolute": false,
    "isModuleFromMonorepo": false,
    "id": "zowgugfbrknxyfsdnbhddngl"
  },
  {
    "createdAt": 1667818163680,
    "updatedAt": 1667818163680,
    "deletedAt": 0,
    "createdFirstAt": 1667818163680,
    "name": "getMarkdownReaderPages",
    "slug": "get-markdown-reader-pages",
    "module": "./getMarkdownReaderPages",
    "isModuleResolved": true,
    "comments": [],
    "operationRelativeTypescriptFilePath": "src/getAllMarkdownReaderPages.ts",
    "classification": "internal",
    "isAbsolute": false,
    "isModuleFromMonorepo": false,
    "id": "gokzillytrebzrvevpsdlfnf"
  },
  {
    "createdAt": 1667818163680,
    "updatedAt": 1667818163680,
    "deletedAt": 0,
    "createdFirstAt": 1667818163680,
    "name": "getTodoPages",
    "slug": "get-todo-pages",
    "module": "./getTodoPages",
    "isModuleResolved": true,
    "comments": [],
    "operationRelativeTypescriptFilePath": "src/getAllMarkdownReaderPages.ts",
    "classification": "internal",
    "isAbsolute": false,
    "isModuleFromMonorepo": false,
    "id": "qsgpnvsckgsysddpndvruzoi"
  },
  {
    "createdAt": 1667818163680,
    "updatedAt": 1667818163680,
    "deletedAt": 0,
    "createdFirstAt": 1667818163680,
    "name": "getMarkdownModelPages",
    "slug": "get-markdown-model-pages",
    "module": "./getMarkdownModelPages",
    "isModuleResolved": true,
    "comments": [],
    "operationRelativeTypescriptFilePath": "src/getAllMarkdownReaderPages.ts",
    "classification": "internal",
    "isAbsolute": false,
    "isModuleFromMonorepo": false,
    "id": "inomrnlmvslvcohxouojrgbe"
  },
  {
    "createdAt": 1667818163680,
    "updatedAt": 1667818163680,
    "deletedAt": 0,
    "createdFirstAt": 1667818163680,
    "name": "readJsonFile",
    "slug": "read-json-file",
    "type": "value",
    "module": "read-json-file",
    "isModuleResolved": true,
    "comments": [],
    "operationRelativeTypescriptFilePath": "src/getAllMarkdownReaderPages.ts",
    "classification": "operation",
    "isAbsolute": true,
    "isModuleFromMonorepo": true,
    "id": "prpsockxqxjomluinxprwauq"
  },
  {
    "createdAt": 1667818163680,
    "updatedAt": 1667818163680,
    "deletedAt": 0,
    "createdFirstAt": 1667818163680,
    "name": "BundleConfig",
    "slug": "bundle-config",
    "type": "type",
    "hasGeneric": false,
    "module": "bundle-types",
    "isModuleResolved": true,
    "comments": [],
    "operationRelativeTypescriptFilePath": "src/getAllMarkdownReaderPages.ts",
    "classification": "operation",
    "isAbsolute": true,
    "isModuleFromMonorepo": true,
    "id": "mjxfenrdazatiakgabyifmdf"
  },
  {
    "createdAt": 1667818163680,
    "updatedAt": 1667818163680,
    "deletedAt": 0,
    "createdFirstAt": 1667818163680,
    "name": "path",
    "slug": "path",
    "type": "value",
    "module": "fs-util",
    "isModuleResolved": true,
    "comments": [],
    "operationRelativeTypescriptFilePath": "src/getAllMarkdownReaderPages.ts",
    "classification": "operation",
    "isAbsolute": true,
    "isModuleFromMonorepo": true,
    "id": "kwowwljrgckmedjuynpkkjkv"
  },
  {
    "createdAt": 1667818163680,
    "updatedAt": 1667818163680,
    "deletedAt": 0,
    "createdFirstAt": 1667818163680,
    "name": "fs",
    "slug": "fs",
    "type": "value",
    "module": "fs-util",
    "isModuleResolved": true,
    "comments": [],
    "operationRelativeTypescriptFilePath": "src/getFolderExplorationInfo.ts",
    "classification": "operation",
    "isAbsolute": true,
    "isModuleFromMonorepo": true,
    "id": "mpvjwndthdqeozobcsouzbrg"
  },
  {
    "createdAt": 1667818163680,
    "updatedAt": 1667818163680,
    "deletedAt": 0,
    "createdFirstAt": 1667818163680,
    "name": "path",
    "slug": "path",
    "type": "value",
    "module": "fs-util",
    "isModuleResolved": true,
    "comments": [],
    "operationRelativeTypescriptFilePath": "src/getFolderExplorationInfo.ts",
    "classification": "operation",
    "isAbsolute": true,
    "isModuleFromMonorepo": true,
    "id": "npfgzoggnnelcqplvznoecdo"
  },
  {
    "createdAt": 1667818163680,
    "updatedAt": 1667818163680,
    "deletedAt": 0,
    "createdFirstAt": 1667818163680,
    "name": "getMarkdownIntro",
    "slug": "get-markdown-intro",
    "type": "value",
    "module": "markdown-parse-js",
    "isModuleResolved": true,
    "comments": [],
    "operationRelativeTypescriptFilePath": "src/getFolderExplorationInfo.ts",
    "classification": "operation",
    "isAbsolute": true,
    "isModuleFromMonorepo": true,
    "id": "buwmxgaevtlyeorlofxpvcmx"
  },
  {
    "createdAt": 1667818163680,
    "updatedAt": 1667818163680,
    "deletedAt": 0,
    "createdFirstAt": 1667818163680,
    "name": "readMarkdownFile",
    "slug": "read-markdown-file",
    "type": "value",
    "module": "read-markdown-file",
    "isModuleResolved": true,
    "comments": [],
    "operationRelativeTypescriptFilePath": "src/getFolderExplorationInfo.ts",
    "classification": "operation",
    "isAbsolute": true,
    "isModuleFromMonorepo": true,
    "id": "whntozqbragynxnscozhgqqq"
  },
  {
    "createdAt": 1667818163680,
    "updatedAt": 1667818163680,
    "deletedAt": 0,
    "createdFirstAt": 1667818163680,
    "name": "getKeysAtPathFromNestedObject",
    "slug": "get-keys-at-path-from-nested-object",
    "type": "value",
    "module": "nested-menu",
    "isModuleResolved": true,
    "comments": [],
    "operationRelativeTypescriptFilePath": "src/getFolderExplorationInfo.ts",
    "classification": "operation",
    "isAbsolute": true,
    "isModuleFromMonorepo": true,
    "id": "pqnbhuwtuwmhhnkvciwaeqgo"
  },
  {
    "createdAt": 1667818163680,
    "updatedAt": 1667818163680,
    "deletedAt": 0,
    "createdFirstAt": 1667818163680,
    "name": "NestedPathObject",
    "slug": "nested-path-object",
    "type": "type",
    "hasGeneric": false,
    "module": "nested-menu",
    "isModuleResolved": true,
    "comments": [],
    "operationRelativeTypescriptFilePath": "src/getFolderExplorationInfo.ts",
    "classification": "operation",
    "isAbsolute": true,
    "isModuleFromMonorepo": true,
    "id": "iovjmqhrbaypqrwljcmhhpej"
  },
  {
    "createdAt": 1667818163680,
    "updatedAt": 1667818163680,
    "deletedAt": 0,
    "createdFirstAt": 1667818163680,
    "name": "QueryConfig",
    "slug": "query-config",
    "type": "type",
    "hasGeneric": false,
    "module": "fs-orm",
    "isModuleResolved": true,
    "comments": [],
    "operationRelativeTypescriptFilePath": "src/getMarkdownModelPages.ts",
    "classification": "operation",
    "isAbsolute": true,
    "isModuleFromMonorepo": true,
    "id": "vzvhjapvmjxawgpunerusnco"
  },
  {
    "createdAt": 1667818163680,
    "updatedAt": 1667818163680,
    "deletedAt": 0,
    "createdFirstAt": 1667818163680,
    "name": "fs",
    "slug": "fs",
    "type": "value",
    "module": "fs-util",
    "isModuleResolved": true,
    "comments": [],
    "operationRelativeTypescriptFilePath": "src/getMarkdownModelPages.ts",
    "classification": "operation",
    "isAbsolute": true,
    "isModuleFromMonorepo": true,
    "id": "zjzonrnkonhajxfiakuplwqg"
  },
  {
    "createdAt": 1667818163680,
    "updatedAt": 1667818163680,
    "deletedAt": 0,
    "createdFirstAt": 1667818163680,
    "name": "path",
    "slug": "path",
    "type": "value",
    "module": "fs-util",
    "isModuleResolved": true,
    "comments": [],
    "operationRelativeTypescriptFilePath": "src/getMarkdownModelPages.ts",
    "classification": "operation",
    "isAbsolute": true,
    "isModuleFromMonorepo": true,
    "id": "irhjrtambrrcfkbkthgaqdnt"
  },
  {
    "createdAt": 1667818163680,
    "updatedAt": 1667818163680,
    "deletedAt": 0,
    "createdFirstAt": 1667818163680,
    "name": "kebabCase",
    "slug": "kebab-case",
    "type": "value",
    "module": "convert-case",
    "isModuleResolved": true,
    "comments": [],
    "operationRelativeTypescriptFilePath": "src/getMarkdownModelPages.ts",
    "classification": "operation",
    "isAbsolute": true,
    "isModuleFromMonorepo": true,
    "id": "pfrlrtyydkuguvxldfhjikeq"
  },
  {
    "createdAt": 1667818163680,
    "updatedAt": 1667818163680,
    "deletedAt": 0,
    "createdFirstAt": 1667818163680,
    "name": "getObjectKeysArray",
    "slug": "get-object-keys-array",
    "type": "value",
    "module": "js-util",
    "isModuleResolved": true,
    "comments": [],
    "operationRelativeTypescriptFilePath": "src/getMarkdownModelPages.ts",
    "classification": "operation",
    "isAbsolute": true,
    "isModuleFromMonorepo": true,
    "id": "mbltliuqqeezagtfbobvsjei"
  },
  {
    "createdAt": 1667818163680,
    "updatedAt": 1667818163680,
    "deletedAt": 0,
    "createdFirstAt": 1667818163680,
    "name": "MarkdownReaderPage",
    "slug": "markdown-reader-page",
    "type": "type",
    "hasGeneric": false,
    "module": "markdown-reader-types",
    "isModuleResolved": true,
    "comments": [],
    "operationRelativeTypescriptFilePath": "src/getMarkdownModelPages.ts",
    "classification": "operation",
    "isAbsolute": true,
    "isModuleFromMonorepo": true,
    "id": "fmoekdfvkgozgtvxtzrxetpv"
  },
  {
    "createdAt": 1667818163681,
    "updatedAt": 1667818163681,
    "deletedAt": 0,
    "createdFirstAt": 1667818163681,
    "name": "modelQueryConfig",
    "slug": "model-query-config",
    "type": "value",
    "module": "sdk-db",
    "isModuleResolved": true,
    "comments": [],
    "operationRelativeTypescriptFilePath": "src/getMarkdownModelPages.ts",
    "classification": "operation",
    "isAbsolute": true,
    "isModuleFromMonorepo": true,
    "id": "udkmsaxqtkknhhtzasurolbt"
  },
  {
    "createdAt": 1667818163681,
    "updatedAt": 1667818163681,
    "deletedAt": 0,
    "createdFirstAt": 1667818163681,
    "name": "pluralize",
    "slug": "pluralize",
    "type": "value",
    "module": "pluralize",
    "isModuleResolved": true,
    "comments": [],
    "operationRelativeTypescriptFilePath": "src/getMarkdownModelPages.ts",
    "classification": "operation",
    "isAbsolute": true,
    "isModuleFromMonorepo": true,
    "id": "awlvmgwgpmljflmthclmdryk"
  },
  {
    "createdAt": 1667818163681,
    "updatedAt": 1667818163681,
    "deletedAt": 0,
    "createdFirstAt": 1667818163681,
    "name": "getMarkdownReaderPages",
    "slug": "get-markdown-reader-pages",
    "module": "./getMarkdownReaderPages",
    "isModuleResolved": true,
    "comments": [],
    "operationRelativeTypescriptFilePath": "src/getMarkdownModelPages.ts",
    "classification": "internal",
    "isAbsolute": false,
    "isModuleFromMonorepo": false,
    "id": "dnqhrvrnqsumhbonhcuricmm"
  },
  {
    "createdAt": 1667818163681,
    "updatedAt": 1667818163681,
    "deletedAt": 0,
    "createdFirstAt": 1667818163681,
    "name": "getOneFolderUpPath",
    "slug": "get-one-folder-up-path",
    "type": "value",
    "module": "fs-util",
    "isModuleResolved": true,
    "comments": [],
    "operationRelativeTypescriptFilePath": "src/getMarkdownPageInfo.ts",
    "classification": "operation",
    "isAbsolute": true,
    "isModuleFromMonorepo": true,
    "id": "umpjwpzttjykfdwbaxxpvmif"
  },
  {
    "createdAt": 1667818163681,
    "updatedAt": 1667818163681,
    "deletedAt": 0,
    "createdFirstAt": 1667818163681,
    "name": "path",
    "slug": "path",
    "type": "value",
    "module": "fs-util",
    "isModuleResolved": true,
    "comments": [],
    "operationRelativeTypescriptFilePath": "src/getMarkdownPageInfo.ts",
    "classification": "operation",
    "isAbsolute": true,
    "isModuleFromMonorepo": true,
    "id": "rjxlodrmqajyhaxxxgrxenvo"
  },
  {
    "createdAt": 1667818163681,
    "updatedAt": 1667818163681,
    "deletedAt": 0,
    "createdFirstAt": 1667818163681,
    "name": "getKeysAtPathFromNestedObject",
    "slug": "get-keys-at-path-from-nested-object",
    "type": "value",
    "module": "nested-menu",
    "isModuleResolved": true,
    "comments": [],
    "operationRelativeTypescriptFilePath": "src/getMarkdownPageInfo.ts",
    "classification": "operation",
    "isAbsolute": true,
    "isModuleFromMonorepo": true,
    "id": "ncchrdjvoiobubatbzyhcljs"
  },
  {
    "createdAt": 1667818163681,
    "updatedAt": 1667818163681,
    "deletedAt": 0,
    "createdFirstAt": 1667818163681,
    "name": "NestedPathObject",
    "slug": "nested-path-object",
    "type": "type",
    "hasGeneric": false,
    "module": "nested-menu",
    "isModuleResolved": true,
    "comments": [],
    "operationRelativeTypescriptFilePath": "src/getMarkdownPageInfo.ts",
    "classification": "operation",
    "isAbsolute": true,
    "isModuleFromMonorepo": true,
    "id": "uoudzovbceycxvpvnwrftbyp"
  },
  {
    "createdAt": 1667818163681,
    "updatedAt": 1667818163681,
    "deletedAt": 0,
    "createdFirstAt": 1667818163681,
    "name": "readMarkdownFileToModel",
    "slug": "read-markdown-file-to-model",
    "type": "value",
    "module": "read-markdown-file",
    "isModuleResolved": true,
    "comments": [],
    "operationRelativeTypescriptFilePath": "src/getMarkdownPageInfo.ts",
    "classification": "operation",
    "isAbsolute": true,
    "isModuleFromMonorepo": true,
    "id": "aypszdbpxljgjfeiojvaxoof"
  },
  {
    "createdAt": 1667818163681,
    "updatedAt": 1667818163681,
    "deletedAt": 0,
    "createdFirstAt": 1667818163681,
    "name": "MarkdownReaderPage",
    "slug": "markdown-reader-page",
    "type": "type",
    "hasGeneric": false,
    "module": "markdown-reader-types",
    "isModuleResolved": true,
    "comments": [],
    "operationRelativeTypescriptFilePath": "src/getMarkdownPageInfo.ts",
    "classification": "operation",
    "isAbsolute": true,
    "isModuleFromMonorepo": true,
    "id": "ijpmzdarvihrdmygktldwhdt"
  },
  {
    "createdAt": 1667818163681,
    "updatedAt": 1667818163681,
    "deletedAt": 0,
    "createdFirstAt": 1667818163681,
    "name": "WebMarkdownFile",
    "slug": "web-markdown-file",
    "type": "type",
    "hasGeneric": false,
    "module": "code-types",
    "isModuleResolved": true,
    "comments": [],
    "operationRelativeTypescriptFilePath": "src/getMarkdownPageInfo.ts",
    "classification": "operation",
    "isAbsolute": true,
    "isModuleFromMonorepo": true,
    "id": "xuctdvslmhaayuqgraqbkera"
  },
  {
    "createdAt": 1667818163681,
    "updatedAt": 1667818163681,
    "deletedAt": 0,
    "createdFirstAt": 1667818163681,
    "name": "makeRelative",
    "slug": "make-relative",
    "type": "value",
    "module": "get-path",
    "isModuleResolved": true,
    "comments": [],
    "operationRelativeTypescriptFilePath": "src/getMarkdownPageInfo.ts",
    "classification": "operation",
    "isAbsolute": true,
    "isModuleFromMonorepo": true,
    "id": "durnadzprwtyzrqrrtjntpen"
  },
  {
    "createdAt": 1667818163681,
    "updatedAt": 1667818163681,
    "deletedAt": 0,
    "createdFirstAt": 1667818163681,
    "name": "makeRelative",
    "slug": "make-relative",
    "type": "value",
    "module": "get-path",
    "isModuleResolved": true,
    "comments": [],
    "operationRelativeTypescriptFilePath": "src/getMarkdownReaderPages.ts",
    "classification": "operation",
    "isAbsolute": true,
    "isModuleFromMonorepo": true,
    "id": "jfdhtexqwmjiumwrcphqwrly"
  },
  {
    "createdAt": 1667818163681,
    "updatedAt": 1667818163681,
    "deletedAt": 0,
    "createdFirstAt": 1667818163681,
    "name": "MarkdownReaderPage",
    "slug": "markdown-reader-page",
    "type": "type",
    "hasGeneric": false,
    "module": "markdown-reader-types",
    "isModuleResolved": true,
    "comments": [],
    "operationRelativeTypescriptFilePath": "src/getMarkdownReaderPages.ts",
    "classification": "operation",
    "isAbsolute": true,
    "isModuleFromMonorepo": true,
    "id": "jtzgoatsujpybdhaytweimvf"
  },
  {
    "createdAt": 1667818163681,
    "updatedAt": 1667818163681,
    "deletedAt": 0,
    "createdFirstAt": 1667818163681,
    "name": "getPublicMarkdownFilePaths",
    "slug": "get-public-markdown-file-paths",
    "module": "./getPublicMarkdownFilePaths",
    "isModuleResolved": true,
    "comments": [],
    "operationRelativeTypescriptFilePath": "src/getMarkdownReaderPages.ts",
    "classification": "internal",
    "isAbsolute": false,
    "isModuleFromMonorepo": false,
    "id": "zammjpdaukzryvwsmiqjfphx"
  },
  {
    "createdAt": 1667818163682,
    "updatedAt": 1667818163682,
    "deletedAt": 0,
    "createdFirstAt": 1667818163682,
    "name": "removeExtensionsFromPath",
    "slug": "remove-extensions-from-path",
    "module": "./removeExtensionsFromPath",
    "isModuleResolved": true,
    "comments": [],
    "operationRelativeTypescriptFilePath": "src/getMarkdownReaderPages.ts",
    "classification": "internal",
    "isAbsolute": false,
    "isModuleFromMonorepo": false,
    "id": "pgpnvturkqogketpioopawnx"
  },
  {
    "createdAt": 1667818163682,
    "updatedAt": 1667818163682,
    "deletedAt": 0,
    "createdFirstAt": 1667818163682,
    "name": "writeToAssets",
    "slug": "write-to-assets",
    "type": "value",
    "module": "write-to-assets",
    "isModuleResolved": true,
    "comments": [],
    "operationRelativeTypescriptFilePath": "src/getMarkdownReaderQueryPaths.test.ts",
    "classification": "operation",
    "isAbsolute": true,
    "isModuleFromMonorepo": true,
    "id": "dqgruajdfxdierllfdhcoilm"
  },
  {
    "createdAt": 1667818163682,
    "updatedAt": 1667818163682,
    "deletedAt": 0,
    "createdFirstAt": 1667818163682,
    "name": "getMarkdownReaderQueryPaths",
    "slug": "get-markdown-reader-query-paths",
    "module": "./getMarkdownReaderQueryPaths",
    "isModuleResolved": true,
    "comments": [],
    "operationRelativeTypescriptFilePath": "src/getMarkdownReaderQueryPaths.test.ts",
    "classification": "internal",
    "isAbsolute": false,
    "isModuleFromMonorepo": false,
    "id": "ofsjoytmzdjsydysmfqfwsua"
  },
  {
    "createdAt": 1667818163682,
    "updatedAt": 1667818163682,
    "deletedAt": 0,
    "createdFirstAt": 1667818163682,
    "name": "getAllFoldersUntilFolder",
    "slug": "get-all-folders-until-folder",
    "type": "value",
    "module": "fs-util",
    "isModuleResolved": true,
    "comments": [],
    "operationRelativeTypescriptFilePath": "src/getMarkdownReaderQueryPaths.ts",
    "classification": "operation",
    "isAbsolute": true,
    "isModuleFromMonorepo": true,
    "id": "qdsnyowicrdwjvcpilwjexwn"
  },
  {
    "createdAt": 1667818163682,
    "updatedAt": 1667818163682,
    "deletedAt": 0,
    "createdFirstAt": 1667818163682,
    "name": "onlyUnique2",
    "slug": "only-unique-2",
    "type": "value",
    "module": "js-util",
    "isModuleResolved": true,
    "comments": [],
    "operationRelativeTypescriptFilePath": "src/getMarkdownReaderQueryPaths.ts",
    "classification": "operation",
    "isAbsolute": true,
    "isModuleFromMonorepo": true,
    "id": "tykbnatnttclfaiytmkrpacn"
  },
  {
    "createdAt": 1667818163682,
    "updatedAt": 1667818163682,
    "deletedAt": 0,
    "createdFirstAt": 1667818163682,
    "name": "trimSlashes",
    "slug": "trim-slashes",
    "type": "value",
    "module": "js-util",
    "isModuleResolved": true,
    "comments": [],
    "operationRelativeTypescriptFilePath": "src/getMarkdownReaderQueryPaths.ts",
    "classification": "operation",
    "isAbsolute": true,
    "isModuleFromMonorepo": true,
    "id": "ljwxgluptuiusiipwhdttzvr"
  },
  {
    "createdAt": 1667818163682,
    "updatedAt": 1667818163682,
    "deletedAt": 0,
    "createdFirstAt": 1667818163682,
    "name": "getAllMarkdownReaderPages",
    "slug": "get-all-markdown-reader-pages",
    "module": "./getAllMarkdownReaderPages",
    "isModuleResolved": true,
    "comments": [],
    "operationRelativeTypescriptFilePath": "src/getMarkdownReaderQueryPaths.ts",
    "classification": "internal",
    "isAbsolute": false,
    "isModuleFromMonorepo": false,
    "id": "zfvbfpgziwfckfosysqhzxmf"
  },
  {
    "createdAt": 1667818163682,
    "updatedAt": 1667818163682,
    "deletedAt": 0,
    "createdFirstAt": 1667818163682,
    "name": "getLastFolder",
    "slug": "get-last-folder",
    "type": "value",
    "module": "fs-util",
    "isModuleResolved": true,
    "comments": [],
    "operationRelativeTypescriptFilePath": "src/getOperationPages.ts",
    "classification": "operation",
    "isAbsolute": true,
    "isModuleFromMonorepo": true,
    "id": "snlxevptrggcfcifmvzeikxv"
  },
  {
    "createdAt": 1667818163682,
    "updatedAt": 1667818163682,
    "deletedAt": 0,
    "createdFirstAt": 1667818163682,
    "name": "path",
    "slug": "path",
    "type": "value",
    "module": "fs-util",
    "isModuleResolved": true,
    "comments": [],
    "operationRelativeTypescriptFilePath": "src/getOperationPages.ts",
    "classification": "operation",
    "isAbsolute": true,
    "isModuleFromMonorepo": true,
    "id": "izihrwwnnpsqjwtrlebulyoj"
  },
  {
    "createdAt": 1667818163682,
    "updatedAt": 1667818163682,
    "deletedAt": 0,
    "createdFirstAt": 1667818163682,
    "name": "getPathsWithOperations",
    "slug": "get-paths-with-operations",
    "type": "value",
    "module": "get-path",
    "isModuleResolved": true,
    "comments": [],
    "operationRelativeTypescriptFilePath": "src/getOperationPages.ts",
    "classification": "operation",
    "isAbsolute": true,
    "isModuleFromMonorepo": true,
    "id": "pfawppfxyjadyhmddnbzcevt"
  },
  {
    "createdAt": 1667818163682,
    "updatedAt": 1667818163682,
    "deletedAt": 0,
    "createdFirstAt": 1667818163682,
    "name": "isSensibleProject",
    "slug": "is-sensible-project",
    "type": "value",
    "module": "get-path",
    "isModuleResolved": true,
    "comments": [],
    "operationRelativeTypescriptFilePath": "src/getOperationPages.ts",
    "classification": "operation",
    "isAbsolute": true,
    "isModuleFromMonorepo": true,
    "id": "sefymeupjddwpzfcpvyjmlxh"
  },
  {
    "createdAt": 1667818163682,
    "updatedAt": 1667818163682,
    "deletedAt": 0,
    "createdFirstAt": 1667818163682,
    "name": "makeRelative",
    "slug": "make-relative",
    "type": "value",
    "module": "get-path",
    "isModuleResolved": true,
    "comments": [],
    "operationRelativeTypescriptFilePath": "src/getOperationPages.ts",
    "classification": "operation",
    "isAbsolute": true,
    "isModuleFromMonorepo": true,
    "id": "wwkiztgpuajcnjcxpfueqytr"
  },
  {
    "createdAt": 1667818163682,
    "updatedAt": 1667818163682,
    "deletedAt": 0,
    "createdFirstAt": 1667818163682,
    "name": "operations",
    "slug": "operations",
    "type": "value",
    "module": "sdk-operations",
    "isModuleResolved": true,
    "comments": [],
    "operationRelativeTypescriptFilePath": "src/getOperationPages.ts",
    "classification": "operation",
    "isAbsolute": true,
    "isModuleFromMonorepo": true,
    "id": "orxjkihlmpozagvaafoozvny"
  },
  {
    "createdAt": 1667818163682,
    "updatedAt": 1667818163682,
    "deletedAt": 0,
    "createdFirstAt": 1667818163682,
    "name": "MarkdownReaderPage",
    "slug": "markdown-reader-page",
    "type": "type",
    "hasGeneric": false,
    "module": "markdown-reader-types",
    "isModuleResolved": true,
    "comments": [],
    "operationRelativeTypescriptFilePath": "src/getOperationPages.ts",
    "classification": "operation",
    "isAbsolute": true,
    "isModuleFromMonorepo": true,
    "id": "tcocpsafwetepevhljcsfzxd"
  },
  {
    "createdAt": 1667818163682,
    "updatedAt": 1667818163682,
    "deletedAt": 0,
    "createdFirstAt": 1667818163682,
    "name": "mergeObjectsArray",
    "slug": "merge-objects-array",
    "type": "value",
    "module": "js-util",
    "isModuleResolved": true,
    "comments": [],
    "operationRelativeTypescriptFilePath": "src/getOperationPages.ts",
    "classification": "operation",
    "isAbsolute": true,
    "isModuleFromMonorepo": true,
    "id": "ehkzjxvnmwovcqgomvxxiecd"
  },
  {
    "createdAt": 1667818163682,
    "updatedAt": 1667818163682,
    "deletedAt": 0,
    "createdFirstAt": 1667818163682,
    "name": "notEmpty",
    "slug": "not-empty",
    "type": "value",
    "module": "js-util",
    "isModuleResolved": true,
    "comments": [],
    "operationRelativeTypescriptFilePath": "src/getOperationPages.ts",
    "classification": "operation",
    "isAbsolute": true,
    "isModuleFromMonorepo": true,
    "id": "bavzammswyyfztiafsxpjixm"
  },
  {
    "createdAt": 1667818163682,
    "updatedAt": 1667818163682,
    "deletedAt": 0,
    "createdFirstAt": 1667818163682,
    "name": "exploreOperationFolders",
    "slug": "explore-operation-folders",
    "type": "value",
    "module": "k-explore",
    "isModuleResolved": true,
    "comments": [],
    "operationRelativeTypescriptFilePath": "src/getOperationPages.ts",
    "classification": "operation",
    "isAbsolute": true,
    "isModuleFromMonorepo": true,
    "id": "yicnoawnwypsqkzhmymvzgfg"
  },
  {
    "createdAt": 1667818163682,
    "updatedAt": 1667818163682,
    "deletedAt": 0,
    "createdFirstAt": 1667818163682,
    "name": "BundleMarkdownReaderConfig",
    "slug": "bundle-markdown-reader-config",
    "type": "type",
    "hasGeneric": false,
    "module": "bundle-types",
    "isModuleResolved": true,
    "comments": [],
    "operationRelativeTypescriptFilePath": "src/getOperationPages.ts",
    "classification": "operation",
    "isAbsolute": true,
    "isModuleFromMonorepo": true,
    "id": "ypeurwgizklsektoofhgbqlh"
  },
  {
    "createdAt": 1667818163682,
    "updatedAt": 1667818163682,
    "deletedAt": 0,
    "createdFirstAt": 1667818163682,
    "name": "fs",
    "slug": "fs",
    "type": "value",
    "module": "fs-util",
    "isModuleResolved": true,
    "comments": [],
    "operationRelativeTypescriptFilePath": "src/getPublicMarkdownFilePaths.ts",
    "classification": "operation",
    "isAbsolute": true,
    "isModuleFromMonorepo": true,
    "id": "dkjexywjojvizgsasplnhtsw"
  },
  {
    "createdAt": 1667818163682,
    "updatedAt": 1667818163682,
    "deletedAt": 0,
    "createdFirstAt": 1667818163682,
    "name": "getProjectRoot",
    "slug": "get-project-root",
    "type": "value",
    "module": "get-path",
    "isModuleResolved": true,
    "comments": [],
    "operationRelativeTypescriptFilePath": "src/getPublicMarkdownFilePaths.ts",
    "classification": "operation",
    "isAbsolute": true,
    "isModuleFromMonorepo": true,
    "id": "asttfoahagohyiufyraabalg"
  },
  {
    "createdAt": 1667818163682,
    "updatedAt": 1667818163682,
    "deletedAt": 0,
    "createdFirstAt": 1667818163682,
    "name": "explore",
    "slug": "explore",
    "type": "value",
    "module": "k-explore",
    "isModuleResolved": true,
    "comments": [],
    "operationRelativeTypescriptFilePath": "src/getPublicMarkdownFilePaths.ts",
    "classification": "operation",
    "isAbsolute": true,
    "isModuleFromMonorepo": true,
    "id": "oystuddifbxqrlrgvagneqml"
  },
  {
    "createdAt": 1667818163683,
    "updatedAt": 1667818163683,
    "deletedAt": 0,
    "createdFirstAt": 1667818163683,
    "name": "parseFrontmatterMarkdownString",
    "slug": "parse-frontmatter-markdown-string",
    "type": "value",
    "module": "markdown-parse-js",
    "isModuleResolved": true,
    "comments": [],
    "operationRelativeTypescriptFilePath": "src/getPublicMarkdownFilePaths.ts",
    "classification": "operation",
    "isAbsolute": true,
    "isModuleFromMonorepo": true,
    "id": "cafqlrnkidnmtayyzygxjpwh"
  },
  {
    "createdAt": 1667818163683,
    "updatedAt": 1667818163683,
    "deletedAt": 0,
    "createdFirstAt": 1667818163683,
    "name": "Frontmatter",
    "slug": "frontmatter",
    "type": "type",
    "hasGeneric": false,
    "module": "matter-types",
    "isModuleResolved": true,
    "comments": [],
    "operationRelativeTypescriptFilePath": "src/getPublicMarkdownFilePaths.ts",
    "classification": "operation",
    "isAbsolute": true,
    "isModuleFromMonorepo": true,
    "id": "dmjtyyhisowywosmdqywinjf"
  },
  {
    "createdAt": 1667818163683,
    "updatedAt": 1667818163683,
    "deletedAt": 0,
    "createdFirstAt": 1667818163683,
    "name": "MarkdownReaderPage",
    "slug": "markdown-reader-page",
    "type": "type",
    "hasGeneric": false,
    "module": "markdown-reader-types",
    "isModuleResolved": true,
    "comments": [],
    "operationRelativeTypescriptFilePath": "src/getTodoPages.ts",
    "classification": "operation",
    "isAbsolute": true,
    "isModuleFromMonorepo": true,
    "id": "swgitjmawuymykrtxutyniaa"
  },
  {
    "createdAt": 1667818163683,
    "updatedAt": 1667818163683,
    "deletedAt": 0,
    "createdFirstAt": 1667818163683,
    "name": "findAllTodoFolderPaths",
    "slug": "find-all-todo-folder-paths",
    "type": "value",
    "module": "k-explore",
    "isModuleResolved": true,
    "comments": [],
    "operationRelativeTypescriptFilePath": "src/getTodoPages.ts",
    "classification": "operation",
    "isAbsolute": true,
    "isModuleFromMonorepo": true,
    "id": "rtlefmvxohsthzgelabyqpxy"
  },
  {
    "createdAt": 1667818163683,
    "updatedAt": 1667818163683,
    "deletedAt": 0,
    "createdFirstAt": 1667818163683,
    "name": "getMarkdownReaderPages",
    "slug": "get-markdown-reader-pages",
    "module": "./getMarkdownReaderPages",
    "isModuleResolved": true,
    "comments": [],
    "operationRelativeTypescriptFilePath": "src/getTodoPages.ts",
    "classification": "internal",
    "isAbsolute": false,
    "isModuleFromMonorepo": false,
    "id": "nsnufmkskmbkgogeqswvngoy"
  },
  {
    "createdAt": 1667818163683,
    "updatedAt": 1667818163683,
    "deletedAt": 0,
    "createdFirstAt": 1667818163683,
    "name": "getProjectRoot",
    "slug": "get-project-root",
    "type": "value",
    "module": "get-path",
    "isModuleResolved": true,
    "comments": [],
    "operationRelativeTypescriptFilePath": "src/getTodoPages.ts",
    "classification": "operation",
    "isAbsolute": true,
    "isModuleFromMonorepo": true,
    "id": "lzaxekswlaubpiglkhofkckl"
  },
  {
    "createdAt": 1667818163683,
    "updatedAt": 1667818163683,
    "deletedAt": 0,
    "createdFirstAt": 1667818163683,
    "name": "getRootPath",
    "slug": "get-root-path",
    "type": "value",
    "module": "get-path",
    "isModuleResolved": true,
    "comments": [],
    "operationRelativeTypescriptFilePath": "src/getTodoPages.ts",
    "classification": "operation",
    "isAbsolute": true,
    "isModuleFromMonorepo": true,
    "id": "judgnnpsetbxfhevbsyenisn"
  },
  {
    "createdAt": 1667818163683,
    "updatedAt": 1667818163683,
    "deletedAt": 0,
    "createdFirstAt": 1667818163683,
    "name": "replaceLastOccurence",
    "slug": "replace-last-occurence",
    "type": "value",
    "module": "js-util",
    "isModuleResolved": true,
    "comments": [],
    "operationRelativeTypescriptFilePath": "src/getTodoPages.ts",
    "classification": "operation",
    "isAbsolute": true,
    "isModuleFromMonorepo": true,
    "id": "pghkgmnhoibhfwpabmmghnow"
  },
  {
    "createdAt": 1667818163683,
    "updatedAt": 1667818163683,
    "deletedAt": 0,
    "createdFirstAt": 1667818163683,
    "name": "GetStaticPaths",
    "slug": "get-static-paths",
    "module": "next",
    "isModuleResolved": true,
    "comments": [],
    "operationRelativeTypescriptFilePath": "src/markdownReaderGetStaticPaths.ts",
    "classification": "package",
    "isAbsolute": true,
    "isModuleFromMonorepo": false,
    "id": "spyulwebrsgoacruznwezrsr"
  },
  {
    "createdAt": 1667818163683,
    "updatedAt": 1667818163683,
    "deletedAt": 0,
    "createdFirstAt": 1667818163683,
    "name": "GetStaticPathsContext",
    "slug": "get-static-paths-context",
    "module": "next",
    "isModuleResolved": true,
    "comments": [],
    "operationRelativeTypescriptFilePath": "src/markdownReaderGetStaticPaths.ts",
    "classification": "package",
    "isAbsolute": true,
    "isModuleFromMonorepo": false,
    "id": "aetrggqvsemocbkmunddwhij"
  },
  {
    "createdAt": 1667818163683,
    "updatedAt": 1667818163683,
    "deletedAt": 0,
    "createdFirstAt": 1667818163683,
    "name": "getMarkdownReaderQueryPaths",
    "slug": "get-markdown-reader-query-paths",
    "module": "./getMarkdownReaderQueryPaths",
    "isModuleResolved": true,
    "comments": [],
    "operationRelativeTypescriptFilePath": "src/markdownReaderGetStaticPaths.ts",
    "classification": "internal",
    "isAbsolute": false,
    "isModuleFromMonorepo": false,
    "id": "guwybbvhjeapoktphfdkwsbj"
  },
  {
    "createdAt": 1667818163683,
    "updatedAt": 1667818163683,
    "deletedAt": 0,
    "createdFirstAt": 1667818163683,
    "name": "MarkdownReaderPageProps",
    "slug": "markdown-reader-page-props",
    "type": "type",
    "hasGeneric": false,
    "module": "markdown-reader-types",
    "isModuleResolved": true,
    "comments": [],
    "operationRelativeTypescriptFilePath": "src/markdownReaderGetStaticProps.ts",
    "classification": "operation",
    "isAbsolute": true,
    "isModuleFromMonorepo": true,
    "id": "zjizextslinrzmdfbfwuzcer"
  },
  {
    "createdAt": 1667818163683,
    "updatedAt": 1667818163683,
    "deletedAt": 0,
    "createdFirstAt": 1667818163683,
    "name": "GetStaticPropsContext",
    "slug": "get-static-props-context",
    "module": "next",
    "isModuleResolved": true,
    "comments": [],
    "operationRelativeTypescriptFilePath": "src/markdownReaderGetStaticProps.ts",
    "classification": "package",
    "isAbsolute": true,
    "isModuleFromMonorepo": false,
    "id": "wtspvaqxiwfzgsdmcbkvbjfu"
  },
  {
    "createdAt": 1667818163683,
    "updatedAt": 1667818163683,
    "deletedAt": 0,
    "createdFirstAt": 1667818163683,
    "name": "getProjectRoot",
    "slug": "get-project-root",
    "type": "value",
    "module": "get-path",
    "isModuleResolved": true,
    "comments": [],
    "operationRelativeTypescriptFilePath": "src/markdownReaderGetStaticProps.ts",
    "classification": "operation",
    "isAbsolute": true,
    "isModuleFromMonorepo": true,
    "id": "tzyfqecvjphbynozqhvcyqrd"
  },
  {
    "createdAt": 1667818163683,
    "updatedAt": 1667818163683,
    "deletedAt": 0,
    "createdFirstAt": 1667818163683,
    "name": "readJsonFile",
    "slug": "read-json-file",
    "type": "value",
    "module": "read-json-file",
    "isModuleResolved": true,
    "comments": [],
    "operationRelativeTypescriptFilePath": "src/markdownReaderGetStaticProps.ts",
    "classification": "operation",
    "isAbsolute": true,
    "isModuleFromMonorepo": true,
    "id": "vqiwemfikhmuhgwpgdcqtuku"
  },
  {
    "createdAt": 1667818163683,
    "updatedAt": 1667818163683,
    "deletedAt": 0,
    "createdFirstAt": 1667818163683,
    "name": "queryPathsArrayToNestedPathObject",
    "slug": "query-paths-array-to-nested-path-object",
    "type": "value",
    "module": "nested-menu",
    "isModuleResolved": true,
    "comments": [],
    "operationRelativeTypescriptFilePath": "src/markdownReaderGetStaticProps.ts",
    "classification": "operation",
    "isAbsolute": true,
    "isModuleFromMonorepo": true,
    "id": "rzlboycvrvblhpzdwxqoduex"
  },
  {
    "createdAt": 1667818163683,
    "updatedAt": 1667818163683,
    "deletedAt": 0,
    "createdFirstAt": 1667818163683,
    "name": "getQueryPath",
    "slug": "get-query-path",
    "type": "value",
    "module": "markdown-reader-functions-js",
    "isModuleResolved": true,
    "comments": [],
    "operationRelativeTypescriptFilePath": "src/markdownReaderGetStaticProps.ts",
    "classification": "operation",
    "isAbsolute": true,
    "isModuleFromMonorepo": true,
    "id": "ucuvlzpzybbzfyuzkgfqqltz"
  },
  {
    "createdAt": 1667818163683,
    "updatedAt": 1667818163683,
    "deletedAt": 0,
    "createdFirstAt": 1667818163683,
    "name": "getFolderExplorationInfo",
    "slug": "get-folder-exploration-info",
    "module": "./getFolderExplorationInfo",
    "isModuleResolved": true,
    "comments": [],
    "operationRelativeTypescriptFilePath": "src/markdownReaderGetStaticProps.ts",
    "classification": "internal",
    "isAbsolute": false,
    "isModuleFromMonorepo": false,
    "id": "hcvupmnlrsrnqirxreuvfjqb"
  },
  {
    "createdAt": 1667818163683,
    "updatedAt": 1667818163683,
    "deletedAt": 0,
    "createdFirstAt": 1667818163683,
    "name": "getAllMarkdownReaderPages",
    "slug": "get-all-markdown-reader-pages",
    "module": "./getAllMarkdownReaderPages",
    "isModuleResolved": true,
    "comments": [],
    "operationRelativeTypescriptFilePath": "src/markdownReaderGetStaticProps.ts",
    "classification": "internal",
    "isAbsolute": false,
    "isModuleFromMonorepo": false,
    "id": "vnkwzfvmcxsymhcpcaizysul"
  },
  {
    "createdAt": 1667818163683,
    "updatedAt": 1667818163683,
    "deletedAt": 0,
    "createdFirstAt": 1667818163683,
    "name": "getMarkdownPageInfo",
    "slug": "get-markdown-page-info",
    "module": "./getMarkdownPageInfo",
    "isModuleResolved": true,
    "comments": [],
    "operationRelativeTypescriptFilePath": "src/markdownReaderGetStaticProps.ts",
    "classification": "internal",
    "isAbsolute": false,
    "isModuleFromMonorepo": false,
    "id": "tgsvitqnxhtmnszlbcslmojr"
  },
  {
    "createdAt": 1667818163683,
    "updatedAt": 1667818163683,
    "deletedAt": 0,
    "createdFirstAt": 1667818163683,
    "name": "getAugmentedWordObject",
    "slug": "get-augmented-word-object",
    "type": "value",
    "module": "augmented-words",
    "isModuleResolved": true,
    "comments": [],
    "operationRelativeTypescriptFilePath": "src/markdownReaderGetStaticProps.ts",
    "classification": "operation",
    "isAbsolute": true,
    "isModuleFromMonorepo": true,
    "id": "jiatbryteodpvytxfgmroowi"
  },
  {
    "createdAt": 1667818163683,
    "updatedAt": 1667818163683,
    "deletedAt": 0,
    "createdFirstAt": 1667818163683,
    "name": "PackageJson",
    "slug": "package-json",
    "type": "type",
    "hasGeneric": false,
    "module": "code-types",
    "isModuleResolved": true,
    "comments": [],
    "operationRelativeTypescriptFilePath": "src/markdownReaderGetStaticProps.ts",
    "classification": "operation",
    "isAbsolute": true,
    "isModuleFromMonorepo": true,
    "id": "ljxatgxomxvjqazhkqhlyyfu"
  },
  {
    "createdAt": 1667818163683,
    "updatedAt": 1667818163683,
    "deletedAt": 0,
    "createdFirstAt": 1667818163683,
    "name": "path",
    "slug": "path",
    "type": "value",
    "module": "fs-util",
    "isModuleResolved": true,
    "comments": [],
    "operationRelativeTypescriptFilePath": "src/markdownReaderGetStaticProps.ts",
    "classification": "operation",
    "isAbsolute": true,
    "isModuleFromMonorepo": true,
    "id": "budcsipwegccpvwqulehglmc"
  },
  {
    "createdAt": 1667818163684,
    "updatedAt": 1667818163684,
    "deletedAt": 0,
    "createdFirstAt": 1667818163684,
    "name": "BundleConfig",
    "slug": "bundle-config",
    "type": "type",
    "hasGeneric": false,
    "module": "bundle-types",
    "isModuleResolved": true,
    "comments": [],
    "operationRelativeTypescriptFilePath": "src/markdownReaderGetStaticProps.ts",
    "classification": "operation",
    "isAbsolute": true,
    "isModuleFromMonorepo": true,
    "id": "xxstgobmijalyerzoylqwdxw"
  },
  {
    "createdAt": 1667818163684,
    "updatedAt": 1667818163684,
    "deletedAt": 0,
    "createdFirstAt": 1667818163684,
    "name": "removeExtensionsFromPath",
    "slug": "remove-extensions-from-path",
    "module": "./removeExtensionsFromPath",
    "isModuleResolved": true,
    "comments": [],
    "operationRelativeTypescriptFilePath": "src/removeExtensionsFromPath.test.ts",
    "classification": "internal",
    "isAbsolute": false,
    "isModuleFromMonorepo": false,
    "id": "hhaicmhyvplopvkvfbziphlu"
  },
  {
    "createdAt": 1667818163684,
    "updatedAt": 1667818163684,
    "deletedAt": 0,
    "createdFirstAt": 1667818163684,
    "name": "trimSlashes",
    "slug": "trim-slashes",
    "type": "value",
    "module": "js-util",
    "isModuleResolved": true,
    "comments": [],
    "operationRelativeTypescriptFilePath": "src/removeExtensionsFromPath.ts",
    "classification": "operation",
    "isAbsolute": true,
    "isModuleFromMonorepo": true,
    "id": "vshxocqzzyjnqiavkbepzdzw"
  },
  {
    "createdAt": 1667818163684,
    "updatedAt": 1667818163684,
    "deletedAt": 0,
    "createdFirstAt": 1667818163684,
    "name": "removeNumberPrefix",
    "slug": "remove-number-prefix",
    "module": "./removeNumberPrefix",
    "isModuleResolved": true,
    "comments": [],
    "operationRelativeTypescriptFilePath": "src/removeExtensionsFromPath.ts",
    "classification": "internal",
    "isAbsolute": false,
    "isModuleFromMonorepo": false,
    "id": "zznqbdcdndievtzkixnwuupl"
  },
  {
    "createdAt": 1667818163684,
    "updatedAt": 1667818163684,
    "deletedAt": 0,
    "createdFirstAt": 1667818163684,
    "name": "copyStaticAssets",
    "slug": "copy-static-assets",
    "module": "../copyStaticAssets",
    "isModuleResolved": true,
    "comments": [],
    "operationRelativeTypescriptFilePath": "src/cli/copyStaticAssets.cli.ts",
    "classification": "internal",
    "isAbsolute": false,
    "isModuleFromMonorepo": false,
    "id": "ymnrpngngmpwfhsxqfgapwof"
  },
  {
    "createdAt": 1667818163684,
    "updatedAt": 1667818163684,
    "deletedAt": 0,
    "createdFirstAt": 1667818163684,
    "name": "getAllMarkdownReaderPages",
    "slug": "get-all-markdown-reader-pages",
    "module": "../getAllMarkdownReaderPages",
    "isModuleResolved": true,
    "comments": [],
    "operationRelativeTypescriptFilePath": "src/cli/copyStaticAssets.cli.ts",
    "classification": "internal",
    "isAbsolute": false,
    "isModuleFromMonorepo": false,
    "id": "vchrxtvjmdwenwvsupsnlszu"
  }
]